Workbook
Name \z: '[1]COAT&WRAP-QIOT-#3'!#REF!
Name ________________________________________________________cao1: #REF!
Name ________________________________________________________cao1: #REF!
Name ________________________________________________________cao2: #REF!
Name ________________________________________________________cao2: #REF!
Name ________________________________________________________cao3: #REF!
Name ________________________________________________________cao3: #REF!
Name ________________________________________________________cao4: #REF!
Name ________________________________________________________cao4: #REF!
Name ________________________________________________________cao5: #REF!
Name ________________________________________________________cao5: #REF!
Name ________________________________________________________cao6: #REF!
Name ________________________________________________________cao6: #REF!
Name ________________________________________________________dai1: #REF!
Name ________________________________________________________dai1: #REF!
Name ________________________________________________________dai2: #REF!
Name ________________________________________________________dai2: #REF!
Name ________________________________________________________dai3: #REF!
Name ________________________________________________________dai3: #REF!
Name ________________________________________________________dai4: #REF!
Name ________________________________________________________dai4: #REF!
Name ________________________________________________________dai5: #REF!
Name ________________________________________________________dai5: #REF!
Name ________________________________________________________dai6: #REF!
Name ________________________________________________________dai6: #REF!
Name ________________________________________________________dan1: #REF!
Name ________________________________________________________dan1: #REF!
Name ________________________________________________________dan2: #REF!
Name ________________________________________________________dan2: #REF!
Name ________________________________________________________phi10: #REF!
Name ________________________________________________________phi10: #REF!
Name ________________________________________________________phi12: #REF!
Name ________________________________________________________phi12: #REF!
Name ________________________________________________________phi14: #REF!
Name ________________________________________________________phi14: #REF!
Name ________________________________________________________phi16: #REF!
Name ________________________________________________________phi16: #REF!
Name ________________________________________________________phi18: #REF!
Name ________________________________________________________phi18: #REF!
Name ________________________________________________________phi20: #REF!
Name ________________________________________________________phi20: #REF!
Name ________________________________________________________phi22: #REF!
Name ________________________________________________________phi22: #REF!
Name ________________________________________________________phi25: #REF!
Name ________________________________________________________phi25: #REF!
Name ________________________________________________________phi28: #REF!
Name ________________________________________________________phi28: #REF!
Name ________________________________________________________phi6: #REF!
Name ________________________________________________________phi6: #REF!
Name ________________________________________________________phi8: #REF!
Name ________________________________________________________phi8: #REF!
Name ________________________________________________________slg1: #REF!
Name ________________________________________________________slg1: #REF!
Name ________________________________________________________slg2: #REF!
Name ________________________________________________________slg2: #REF!
Name ________________________________________________________slg3: #REF!
Name ________________________________________________________slg3: #REF!
Name ________________________________________________________slg4: #REF!
Name ________________________________________________________slg4: #REF!
Name ________________________________________________________slg5: #REF!

Sheet INV
A1: ADVANCE KNITTING VIETNAM CO., LTD
A2: LOT F5-4, THUAN DAO INDUSTRIAL PARK'S EXPANSION PHASE, LONG CANG COMMUNE, TAY NINH PROVINCE, VIETNAM
A3: TEL:(+84)-723-643-733; (+84)-723-643-734 FAX: (+84)-723-643-735
A4: COMMERCIAL INVOICE
A5: Shipper / Exporter: | F5: No. / Date of Invoice :
A6: ADVANCE KNITTING VIETNAM CO.,LTD | F6: =DPL!J7 -> AK/GDI-20260010 | G6: =DPL!L7 -> 46125
A7: LOT F5-4, THUAN DAO INDUSTRIAL PARK'S EXPANSION PHASE, LONG CANG | F7: Contract No. / Date:
A8: COMMUNE, TAY NINH PROVINCE, VIETNAM
A9: TEL:(+84)-723-643-733; (+84)-723-643-734 FAX: (+84)-723-643-735 | F9: =DPL!J12 -> AK/GDI/CT-202602 | G9: =DPL!L12 -> 46035
A10: Buyer:
A11: GDI HK LIMITED
A12: FLAT H, 2/F MANSION INDUSTRIAL BUILDING,
A13: 8 A KUNG NGAM VILLAGE LANE, SHAU KEI WAN, HONG KONG
A15: Consignee: | F15: Term of Delivery: CFR JAKARTA INDONESIA
A16: =DPL!A17 -> PT NIRWANA ALABARE GARMENT | F16: Origin of Goods: Vietnam
A17: =DPL!A18 -> JL. RAYA RANCAEKEK - MAJALAYA , NO.289, DESA SOLOKAN JERUK,
A18: =DPL!A19 -> KECAMATAN SOLOKAN JERUK, KABUPATEN BANDUNG JAWA BARAT
A19: =DPL!A20 -> 40382, INDONESIA
A20: =DPL!A21 -> TAX ID :0745 4069 2644 4000
A23: Loading: | C23: Discharge:
A24: =DPL!A24 -> HO CHI MINH | C24: =DPL!E24 -> JAKARTA
A27: FLIGHT NO: | C27: Delivery date | D27: ETA:
C28: =DPL!C27 -> 46126 | D28: =DPL!E27 -> 46128 | F28: Term of Payment: By T/T
A29: PO | B29: REF# | C29: ITEM NO | D29: DESCRIPTION OF GOODS | E29: COLOR | F29: SIZE | G29: QUANTITY | H29: Unit | I29: UNIT PRICE (USD) | J29: AMOUNT (USD)
A30: SIOB260205005 | B30: KD00397 265K0051-1ST LOT/ S/416363 | C30: 1051120 | D30: 60% BETTER COTTON (BCI) 40% POLYESTER 32S/1x4 PLY FLAT KNIT COLLAR | E30: CALLA LILY 451漂白 | F30: XS | G30: 2400 | H30: PCS | I30: 0.165 | J30: =ROUND(G30*I30,2) -> 396
A31: SIOB260205005 | B31: KD00397 265K0051-1ST LOT/ S/416363 | C31: 1051120 | D31: 60% BETTER COTTON (BCI) 40% POLYESTER 32S/1x4 PLY FLAT KNIT COLLAR | E31: CALLA LILY 451漂白 | F31: S | G31: 3500 | H31: PCS | I31: 0.165 | J31: =ROUND(G31*I31,2) -> 577.5
A32: SIOB260205005 | B32: KD00397 265K0051-1ST LOT/ S/416363 | C32: 1051120 | D32: 60% BETTER COTTON (BCI) 40% POLYESTER 32S/1x4 PLY FLAT KNIT COLLAR | E32: CALLA LILY 451漂白 | F32: M | G32: 2200 | H32: PCS | I32: 0.165 | J32: =ROUND(G32*I32,2) -> 363
A33: SIOB260205005 | B33: KD00397 265K0051-1ST LOT/ S/416363 | C33: 1051120 | D33: 60% BETTER COTTON (BCI) 40% POLYESTER 32S/1x4 PLY FLAT KNIT COLLAR | E33: CALLA LILY 451漂白 | F33: L | G33: 4648 | H33: PCS | I33: 0.165 | J33: =ROUND(G33*I33,2) -> 766.92
A34: SIOB260205005 | B34: KD00397 265K0051-1ST LOT/ S/416363 | C34: 1051120 | D34: 60% BETTER COTTON (BCI) 40% POLYESTER 32S/1x4 PLY FLAT KNIT COLLAR | E34: CALLA LILY 451漂白 | F34: XL | G34: 3122 | H34: PCS | I34: 0.165 | J34: =ROUND(G34*I34,2) -> 515.13
A35: SIOB260205005 | B35: KD00397 265K0051-1ST LOT/ S/416363 | C35: 1051120 | D35: 60% BETTER COTTON (BCI) 40% POLYESTER 32S/1x4 PLY FLAT KNIT COLLAR | E35: CALLA LILY 451漂白 | F35: XXL | G35: 2600 | H35: PCS | I35: 0.165 | J35: =ROUND(G35*I35,2) -> 429
A36: SIOB260205005 | B36: KD00397 265K0051-1ST LOT/ S/416363 | C36: 1051120 | D36: 60% BETTER COTTON (BCI) 40% POLYESTER 32S/1x4 PLY FLAT KNIT COLLAR | E36: CALLA LILY 451漂白 | F36: XL HUSKY | G36: 1708 | H36: PCS | I36: 0.165 | J36: =ROUND(G36*I36,2) -> 281.82
A37: SIOB260205005 | B37: KD00397 265K0051-1ST LOT/ S/416363 | C37: 1051120 | D37: 60% BETTER COTTON (BCI) 40% POLYESTER 32S/1x4 PLY FLAT KNIT COLLAR | E37: CALLA LILY 451漂白 | F37: XXL HUSKY | G37: 2337 | H37: PCS | I37: 0.165 | J37: =ROUND(G37*I37,2) -> 385.61
A38: SIOB260205005 | B38: KD00397 265K0051-1ST LOT/ S/416363 | C38: 1051120 | D38: 60% BETTER COTTON (BCI) 40% POLYESTER 32S/1x4 PLY FLAT KNIT COLLAR | E38: MONET BLUE 744油画蓝 | F38: XXL | G38: 292 | H38: PCS | I38: 0.17 | J38: =ROUND(G38*I38,2) -> 49.64
A39: SIOB260205005 | B39: KD00397 265K0051-1ST LOT/ S/416363 | C39: 1051120 | D39: 60% BETTER COTTON (BCI) 40% POLYESTER 32S/1x4 PLY FLAT KNIT COLLAR | E39: MONET BLUE 744油画蓝 | F39: XXL HUSKY | G39: 189 | H39: PCS | I39: 0.17 | J39: =ROUND(G39*I39,2) -> 32.13
A40: SIOB260205005 | B40: KD00397 265K0051-1ST LOT/ S/416363 | C40: 1051120 | D40: 60% BETTER COTTON (BCI) 40% POLYESTER 32S/1x4 PLY FLAT KNIT COLLAR | E40: RED TAPE 729正红色 | F40: XS | G40: 1705 | H40: PCS | I40: 0.17 | J40: =ROUND(G40*I40,2) -> 289.85
A41: SIOB260205005 | B41: KD00397 265K0051-1ST LOT/ S/416363 | C41: 1051120 | D41: 60% BETTER COTTON (BCI) 40% POLYESTER 32S/1x4 PLY FLAT KNIT COLLAR | E41: RED TAPE 729正红色 | F41: S | G41: 1556 | H41: PCS | I41: 0.17 | J41: =ROUND(G41*I41,2) -> 264.52
... A53: SIOB260205012 | B53: KD00400 265K0052 -1ST LOT/ S/767468 | C53: 1051120 | D53: 60% BETTER COTTON (BCI) 40% POLYESTER 32S/1x4 PLY FLAT KNIT COLLAR | E53: CALLA LILY 451漂白 | F53: XXL HUSKY | G53: 357 | H53: PCS | I53: 0.165 | J53: =ROUND(G53*I53,2) -> 58.91
D54: TOTAL | G54: =SUM(G30:G53) -> 34826 | H54: PCS | I54: USD | J54: =SUM(J30:J53) -> 5802.09
A55: SAY: | B55: US DOLLAR FIVE THOUSAND EIGHT HUNDRED TWO AND NINE CENTS ONLY.
A56: PLEASE MAKE PAYMENT TO OUR BANK : JOINT STOCK COMMERCIAL BANK FOR FOREIGN TRADE OF VIET NAM (VIETCOMBANK)
A57: ACCOUNT NO : 0631370457237
I58: ADVANCE KNITTING VIETNAM CO., LTD
I59: Signature, full name, seal

Sheet DPL
A1: ADVANCE KNITTING VIETNAM CO., LTD
A2: LOT F5-4, THUAN DAO INDUSTRIAL PARK'S EXPANSION PHASE, LONG CANG COMMUNE, TAY NINH PROVINCE, VIETNAM
A3: TEL:(+84)-723-643-733; (+84)-723-643-734 FAX: (+84)-723-643-735
A4: PACKING LIST
A6: Shipper / Exporter: | J6: No. / Date of Packing List :
A7: ADVANCE KNITTING VIETNAM CO.,LTD | J7: AK/GDI-20260010 | L7: 46125
A8: LOT F5-4, THUAN DAO INDUSTRIAL PARK'S EXPANSION PHASE, LONG CANG COMMUNE, TAY NINH PROVINCE, VIETNAM | J8: No. / Date of Invoice :
A9: TEL:(+84)-723-643-733; (+84)-723-643-734 FAX: (+84)-723-643-735 | J9: =J7 -> AK/GDI-20260010 | L9: =L7 -> 46125
A10: Buyer:
A11: GDI HK LIMITED | J11: No. / Date of Contract :
A12: FLAT H, 2/F MANSION INDUSTRIAL BUILDING, | J12: AK/GDI/CT-202602 | L12: 46035
A13: 8 A KUNG NGAM VILLAGE LANE, SHAU KEI WAN, HONG KONG
A16: Consignee:
A17: PT NIRWANA ALABARE GARMENT
A18: JL. RAYA RANCAEKEK - MAJALAYA , NO.289, DESA SOLOKAN JERUK,
A19: KECAMATAN SOLOKAN JERUK, KABUPATEN BANDUNG JAWA BARAT
A20: 40382, INDONESIA
A21: TAX ID :0745 4069 2644 4000
A23: Loading: | E23: Discharge: | J23: Term of Delivery: | L23: CFR JAKARTA INDONESIA
A24: HO CHI MINH | E24: JAKARTA | J24: Origin of Goods: | L24: Vietnam
J25: PO No:
A26: FLIGHT NO: | C26: Delivery date | E26: ETA:
C27: 46126 | E27: 46128 | J27: Term of Payment: | K27: By T/T
C28: POLYESTER KNITTED RIB
A29: CARTON NO | B29: PO | C29: DESCRIPTION OF GOODS | D29: ITEM NO | E29: COLOR | F29: SIZE | H29: REF# | I29: Q'TY | J29: UNIT | K29: Net Weight (Kgs) | L29: Gross Weight (Kgs) | M29: Measurements (CBM)
A30: 1 | B30: SIOB260205005 | C30: 60% BETTER COTTON (BCI) 40% POLYESTER 32S/1x4 PLY FLAT KNIT COLLAR | D30: 1051120 | E30: CALLA LILY 451漂白 | F30: S | G30: 13-3/4"x3.375” | H30: KD00397 265K0051-1ST LOT/ S/416363 | I30: 1200 | J30: PCS | K30: =L30-1.45 -> 24.85 | L30: 26.3 | M30: 0.11 | N30: ĐƠN 10 | O30: =B30&E30&F30 -> SIOB260205005CALLA LILY 451漂白S
A31: 2 | B31: SIOB260205005 | C31: 60% BETTER COTTON (BCI) 40% POLYESTER 32S/1x4 PLY FLAT KNIT COLLAR | D31: 1051120 | E31: CALLA LILY 451漂白 | F31: S | G31: 13-3/4"x3.375” | H31: KD00397 265K0051-1ST LOT/ S/416363 | I31: 1200 | J31: PCS | K31: =L31-1.45 -> 25.1 | L31: 26.55 | M31: 0.11 | O31: =B31&E31&F31 -> SIOB260205005CALLA LILY 451漂白S
A32: 3 | B32: SIOB260205005 | C32: 60% BETTER COTTON (BCI) 40% POLYESTER 32S/1x4 PLY FLAT KNIT COLLAR | D32: 1051120 | E32: CALLA LILY 451漂白 | F32: S | G32: 13-3/4"x3.375” | H32: KD00397 265K0051-1ST LOT/ S/416363 | I32: 1100 | J32: PCS | K32: =L32-1.45 -> 22.95 | L32: 24.4 | M32: 0.11 | O32: =B32&E32&F32 -> SIOB260205005CALLA LILY 451漂白S
A33: 4 | B33: SIOB260205005 | C33: 60% BETTER COTTON (BCI) 40% POLYESTER 32S/1x4 PLY FLAT KNIT COLLAR | D33: 1051120 | E33: CALLA LILY 451漂白 | F33: M | G33: 14-1/4"x3.625” | H33: KD00397 265K0051-1ST LOT/ S/416363 | I33: 1100 | J33: PCS | K33: =L33-1.45 -> 25.55 | L33: 27 | M33: 0.11 | O33: =B33&E33&F33 -> SIOB260205005CALLA LILY 451漂白M
A34: 5 | B34: SIOB260205005 | C34: 60% BETTER COTTON (BCI) 40% POLYESTER 32S/1x4 PLY FLAT KNIT COLLAR | D34: 1051120 | E34: CALLA LILY 451漂白 | F34: M | G34: 14-1/4"x3.625” | H34: KD00397 265K0051-1ST LOT/ S/416363 | I34: 1100 | J34: PCS | K34: =L34-1.45 -> 25.6 | L34: 27.05 | M34: 0.11 | O34: =B34&E34&F34 -> SIOB260205005CALLA LILY 451漂白M
A35: 6 | B35: SIOB260205005 | C35: 60% BETTER COTTON (BCI) 40% POLYESTER 32S/1x4 PLY FLAT KNIT COLLAR | D35: 1051120 | E35: CALLA LILY 451漂白 | F35: L | G35: 15"x3.625” | H35: KD00397 265K0051-1ST LOT/ S/416363 | I35: 1100 | J35: PCS | K35: =L35-1.45 -> 26.7 | L35: 28.15 | M35: 0.11 | O35: =B35&E35&F35 -> SIOB260205005CALLA LILY 451漂白L
A36: 7 | B36: SIOB260205005 | C36: 60% BETTER COTTON (BCI) 40% POLYESTER 32S/1x4 PLY FLAT KNIT COLLAR | D36: 1051120 | E36: CALLA LILY 451漂白 | F36: L | G36: 15"x3.625” | H36: KD00397 265K0051-1ST LOT/ S/416363 | I36: 1100 | J36: PCS | K36: =L36-1.45 -> 26.7 | L36: 28.15 | M36: 0.11 | O36: =B36&E36&F36 -> SIOB260205005CALLA LILY 451漂白L
A37: 8 | B37: SIOB260205005 | C37: 60% BETTER COTTON (BCI) 40% POLYESTER 32S/1x4 PLY FLAT KNIT COLLAR | D37: 1051120 | E37: CALLA LILY 451漂白 | F37: L | G37: 15"x3.625” | H37: KD00397 265K0051-1ST LOT/ S/416363 | I37: 548 | J37: PCS | K37: =L37-1.45 -> 28.85 | L37: 30.3 | M37: 0.11 | O37: =B37&E37&F37 -> SIOB260205005CALLA LILY 451漂白L
B38: SIOB260205005 | C38: 60% BETTER COTTON (BCI) 40% POLYESTER 32S/1x4 PLY FLAT KNIT COLLAR | D38: 1051120 | E38: CALLA LILY 451漂白 | F38: XL | G38: 16"x3.625” | H38: KD00397 265K0051-1ST LOT/ S/416363 | I38: 600 | J38: PCS | O38: =B38&E38&F38 -> SIOB260205005CALLA LILY 451漂白XL
A39: 9 | B39: SIOB260205005 | C39: 60% BETTER COTTON (BCI) 40% POLYESTER 32S/1x4 PLY FLAT KNIT COLLAR | D39: 1051120 | E39: CALLA LILY 451漂白 | F39: XL | G39: 16"x3.625” | H39: KD00397 265K0051-1ST LOT/ S/416363 | I39: 1100 | J39: PCS | K39: =L39-1.45 -> 28.05 | L39: 29.5 | M39: 0.11 | O39: =B39&E39&F39 -> SIOB260205005CALLA LILY 451漂白XL
A40: 10 | B40: SIOB260205005 | C40: 60% BETTER COTTON (BCI) 40% POLYESTER 32S/1x4 PLY FLAT KNIT COLLAR | D40: 1051120 | E40: CALLA LILY 451漂白 | F40: XL | G40: 16"x3.625” | H40: KD00397 265K0051-1ST LOT/ S/416363 | I40: 1100 | J40: PCS | K40: =L40-1.45 -> 28.25 | L40: 29.7 | M40: 0.11 | O40: =B40&E40&F40 -> SIOB260205005CALLA LILY 451漂白XL
A41: 11 | B41: SIOB260205005 | C41: 60% BETTER COTTON (BCI) 40% POLYESTER 32S/1x4 PLY FLAT KNIT COLLAR | D41: 1051120 | E41: CALLA LILY 451漂白 | F41: XXL | G41: 17"x3.625” | H41: KD00397 265K0051-1ST LOT/ S/416363 | I41: 1100 | J41: PCS | K41: =L41-1.45 -> 30.55 | L41: 32 | M41: 0.11 | O41: =B41&E41&F41 -> SIOB260205005CALLA LILY 451漂白XXL
A42: 12 | B42: SIOB260205005 | C42: 60% BETTER COTTON (BCI) 40% POLYESTER 32S/1x4 PLY FLAT KNIT COLLAR | D42: 1051120 | E42: CALLA LILY 451漂白 | F42: XXL | G42: 17"x3.625” | H42: KD00397 265K0051-1ST LOT/ S/416363 | I42: 1100 | J42: PCS | K42: =L42-1.45 -> 30.5 | L42: 31.95 | M42: 0.11 | O42: =B42&E42&F42 -> SIOB260205005CALLA LILY 451漂白XXL
A43: 13 | B43: SIOB260205005 | C43: 60% BETTER COTTON (BCI) 40% POLYESTER 32S/1x4 PLY FLAT KNIT COLLAR | D43: 1051120 | E43: CALLA LILY 451漂白 | F43: XXL | G43: 17"x3.625” | H43: KD00397 265K0051-1ST LOT/ S/416363 | I43: 400 | J43: PCS | K43: =L43-1.45 -> 31.45 | L43: 32.9 | M43: 0.11 | O43: =B43&E43&F43 -> SIOB260205005CALLA LILY 451漂白XXL
B44: SIOB260205005 | C44: 60% BETTER COTTON (BCI) 40% POLYESTER 32S/1x4 PLY FLAT KNIT COLLAR | D44: 1051120 | E44: CALLA LILY 451漂白 | F44: XL HUSKY | G44: 16-1/2"x3.625” | H44: KD00397 265K0051-1ST LOT/ S/416363 | I44: 608 | J44: PCS | O44: =B44&E44&F44 -> SIOB260205005CALLA LILY 451漂白XL HUSKY
B45: SIOB260205005 | C45: 60% BETTER COTTON (BCI) 40% POLYESTER 32S/1x4 PLY FLAT KNIT COLLAR | D45: 1051120 | E45: CALLA LILY 451漂白 | F45: XXL HUSKY | G45: 17-1/2"x3.625” | H45: KD00397 265K0051-1ST LOT/ S/416363 | I45: 137 | J45: PCS | O45: =B45&E45&F45 -> SIOB260205005CALLA LILY 451漂白XXL HUSKY
A46: 14 | B46: SIOB260205005 | C46: 60% BETTER COTTON (BCI) 40% POLYESTER 32S/1x4 PLY FLAT KNIT COLLAR | D46: 1051120 | E46: CALLA LILY 451漂白 | F46: XL HUSKY | G46: 16-1/2"x3.625” | H46: KD00397 265K0051-1ST LOT/ S/416363 | I46: 1100 | J46: PCS | K46: =L46-1.45 -> 29.3 | L46: 30.75 | M46: 0.11 | O46: =B46&E46&F46 -> SIOB260205005CALLA LILY 451漂白XL HUSKY
A47: 15 | B47: SIOB260205005 | C47: 60% BETTER COTTON (BCI) 40% POLYESTER 32S/1x4 PLY FLAT KNIT COLLAR | D47: 1051120 | E47: CALLA LILY 451漂白 | F47: XXL HUSKY | G47: 17-1/2"x3.625” | H47: KD00397 265K0051-1ST LOT/ S/416363 | I47: 1100 | J47: PCS | K47: =L47-1.45 -> 31.85 | L47: 33.3 | M47: 0.11 | O47: =B47&E47&F47 -> SIOB260205005CALLA LILY 451漂白XXL HUSKY
A48: 16 | B48: SIOB260205005 | C48: 60% BETTER COTTON (BCI) 40% POLYESTER 32S/1x4 PLY FLAT KNIT COLLAR | D48: 1051120 | E48: CALLA LILY 451漂白 | F48: XXL HUSKY | G48: 17-1/2"x3.625” | H48: KD00397 265K0051-1ST LOT/ S/416363 | I48: 1100 | J48: PCS | K48: =L48-1.45 -> 31.8 | L48: 33.25 | M48: 0.11 | O48: =B48&E48&F48 -> SIOB260205005CALLA LILY 451漂白XXL HUSKY
A49: 17 | B49: SIOB260205012 | C49: 60% BETTER COTTON (BCI) 40% POLYESTER 32S/1x4 PLY FLAT KNIT COLLAR | D49: 1051120 | E49: RED TAPE 729正红色 | F49: M | G49: 14"x3.625” | H49: KD00400 265K0052 -1ST LOT/ S/767468 | I49: 742 | J49: PCS | K49: 29.45 | L49: 30.9 | M49: 0.11 | O49: =B49&E49&F49 -> SIOB260205012RED TAPE 729正红色M
B50: SIOB260205012 | C50: 60% BETTER COTTON (BCI) 40% POLYESTER 32S/1x4 PLY FLAT KNIT COLLAR | D50: 1051120 | E50: RED TAPE 729正红色 | F50: L HUSKY | G50: 15"x3.625” | H50: KD00400 265K0052 -1ST LOT/ S/767468 | I50: 176 | J50: PCS | O50: =B50&E50&F50 -> SIOB260205012RED TAPE 729正红色L HUSKY
B51: SIOB260205012 | C51: 60% BETTER COTTON (BCI) 40% POLYESTER 32S/1x4 PLY FLAT KNIT COLLAR | D51: 1051120 | E51: RED TAPE 729正红色 | F51: XXL HUSKY | G51: 16-1/2"x3.625” | H51: KD00400 265K0052 -1ST LOT/ S/767468 | I51: 271 | J51: PCS | O51: =B51&E51&F51 -> SIOB260205012RED TAPE 729正红色XXL HUSKY
A52: 18 | B52: SIOB260205012 | C52: 60% BETTER COTTON (BCI) 40% POLYESTER 32S/1x4 PLY FLAT KNIT COLLAR | D52: 1051120 | E52: RED TAPE 729正红色 | F52: L | G52: 14"x3.625” | H52: KD00400 265K0052 -1ST LOT/ S/767468 | I52: 1235 | J52: PCS | K52: 29.35 | L52: 30.8 | M52: 0.11 | N52: ĐƠN 10 | O52: =B52&E52&F52 -> SIOB260205012RED TAPE 729正红色L
A53: 19 | B53: SIOB260205005 | C53: 60% BETTER COTTON (BCI) 40% POLYESTER 32S/1x4 PLY FLAT KNIT COLLAR | D53: 1051120 | E53: RED TAPE 729正红色 | F53: XS | G53: 13-1/4"x3.375” | H53: KD00397 265K0051-1ST LOT/ S/416363 | I53: 1200 | J53: PCS | K53: =L53-1.45 -> 24.8 | L53: 26.25 | M53: 0.11 | N53: ĐƠN 10 | O53: =B53&E53&F53 -> SIOB260205005RED TAPE 729正红色XS
A54: 20 | B54: SIOB260205005 | C54: 60% BETTER COTTON (BCI) 40% POLYESTER 32S/1x4 PLY FLAT KNIT COLLAR | D54: 1051120 | E54: RED TAPE 729正红色 | F54: XS | G54: 13-1/4"x3.375” | H54: KD00397 265K0051-1ST LOT/ S/416363 | I54: 505 | J54: PCS | K54: =L54-1.45 -> 26.6 | L54: 28.05 | M54: 0.11 | N54: ĐƠN 10 | O54: =B54&E54&F54 -> SIOB260205005RED TAPE 729正红色XS
B55: SIOB260205005 | C55: 60% BETTER COTTON (BCI) 40% POLYESTER 32S/1x4 PLY FLAT KNIT COLLAR | D55: 1051120 | E55: RED TAPE 729正红色 | F55: S | G55: 13-3/4"x3.375” | H55: KD00397 265K0051-1ST LOT/ S/416363 | I55: 356 | J55: PCS | N55: ĐƠN 10 | O55: =B55&E55&F55 -> SIOB260205005RED TAPE 729正红色S
B56: SIOB260205005 | C56: 60% BETTER COTTON (BCI) 40% POLYESTER 32S/1x4 PLY FLAT KNIT COLLAR | D56: 1051120 | E56: RED TAPE 729正红色 | F56: XXL | G56: 17"x3.625” | H56: KD00397 265K0051-1ST LOT/ S/416363 | I56: 295 | J56: PCS | N56: ĐƠN 10 | O56: =B56&E56&F56 -> SIOB260205005RED TAPE 729正红色XXL
A57: 21 | B57: SIOB260205005 | C57: 60% BETTER COTTON (BCI) 40% POLYESTER 32S/1x4 PLY FLAT KNIT COLLAR | D57: 1051120 | E57: RED TAPE 729正红色 | F57: S | G57: 13-3/4"x3.375” | H57: KD00397 265K0051-1ST LOT/ S/416363 | I57: 1200 | J57: PCS | K57: =L57-1.45 -> 25.4 | L57: 26.85 | M57: 0.11 | N57: ĐƠN 10 | O57: =B57&E57&F57 -> SIOB260205005RED TAPE 729正红色S
A58: 22 | B58: SIOB260205005 | C58: 60% BETTER COTTON (BCI) 40% POLYESTER 32S/1x4 PLY FLAT KNIT COLLAR | D58: 1051120 | E58: MONET BLUE 744油画蓝 | F58: XXL | G58: 17"x3.625” | H58: KD00397 265K0051-1ST LOT/ S/416363 | I58: 292 | J58: PCS | K58: =L58-1.15 -> 13.65 | L58: 14.8 | M58: =65*49*20/1000000 -> 0.0637 | N58: ĐƠN 10 | O58: =B58&E58&F58 -> SIOB260205005MONET BLUE 744油画蓝XXL
B59: SIOB260205005 | C59: 60% BETTER COTTON (BCI) 40% POLYESTER 32S/1x4 PLY FLAT KNIT COLLAR | D59: 1051120 | E59: MONET BLUE 744油画蓝 | F59: XXL HUSKY | G59: 17-1/2"x3.625” | H59: KD00397 265K0051-1ST LOT/ S/416363 | I59: 189 | J59: PCS | N59: ĐƠN 10 | O59: =B59&E59&F59 -> SIOB260205005MONET BLUE 744油画蓝XXL HUSKY
A60: 23 | B60: SIOB260205005 | C60: 60% BETTER COTTON (BCI) 40% POLYESTER 32S/1x4 PLY FLAT KNIT COLLAR | D60: 1051120 | E60: WINE STAIN 853酒红 | F60: M | G60: 14-1/4"x3.625” | H60: KD00397 265K0051-1ST LOT/ S/416363 | I60: 702 | J60: PCS | K60: =L60-1.45 -> 28.3 | L60: 29.75 | M60: 0.11 | N60: ĐƠN 11 | O60: =B60&E60&F60 -> SIOB260205005WINE STAIN 853酒红M
B61: SIOB260205005 | C61: 60% BETTER COTTON (BCI) 40% POLYESTER 32S/1x4 PLY FLAT KNIT COLLAR | D61: 1051120 | E61: WINE STAIN 853酒红 | F61: L | G61: 15"x3.625” | H61: KD00397 265K0051-1ST LOT/ S/416363 | I61: 494 | J61: PCS | N61: ĐƠN 11 | O61: =B61&E61&F61 -> SIOB260205005WINE STAIN 853酒红L
A62: 24 | B62: SIOB260205005 | C62: 60% BETTER COTTON (BCI) 40% POLYESTER 32S/1x4 PLY FLAT KNIT COLLAR | D62: 1051120 | E62: WINE STAIN 853酒红 | F62: L | G62: 15"x3.625” | H62: KD00397 265K0051-1ST LOT/ S/416363 | I62: 1200 | J62: PCS | K62: =L62-1.45 -> 29.1 | L62: 30.55 | M62: 0.11 | N62: ĐƠN 11 | O62: =B62&E62&F62 -> SIOB260205005WINE STAIN 853酒红L
A63: 25 | B63: SIOB260205005 | C63: 60% BETTER COTTON (BCI) 40% POLYESTER 32S/1x4 PLY FLAT KNIT COLLAR | D63: 1051120 | E63: WINE STAIN 853酒红 | F63: XL | G63: 16"x3.625” | H63: KD00397 265K0051-1ST LOT/ S/416363 | I63: 1100 | J63: PCS | K63: =L63-1.45 -> 28.65 | L63: 30.1 | M63: 0.11 | N63: ĐƠN 11 | O63: =B63&E63&F63 -> SIOB260205005WINE STAIN 853酒红XL
A64: 26 | B64: SIOB260205005 | C64: 60% BETTER COTTON (BCI) 40% POLYESTER 32S/1x4 PLY FLAT KNIT COLLAR | D64: 1051120 | E64: WINE STAIN 853酒红 | F64: XXL | G64: 17"x3.625” | H64: KD00397 265K0051-1ST LOT/ S/416363 | I64: 1200 | J64: PCS | K64: =L64-1.45 -> 32.25 | L64: 33.7 | M64: 0.11 | N64: ĐƠN 11 | O64: =B64&E64&F64 -> SIOB260205005WINE STAIN 853酒红XXL
A65: 27 | B65: SIOB260205012 | C65: 60% BETTER COTTON (BCI) 40% POLYESTER 32S/1x4 PLY FLAT KNIT COLLAR | D65: 1051120 | E65: CALLA LILY 451漂白 | F65: L | G65: 14"x3.625” | H65: KD00400 265K0052 -1ST LOT/ S/767468 | I65: 600 | J65: PCS | K65: =L65-1.45 -> 28.8 | L65: 30.25 | M65: 0.11 | N65: ĐƠN 11 | O65: =B65&E65&F65 -> SIOB260205012CALLA LILY 451漂白L
B66: SIOB260205012 | C66: 60% BETTER COTTON (BCI) 40% POLYESTER 32S/1x4 PLY FLAT KNIT COLLAR | D66: 1051120 | E66: CALLA LILY 451漂白 | F66: XL HUSKY | G66: 16-1/2"x3.625” | H66: KD00400 265K0052 -1ST LOT/ S/767468 | I66: 197 | J66: PCS | N66: ĐƠN 11 | O66: =B66&E66&F66 -> SIOB260205012CALLA LILY 451漂白XL HUSKY
B67: SIOB260205012 | C67: 60% BETTER COTTON (BCI) 40% POLYESTER 32S/1x4 PLY FLAT KNIT COLLAR | D67: 1051120 | E67: CALLA LILY 451漂白 | F67: XXL HUSKY | G67: 16-1/2"x3.625” | H67: KD00400 265K0052 -1ST LOT/ S/767468 | I67: 357 | J67: PCS | N67: ĐƠN 11 | O67: =B67&E67&F67 -> SIOB260205012CALLA LILY 451漂白XXL HUSKY
A68: 28 | B68: SIOB260205005 | C68: 60% BETTER COTTON (BCI) 40% POLYESTER 32S/1x4 PLY FLAT KNIT COLLAR | D68: 1051120 | E68: CALLA LILY 451漂白 | F68: XS | G68: 13-1/4"x3.375” | H68: KD00397 265K0051-1ST LOT/ S/416363 | I68: 1200 | J68: PCS | K68: =L68-1.45 -> 24.2 | L68: 25.65 | M68: 0.11 | N68: ĐƠN 11 | O68: =B68&E68&F68 -> SIOB260205005CALLA LILY 451漂白XS
A69: 29 | B69: SIOB260205005 | C69: 60% BETTER COTTON (BCI) 40% POLYESTER 32S/1x4 PLY FLAT KNIT COLLAR | D69: 1051120 | E69: CALLA LILY 451漂白 | F69: XS | G69: 13-1/4"x3.375” | H69: KD00397 265K0051-1ST LOT/ S/416363 | I69: 1200 | J69: PCS | K69: =L69-1.45 -> 24 | L69: 25.45 | M69: 0.11 | N69: ĐƠN 11 | O69: =B69&E69&F69 -> SIOB260205005CALLA LILY 451漂白XS
A70: 30 | B70: SIOB260205005 | C70: 60% BETTER COTTON (BCI) 40% POLYESTER 32S/1x4 PLY FLAT KNIT COLLAR | D70: 1051120 | E70: CALLA LILY 451漂白 | F70: L | G70: 15"x3.625” | H70: KD00397 265K0051-1ST LOT/ S/416363 | I70: 1200 | J70: PCS | K70: =L70-1.45 -> 29.25 | L70: 30.7 | M70: 0.11 | N70: ĐƠN 11 | O70: =B70&E70&F70 -> SIOB260205005CALLA LILY 451漂白L
A71: 31 | B71: SIOB260205005 | C71: 60% BETTER COTTON (BCI) 40% POLYESTER 32S/1x4 PLY FLAT KNIT COLLAR | D71: 1051120 | E71: CALLA LILY 451漂白 | F71: L | G71: 15"x3.625” | H71: KD00397 265K0051-1ST LOT/ S/416363 | I71: 700 | J71: PCS | K71: =L71-1.45 -> 25.5 | L71: 26.95 | M71: 0.11 | N71: ĐƠN 11 | O71: =B71&E71&F71 -> SIOB260205005CALLA LILY 451漂白L
B72: SIOB260205005 | C72: 60% BETTER COTTON (BCI) 40% POLYESTER 32S/1x4 PLY FLAT KNIT COLLAR | D72: 1051120 | E72: CALLA LILY 451漂白 | F72: XL | G72: 16"x3.625” | H72: KD00397 265K0051-1ST LOT/ S/416363 | I72: 322 | J72: PCS | N72: ĐƠN 11 | O72: =B72&E72&F72 -> SIOB260205005CALLA LILY 451漂白XL
A73: TOTAL | E73: 31 | I73: =SUM(I19:I72) -> 34826 | J73: PCS | K73: =SUM(K30:K72) -> 847.35 | L73: =SUM(L30:L72) -> 892 | M73: =SUM(M30:M72) -> 3.3637
A74: MADE IN VIETNAM
I75: ADVANCE KNITTING VIETNAM CO., LTD

Sheet PL
A1: ADVANCE KNITTING VIETNAM CO., LTD
A2: LOT F5-4, THUAN DAO INDUSTRIAL PARK'S EXPANSION PHASE, LONG CANG COMMUNE, TAY NINH PROVINCE, VIETNAM
A3: TEL:(+84)-723-643-733; (+84)-723-643-734 FAX: (+84)-723-643-735
A4: PACKING LIST
A6: Shipper / Exporter: | I6: No. / Date of Packing List :
A7: ADVANCE KNITTING VIETNAM CO.,LTD | I7: AK/GDI-20260010 | K7: 46125
A8: LOT F5-4, THUAN DAO INDUSTRIAL PARK'S EXPANSION PHASE, LONG CANG COMMUNE, TAY NINH PROVINCE, VIETNAM | I8: No. / Date of Invoice :
A9: TEL:(+84)-723-643-733; (+84)-723-643-734 FAX: (+84)-723-643-735 | I9: =I7 -> AK/GDI-20260010 | K9: =K7 -> 46125
A10: Buyer:
A11: GDI HK LIMITED | I11: No. / Date of Contract :
A12: FLAT H, 2/F MANSION INDUSTRIAL BUILDING, | I12: AK/GDI/CT-202602 | K12: 46035
A13: 8 A KUNG NGAM VILLAGE LANE, SHAU KEI WAN, HONG KONG
A16: Consignee:
A17: PT NIRWANA ALABARE GARMENT
A18: JL. RAYA RANCAEKEK - MAJALAYA , NO.289, DESA SOLOKAN JERUK,
A19: KECAMATAN SOLOKAN JERUK, KABUPATEN BANDUNG JAWA BARAT
A20: 40382, INDONESIA
A21: TAX ID :0745 4069 2644 4000
A23: Loading: | E23: Discharge: | I23: Term of Delivery: | K23: CFR JAKARTA INDONESIA
A24: HO CHI MINH | E24: JAKARTA | I24: Origin of Goods: | K24: Vietnam
I25: PO No:
A26: FLIGHT NO: | C26: Delivery date | E26: ETA:
C27: 46126 | E27: 46128 | I27: Term of Payment: | J27: By T/T
C28: POLYESTER KNITTED RIB
B29: PO | C29: DESCRIPTION OF GOODS | D29: ITEM NO | E29: COLOR | F29: REF# | G29: TTL CARTONS | H29: Q'TY | I29: UNIT | J29: Net Weight (Kgs) | K29: Gross Weight (Kgs)
B30: SIOB260205005 | C30: 60% BETTER COTTON (BCI) 40% POLYESTER 32S/1x4 PLY FLAT KNIT COLLAR | D30: 1051120 | E30: CALLA LILY 451漂白 | F30: KD00397 265K0051-1ST LOT/ S/416363 | G30: 20 | H30: 22515 | I30: PCS | J30: 550.8 | K30: =579.8+0.2 -> 580
B31: SIOB260205005 | C31: 60% BETTER COTTON (BCI) 40% POLYESTER 32S/1x4 PLY FLAT KNIT COLLAR | D31: 1051120 | E31: RED TAPE 729正红色 | F31: KD00397 265K0051-1ST LOT/ S/416363 | G31: 3 | H31: 3556 | I31: PCS | J31: 76.8 | K31: 81.15
B32: SIOB260205005 | C32: 60% BETTER COTTON (BCI) 40% POLYESTER 32S/1x4 PLY FLAT KNIT COLLAR | D32: 1051120 | E32: MONET BLUE 744油画蓝 | F32: KD00397 265K0051-1ST LOT/ S/416363 | G32: 1 | H32: 481 | I32: PCS | J32: =K32-1.15 -> 13.65 | K32: 14.8
B33: SIOB260205005 | C33: 60% BETTER COTTON (BCI) 40% POLYESTER 32S/1x4 PLY FLAT KNIT COLLAR | D33: 1051120 | E33: WINE STAIN 853酒红 | F33: KD00397 265K0051-1ST LOT/ S/416363 | G33: 4 | H33: 4696 | I33: PCS | J33: 118.3 | K33: 124.1
B34: SIOB260205012 | C34: 60% BETTER COTTON (BCI) 40% POLYESTER 32S/1x4 PLY FLAT KNIT COLLAR | D34: 1051120 | E34: CALLA LILY 451漂白 | F34: KD00400 265K0052 -1ST LOT/ S/767468 | G34: 1 | H34: 1154 | I34: PCS | J34: =K34-1.45 -> 28.8 | K34: 30.25
B35: SIOB260205012 | C35: 60% BETTER COTTON (BCI) 40% POLYESTER 32S/1x4 PLY FLAT KNIT COLLAR | D35: 1051120 | E35: RED TAPE 729正红色 | F35: KD00400 265K0052 -1ST LOT/ S/767468 | G35: 2 | H35: 2424 | I35: PCS | J35: 58.8 | K35: 61.7
A36: TOTAL | G36: =SUM(G30:G35) -> 31 | H36: =SUM(H30:H35) -> 34826 | I36: PCS | J36: =SUM(J30:J35) -> 847.15 | K36: =SUM(K30:K35) -> 892
A37: MADE IN VIETNAM
H38: ADVANCE KNITTING VIETNAM CO., LTD

Sheet TEM
A1: SHIMADA 4
A2: Carton No | B2: PO NUMBER | D2: DESCRIPTION OF GOODS | E2: PRODUCT CODE | F2: COLOR | H2: SIZE | I2: LOT | J2: Q'TY | K2: UNIT | L2: Net Weight (Kgs) | M2: Gross Weight (Kgs) | N2: Measurements (CBM)
A3: 14 | B3: PO-DMBK-I-2435/25 | C3: ĐƠN 4 | D3: (H25234206(TL-1)) POLYESTER KNITTED RIB SIZE S 100% POLYESTER | E3: H25234206(TL-1) | F3: 1030 | G3: S | H3: 7.5*37.5 CM | I3: GT250128 | J3: 98 | K3: PCS | L3: =M3-1.35 -> 28.95 | M3: 30.3 | N3: 0.11
B4: PO-DMBK-I-2435/25 | C4: ĐƠN 4 | D4: (H25234206(TL-1)) POLYESTER KNITTED RIB SIZE S 100% POLYESTER | E4: H25234206(TL-1) | F4: 1030 | G4: M | H4: 7.5*38.5 CM | I4: GT250128 | J4: 219 | K4: PCS
B5: PO-DMBK-I-2435/25 | C5: ĐƠN 4 | D5: (H25234206(TL-1)) POLYESTER KNITTED RIB SIZE S 100% POLYESTER | E5: H25234206(TL-1) | F5: 1030 | G5: L | H5: 7.5*39.5 CM | I5: GT250128 | J5: 208 | K5: PCS
B6: PO-DMBK-I-2435/25 | C6: ĐƠN 4 | D6: (H25234206(TL-1)) POLYESTER KNITTED RIB SIZE S 100% POLYESTER | E6: H25234206(TL-1) | F6: 1030 | G6: LL | H6: 7.5*40.5 CM | I6: GT250128 | J6: 84 | K6: PCS
B7: PO-DMBK-I-2432/25 | C7: ĐƠN 4 | D7: (H25234110(TM-1)) POLYESTER KNITTED RIB SIZE 3L 100% POLYESTER | E7: H25234110(TM-1) | F7: 1030 | G7: M | H7: 8*41 CM | I7: GT250128 | J7: 209 | K7: PCS
B8: PO-DMBK-I-2432/25 | C8: ĐƠN 4 | D8: (H25234110(TM-1)) POLYESTER KNITTED RIB SIZE 3L 100% POLYESTER | E8: H25234110(TM-1) | F8: 1030 | G8: L | H8: 8*42.5 CM | I8: GT250128 | J8: 412 | K8: PCS
B9: PO-DMBK-I-2432/25 | C9: ĐƠN 4 | D9: (H25234110(TM-1)) POLYESTER KNITTED RIB SIZE 3L 100% POLYESTER | E9: H25234110(TM-1) | F9: 1030 | G9: LL | H9: 8*44 CM | I9: GT250128 | J9: 330 | K9: PCS
B10: PO-DMBK-I-2432/25 | C10: ĐƠN 4 | D10: (H25234110(TM-1)) POLYESTER KNITTED RIB SIZE 3L 100% POLYESTER | E10: H25234110(TM-1) | F10: 1030 | G10: 3L | H10: 8*45.5 CM | I10: GT250128 | J10: 199 | K10: PCS
A11: =COUNT(A3:A10) -> 1 | J11: =SUM(J3:J10) -> 1759 | K11: PCS | L11: =SUM(L3:L10) -> 28.95 | M11: =SUM(M3:M10) -> 30.3 | N11: =SUM(N3:N10) -> 0.11
A12: MADE IN VIETNAM
F13: ADVANCE KNITTING VIETNAM CO., LTD
J14: Signature, full name, seal

Sheet DELIVERY INSTRUCTION
A2: DELIVERY INSTRUCTION
A3: No. | B3: : | C3: =DPL!J7 -> AK/GDI-20260010
A4: Date | B4: : | C4: =DPL!L7 -> 46125
A6: Pursuant to Contract No. | B6: : | C6: AK/GDI/CT-202512 on Dec. 17, 2025
A9: We (Buyer) hereby | B9: : | C9: =DPL!A11 -> GDI HK LIMITED
C10: ADD: FLAT H, 2/F MANSION INDUSTRIAL BUILDING, 8 A KUNG NGAM VILLAGE LANE, SHAU KEI WAN, HONG KONG
A12: To appoint to Seller | C12: ADVANCE KNITTING VIETNAM CO.,LTD
C13: LOT F5-4, THUAN DAO INDUSTRIAL PARK'S EXPANSION PHASE, LONG CANG COMMUNE, TAY NINH PROVINCE, VIETNAM
C14: TEL:(+84)-723-643-733; (+84)-723-643-734 FAX: (+84)-723-643-735
A15: To release cargo to Consignee | B15: : | C15: =DPL!A17 -> PT NIRWANA ALABARE GARMENT
C16: NO.18 THONG NHAT ROAD, SONG THAN INDUSTRIAL ZONE II,DI AN WARD,
C17: HO CHI MINH CITY, VIETNAM.
C18: TAX CODE :3700346873
C19: TEL :0084-274.3790.780|Ext.:260
A20: Notify party: | C20: KANMAX ENTERPRISES LIMITED
C21: ADD: 60 PAYA LEBAR ROAD, #04-21 PAYA LEBAR SQUARE, SINGAPORE 409051, SINGAPORE.
C22: TEL: 65 6702 1179 FAX : FAX: 65 6702 1182
A23: As the followings
A25: PO | B25: REF# | D25: ITEM NO | E25: DESCRIPTION OF GOODS | F25: COLOR | G25: SIZE | H25: QUANTITY | I25: Unit | J25: UNIT PRICE (USD) | K25: AMOUNT (USD)
A26: SIOB251105016 | B26: KV06800 263K0033-B~E4(3RD MB)/ S/416363 | D26: 1051120 | E26: 60% BETTER COTTON (BCI) 40% POLYESTER 32S/1x4 PLY FLAT KNIT COLLAR | F26: BLACK JACK 400黑色 | G26: XS | H26: 1152 | I26: PCS | J26: 0.17 | K26: =ROUND(H26*J26,3) -> 195.84
A27: SIOB251105016 | B27: KV06800 263K0033-B~E4(3RD MB)/ S/416363 | D27: 1051120 | E27: 60% BETTER COTTON (BCI) 40% POLYESTER 32S/1x4 PLY FLAT KNIT COLLAR | F27: BLACK JACK 400黑色 | G27: S | H27: 2703 | I27: PCS | J27: 0.17 | K27: =ROUND(H27*J27,3) -> 459.51
A28: SIOB251105016 | B28: KV06800 263K0033-B~E4(3RD MB)/ S/416363 | D28: 1051120 | E28: 60% BETTER COTTON (BCI) 40% POLYESTER 32S/1x4 PLY FLAT KNIT COLLAR | F28: BLACK JACK 400黑色 | G28: M | H28: 1869 | I28: PCS | J28: 0.17 | K28: =ROUND(H28*J28,3) -> 317.73
A29: SIOB251105016 | B29: KV06800 263K0033-B~E4(3RD MB)/ S/416363 | D29: 1051120 | E29: 60% BETTER COTTON (BCI) 40% POLYESTER 32S/1x4 PLY FLAT KNIT COLLAR | F29: BLACK JACK 400黑色 | G29: L | H29: 3823 | I29: PCS | J29: 0.17 | K29: =ROUND(H29*J29,3) -> 649.91
A30: SIOB251105016 | B30: KV06800 263K0033-B~E4(3RD MB)/ S/416363 | D30: 1051120 | E30: 60% BETTER COTTON (BCI) 40% POLYESTER 32S/1x4 PLY FLAT KNIT COLLAR | F30: BLACK JACK 400黑色 | G30: XL | H30: 2332 | I30: PCS | J30: 0.17 | K30: =ROUND(H30*J30,3) -> 396.44
A31: SIOB251105016 | B31: KV06800 263K0033-B~E4(3RD MB)/ S/416363 | D31: 1051120 | E31: 60% BETTER COTTON (BCI) 40% POLYESTER 32S/1x4 PLY FLAT KNIT COLLAR | F31: BLACK JACK 400黑色 | G31: XXL | H31: 1744 | I31: PCS | J31: 0.17 | K31: =ROUND(H31*J31,3) -> 296.48
A32: SIOB251105016 | B32: KV06800 263K0033-B~E4(3RD MB)/ S/416363 | D32: 1051120 | E32: 60% BETTER COTTON (BCI) 40% POLYESTER 32S/1x4 PLY FLAT KNIT COLLAR | F32: BLACK JACK 400黑色 | G32: L HUSKY | H32: 205 | I32: PCS | J32: 0.17 | K32: =ROUND(H32*J32,3) -> 34.85
A33: SIOB251105016 | B33: KV06800 263K0033-B~E4(3RD MB)/ S/416363 | D33: 1051120 | E33: 60% BETTER COTTON (BCI) 40% POLYESTER 32S/1x4 PLY FLAT KNIT COLLAR | F33: BLACK JACK 400黑色 | G33: XL HUSKY | H33: 147 | I33: PCS | J33: 0.17 | K33: =ROUND(H33*J33,3) -> 24.99
A34: SIOB251105016 | B34: KV06800 263K0033-B~E4(3RD MB)/ S/416363 | D34: 1051120 | E34: 60% BETTER COTTON (BCI) 40% POLYESTER 32S/1x4 PLY FLAT KNIT COLLAR | F34: BLACK JACK 400黑色 | G34: XXL HUSKY | H34: 186 | I34: PCS | J34: 0.17 | K34: =ROUND(H34*J34,3) -> 31.62
B35: TOTAL | H35: =SUM(H26:H34) -> 14161 | I35: PCS | J35: USD | K35: =SUM(K26:K34) -> 2407.37
A38: AMOUNT IN WORDS | C38: =INV!B55 -> US DOLLAR FIVE THOUSAND EIGHT HUNDRED TWO AND NINE CENTS ONLY.
A39: ARTICLE 2: ORIGIN OF VIETNAM
A40: ARTICLE 3: PACKING | C40: Export Standard Packing
A41: ARTICLE 4: DELIVERY AND PAYMENT
A42: *Delivery | C42: By Truck/ Lalamove
A43: *Delivery Time | C43: =DPL!E27 -> 46128
A44: *Delivery Term | C44: DAP HO CHI MINH
A45: *Bill To | C45: =C9 -> GDI HK LIMITED
A46: We kindly request the relevant parties to perform the delivery and receipt of goods in accordance with the above instruction and comply with the customs
A48: For and on behalf of Buyer

Sheet SC
A1: ADVANCE KNITTING VIETNAM CO., LTD
A2: LOT F5-4, THUAN DAO INDUSTRIAL PARK'S EXPANSION PHASE, LONG CANG COMMUNE, TAY NINH PROVINCE, VIETNAM
A3: TEL:(+84)-723-643-733; (+84)-723-643-734 FAX: (+84)-723-643-735
A4: SALE CONTRACT
A6: BUYER: GDI HK LIMITED | H6: No: | I6: SIOB251103005-1
A7: FLAT H, 2/F MANSION INDUSTRIAL BUILDING, 8 A KUNG NGAM VILLAGE LANE, SHAU KEI WAN, HONG KONG | H7: Date: | I7: 46018
A9: BASE ON PO NO SIOB251103005 SIGNED ON NOVEMBER 03, 2025 ; ADVANCE KNITTING VIETNAM CO.,LTD AS SELLER , HEREBY CONFIRMS HAVING SOLD THE REMAIN QUANTITY OF THIS PO TO YOUR FIRM
A10: THE FOLLOWING GOODS BY CONTRACT OF SALE MADE ON THE ABOVE DATE AND ON THE TERNMS AND
A11: CONDITIONS HEREAFTER SET FORTH:
A12: COMMODITY | C12: : | D12: CLOTHING ACCESSORIES
A14: PO | B14: REF# | C14: ITEM NO | D14: DESCRIPTION OF GOODS | E14: COLOR | F14: SIZE | G14: QUANTITY | H14: Unit | I14: UNIT PRICE (USD) | J14: AMOUNT (USD)
A15: SIOB251103005 | B15: KV06798 263K0033-A2+~A4(1ST LOT)/S/416363 | C15: 1051120 | D15: 60% BETTER COTTON (BCI) 40% POLYESTER 32S/1x4 PLY FLAT KNIT COLLAR | E15: MONET BLUE 744油画蓝 | F15: XL | G15: 41 | H15: PCS | I15: 0.17 | J15: 6.97
A16: SIOB251103005 | B16: KV06798 263K0033-A2+~A4(1ST LOT)/S/416363 | C16: 1051120 | D16: 60% BETTER COTTON (BCI) 40% POLYESTER 32S/1x4 PLY FLAT KNIT COLLAR | E16: MONET BLUE 744油画蓝 | F16: XXL | G16: 12 | H16: PCS | I16: 0.17 | J16: 2.04
A17: SIOB251103005 | B17: KV06798 263K0033-A2+~A4(1ST LOT)/S/416363 | C17: 1051120 | D17: 60% BETTER COTTON (BCI) 40% POLYESTER 32S/1x4 PLY FLAT KNIT COLLAR | E17: BLACK JACK 400黑色 | F17: S | G17: 123 | H17: PCS | I17: 0.17 | J17: 20.91
A18: SIOB251103005 | B18: KV06798 263K0033-A2+~A4(1ST LOT)/S/416363 | C18: 1051120 | D18: 60% BETTER COTTON (BCI) 40% POLYESTER 32S/1x4 PLY FLAT KNIT COLLAR | E18: BLACK JACK 400黑色 | F18: XL HUSKY | G18: 52 | H18: PCS | I18: 0.17 | J18: 8.84
A19: SIOB251103005 | B19: KV06798 263K0033-A2+~A4(1ST LOT)/S/416363 | C19: 1051120 | D19: 60% BETTER COTTON (BCI) 40% POLYESTER 32S/1x4 PLY FLAT KNIT COLLAR | E19: BLACK JACK 400黑色 | F19: XXL HUSKY | G19: 31 | H19: PCS | I19: 0.17 | J19: 5.27
C20: TOTAL | G20: =SUM(G15:G19) -> 259 | H20: PCS | I20: USD | J20: =SUM(J15:J19) -> 44.03
A23: QUALITY | C23: : | D23: AS PER ADVANCE KNITTING VIETNAM'S STANDARD GRADE
A24: QUANTITY | C24: : | D24: =G20 -> 259 | E24: PCS
A25: PACKING MARKING | C25: : | D25: EXPORT STANDARD PACKING IN TRUCK
A26: TOTAL AMOUNT OF CONTRACT | C26: : | D26: =J20 -> 44.03
D27: US DOLLAR FORTY FOUR AND THREE CENTS ONLY.
A28: TERMS OF PAYMENT | C28: : | D28: T/T 100% PAYMENT WITHIN 30 DAYS DELIVERY
A29: DELIVERY PLACE: | C29: : | D29: BUYER NOMINATE SELLER DELIVER GOODS TO CONSIGNEE BELOW:
D30: CHUTEX INTERNATIONAL CO.,LTD
D31: NO.18 THONG NHAT ROAD, SONG THAN INDUSTRIAL ZONE II,DI AN WARD,
D32: HO CHI MINH CITY, VIETNAM.
A33: DELIVERY TERM: | D33: DAP HO CHI MINH
A34: NOTIFY PARTY (IF NEEDED) | D34: =DPL!#REF! -> #REF!
D35: =DPL!#REF! -> #REF!
D36: =DPL!#REF! -> #REF!
A37: OUR BANK | C37: : | D37: JOINT STOCK COMMERCIAL BANK FOR FOREIGN TRADE OF VIET NAM (VIETCOMBANK)
A38: BRANCH | C38: : | D38: 2A PHAM VAN NGU STREET, BEN LUC DISTRICT, LONG AN PROVINCE, VIET NAM
A39: ACCOUNT NO. | C39: : | D39: 0631370457237
A40: SWIFT CODE | C40: : | D40: BFTVVNVX
A41: TIME OF SHIPMENT | C41: : | D41: =DPL!C27 -> 46126
A42: FROM | C42: : | D42: TAY NINH
A43: DESTINATION : | C43: : | D43: HO CHI MINH
A44: INSPECTION | C44: : | D44: ADVANCE KNITTING VIETNAM FACTORY 'S INSPECTION TO BE TAKEN AS FINAL
A45: OTHER CONDITIONS | C45: : | D45: PRICE ADJUSTMENT FOR INFERIOR PRODUCTS IF ANY SHALL BE SETTLED BY THE
D46: SELLER BASED ON MUTUAL BENEFIT AND AMICABLE NEGOTIATION DURING TRANSACTION
D47: TERMS OF PAYMENT ALSO CAN BE MADE BY BALANCE SETTLE.
A48: Accepted and confirmed by | F48: Accepted and confirmed by
A49: ( BUYER) | F49: ( SELLER)

Sheet IN PHIẾU XUẤT 
I1: Mẫu số: 02-VT
D2: 出货明细 PHIẾU XUẤT KHO | I2: (Ban hành theo TT số: 200/2014/TT-BTC)
A3: Lô F5-4, KCN Thuận Đạo, huyện Cần Đước, tỉnh Long An | I3: Ngày 22/12/2014 của bộ trưởng BTC
C4: =NOW() -> 46126.497 | I4: Nợ……………...........
C5: PXK:SH28032025 | I5: Có……………............
A6: Họ tên người nhận hàng 领料员: | H6: PO:
A7: Khách hàng/ Bộ phận 部门SHIMADA SHOJI (VIETNAM) CO., LTD | H7: Biển kiểm soát :
A8: Địa chỉ 地址Lô số 21-1, 21-2 và 21-3, Đường số 8B, Khu Công Nghiệp Quốc Tế Protrade,Xã An Tây, Thị xã Bến Cát, T.BD.VN
A9: Lý do xuất kho: | C9: XUẤT THÀNH PHẨM 出口成品
A10: Xuất tại kho: | C10: CÔNG TY TNHH ADVANCE KNITTING VIỆT NAM
A11: Ghi chú备注: 15 THÙNG
A12: STT | B12: PO | C12: 色號 Mã màu | D12: 缸号 Mã Lot | E12: 尺寸 Quy cách | G12: 单位 Đơn vị | H12: 数量 Số lượng | I12: Ghi chú 备注
H13: 良品数量 Thực xuất
A14: 1 | B14: PO-DMBK-I-1669(HN)/25 | C14: NVY | D14: GT240114 | E14: 140MMX500MM | G14: PCS | H14: 238
A15: 2 | B15: PO-DMBK-I-1669(HN)/25 | C15: WHT | D15: GT240815 | E15: 140MMX500MM | G15: PCS | H15: 361
A16: 3 | B16: PO-DMBK-I-1669(HN)/25 | C16: ABN | D16: GT250221 | E16: 140MMX500MM | G16: PCS | H16: 64
A17: 4 | B17: PO-DMBK-I-2418/25 | C17: 1120(NAVY) | D17: GT250204 | E17: M | F17: 6.5X50CM | G17: PCS | H17: 214
A18: 5 | B18: PO-DMBK-I-2418/25 | C18: 1120(NAVY) | D18: GT250204 | E18: L | F18: 6.5X50CM | G18: PCS | H18: 353
A19: 6 | B19: PO-DMBK-I-2418/25 | C19: 1120(NAVY) | D19: GT250204 | E19: LL | F19: 6.5X50CM | G19: PCS | H19: 177
A20: 7 | B20: PO-DMBK-I-2418/25 | C20: 1120(NAVY) | D20: GT250204 | E20: 3L | F20: 6.5X50CM | G20: PCS | H20: 96
A21: 8 | B21: PO-DMBK-I-2418/25 | C21: 1030(WHITE) | D21: GT250204 | E21: M | F21: 6.5X50CM | G21: PCS | H21: 298
A22: 9 | B22: PO-DMBK-I-2418/25 | C22: 1030(WHITE) | D22: GT250204 | E22: L | F22: 6.5X50CM | G22: PCS | H22: 496
A23: 10 | B23: PO-DMBK-I-2418/25 | C23: 1030(WHITE) | D23: GT250204 | E23: LL | F23: 6.5X50CM | G23: PCS | H23: 247
A24: 11 | B24: PO-DMBK-I-2418/25 | C24: 1030(WHITE) | D24: GT250204 | E24: 3L | F24: 6.5X50CM | G24: PCS | H24: 129
A25: 12 | B25: PO-DMBK-I-2418/25 | C25: 1140(GREEN) | D25: GT250204 | E25: M | F25: 6.5X50CM | G25: PCS | H25: 162
A26: 13 | B26: PO-DMBK-I-2418/25 | C26: 1140(GREEN) | D26: GT250204 | E26: L | F26: 6.5X50CM | G26: PCS | H26: 272
A27: 14 | B27: PO-DMBK-I-2418/25 | C27: 1140(GREEN) | D27: GT250204 | E27: LL | F27: 6.5X50CM | G27: PCS | H27: 135
A28: 15 | B28: PO-DMBK-I-2418/25 | C28: 1140(GREEN) | D28: GT250204 | E28: 3L | F28: 6.5X50CM | G28: PCS | H28: 71
... A32: 19 | B32: PO-DMBK-I-2418/25 | C32: 1110(RED) | D32: GT250204 | E32: 3L | F32: 6.5X50CM | G32: PCS | H32: 47
A33: 20 | B33: PO-DMBK-I-2435/25 | C33: 1030 | D33: GT250128 | E33: S | F33: 7.5*37.5 CM | G33: PCS | H33: 98
A34: 21 | B34: PO-DMBK-I-2435/25 | C34: 1030 | D34: GT250128 | E34: M | F34: 7.5*38.5 CM | G34: PCS | H34: 219
A35: 22 | B35: PO-DMBK-I-2435/25 | C35: 1030 | D35: GT250128 | E35: L | F35: 7.5*39.5 CM | G35: PCS | H35: 208
A36: 23 | B36: PO-DMBK-I-2435/25 | C36: 1030 | D36: GT250128 | E36: LL | F36: 7.5*40.5 CM | G36: PCS | H36: 84
A37: 24 | B37: PO-DMBK-I-2432/25 | C37: 1030 | D37: GT250128 | E37: M | F37: 8*41 CM | G37: PCS | H37: 209
A38: 25 | B38: PO-DMBK-I-2432/25 | C38: 1030 | D38: GT250128 | E38: L | F38: 8*42.5 CM | G38: PCS | H38: 412
A39: 26 | B39: PO-DMBK-I-2432/25 | C39: 1030 | D39: GT250128 | E39: LL | F39: 8*44 CM | G39: PCS | H39: 330
A40: 27 | B40: PO-DMBK-I-2432/25 | C40: 1030 | D40: GT250128 | E40: 3L | F40: 8*45.5 CM | G40: PCS | H40: 199
A41: 28 | B41: PO-DMBK-I-2435/25 | C41: 1120 | D41: GT250128 | E41: S | F41: 7.5*37.5 CM | G41: PCS | H41: 42
A42: 29 | B42: PO-DMBK-I-2435/25 | C42: 1120 | D42: GT250128 | E42: M | F42: 7.5*38.5 CM | G42: PCS | H42: 112
A43: 30 | B43: PO-DMBK-I-2435/25 | C43: 1120 | D43: GT250128 | E43: L | F43: 7.5*39.5 CM | G43: PCS | H43: 105
A44: 31 | B44: PO-DMBK-I-2435/25 | C44: 1120 | D44: GT250128 | E44: LL | F44: 7.5*40.5 CM | G44: PCS | H44: 40
... A53: 40 | B53: PO-DMBK-I-2435/25 | C53: 1120 | D53: GT250204 | E53: LL | F53: 7.5*40.5 CM | G53: PCS | H53: 7
A54: 41 | B54: PO-DMBK-I-1668/25 | C54: ABN | D54: GT250218 GT240815 | E54: 100MM*600MM | G54: PCS | H54: 1917 | I54: THIẾU 800
A55: 42 | B55: PO-DMBK-I-1668/25 | C55: DBL | D55: GT250114 GT240815 | E55: 100MM*600MM | G55: PCS | H55: 1231
A56: 43 | B56: PO-DMBK-I-1668/25 | C56: WHT | D56: GT250114 GT240815 | E56: 100MM*600MM | G56: PCS | H56: 1658 | I56: THIẾU 200
A57: 44 | B57: PO-DMBK-I-1668/25 | C57: BLK | D57: GT250218 GT240815 | E57: 100MM*600MM | G57: PCS | H57: 3545 | L57: =1300+16749 -> 18049
A58: 45 | B58: PO-DMBK-I-1668/25 | C58: BLK | D58: GT250218 | E58: 110MM*800MM | G58: PCS | H58: 1907 | I58: THIẾU 300
A59: 金额 Tổng | H59: =SUM(H14:H58) -> 16749
B60: Tổng Tiền: | C60: =F66 -> Không đồng.
A61: =J59 -> 0 | C61: =RIGHT("000000000000"&ROUND(A61,0),12) -> 000000000000 | F61: 1 | G61: 2 | H61: 3 | I61: 4 | J61: 5 | K61: 6 | L61: 7 | M61: 8 | N61: 9 | O61: 10 | P61: 11 | Q61: 12
F62: =VALUE(MID(C61,F61,1)) -> 0 | G62: =VALUE(MID(C61,G61,1)) -> 0 | H62: =VALUE(MID(C61,H61,1)) -> 0 | I62: =VALUE(MID(C61,I61,1)) -> 0 | J62: =VALUE(MID(C61,J61,1)) -> 0 | K62: =VALUE(MID(C61,K61,1)) -> 0 | L62: =VALUE(MID(C61,L61,1)) -> 0 | M62: =VALUE(MID(C61,M61,1)) -> 0 | N62: =VALUE(MID(C61,N61,1)) -> 0 | O62: =VALUE(MID(C61,O61,1)) -> 0 | P62: =VALUE(MID(C61,P61,1)) -> 0 | Q62: =VALUE(MID(C61,Q61,1)) -> 0
F63: =SUM(F62:F62) -> 0 | G63: =SUM(F62:G62) -> 0 | H63: =SUM(F62:H62) -> 0 | I63: =SUM(I62:I62) -> 0 | J63: =SUM(I62:J62) -> 0 | K63: =SUM(I62:K62) -> 0 | L63: =SUM(L62:L62) -> 0 | M63: =SUM(L62:M62) -> 0 | N63: =SUM(L62:N62) -> 0 | O63: =SUM(O62:O62) -> 0 | P63: =SUM(O62:P62) -> 0 | Q63: =SUM(O62:Q62) -> 0
F64: =IF(F62=0,"",CHOOSE(F62,"một","hai","ba","bốn","năm","sáu","bảy","tám","chín")) | G64: =IF(G62=0,IF(AND(F62<>0,H62<>0),"lẻ",""),CHOOSE(G62,"mười","hai","ba","bốn","năm","sáu","bảy","tám","chín")) | H64: =IF(H62=0,"",CHOOSE(H62,IF(G62>1,"mốt","một"),"hai","ba","bốn",IF(G62=0,"năm","lăm"),"sáu","bảy","tám","chín")) | I64: =IF(I62=0,"",CHOOSE(I62,"một","hai","ba","bốn","năm","sáu","bảy","tám","chín")) | J64: =IF(J62=0,IF(AND(I62<>0,K62<>0),"lẻ",""),CHOOSE(J62,"mười","hai","ba","bốn","năm","sáu","bảy","tám","chín")) | K64: =IF(K62=0,"",CHOOSE(K62,IF(J62>1,"mốt","một"),"hai","ba","bốn",IF(J62=0,"năm","lăm"),"sáu","bảy","tám","chín")) | L64: =IF(L62=0,"",CHOOSE(L62,"một","hai","ba","bốn","năm","sáu","bảy","tám","chín")) | M64: =IF(M62=0,IF(AND(L62<>0,N62<>0),"lẻ",""),CHOOSE(M62,"mười","hai","ba","bốn","năm","sáu","bảy","tám","chín")) | N64: =IF(N62=0,"",CHOOSE(N62,IF(M62>1,"mốt","một"),"hai","ba","bốn",IF(M62=0,"năm","lăm"),"sáu","bảy","tám","chín")) | O64: =IF(O62=0,"",CHOOSE(O62,"một","hai","ba","bốn","năm","sáu","bảy","tám","chín")) | P64: =IF(P62=0,IF(AND(O62<>0,Q62<>0),"lẻ",""),CHOOSE(P62,"mười","hai","ba","bốn","năm","sáu","bảy","tám","chín")) | Q64: =IF(Q62=0,"",CHOOSE(Q62,IF(P62>1,"mốt","một"),"hai","ba","bốn",IF(P62=0,"năm","lăm"),"sáu","bảy","tám","chín"))
F65: =IF(F62=0,"","trăm") | G65: =IF(G62=0,"",IF(G62=1,"","mươi")) | H65: =IF(AND(H62=0,H63=0),"","tỷ") | I65: =IF(I62=0,"","trăm") | J65: =IF(J62=0,"",IF(J62=1,"","mươi")) | K65: =IF(AND(K62=0,K63=0),"","triệu") | L65: =IF(L62=0,"","trăm") | M65: =IF(M62=0,"",IF(M62=1,"","mươi")) | N65: =IF(AND(N62=0,N63=0),"","nghìn") | O65: =IF(O62=0,"","trăm") | P65: =IF(P62=0,"",IF(P62=1,"","mươi")) | Q65: đồng./.
F66: =UPPER(LEFT(TRIM(IF(A61=0,"không đồng.",F64&" "&F65&" "&G64&" "&G65&" "&H64&" "&H65&" "&I64&" "&I65&" "&J64&" "&J65&" "&K64&" "&K65&" "&L64&" "&L65&" "&M64&" "&M65&" "&N64&" "&N65&" "&O64&" "&O65&" "&P64&" "&P65&" "&Q64&" "&Q65)),1))&RIGHT(TRIM(IF(A61=0,"không đồng.",F64&" "&F65&" "&G64&" "&G65&" "&H64&" "&H65&" "&I64&" "&I65&" "&J64&" "&J65&" "&K64&" "&K65&" "&L64&" "&L65&" "&M64&" "&M65&" "&N64&" "&N65&" "&O64&" "&O65&" "&P64&" "&P65&" "&Q64&" "&Q65)),LEN(TRIM(IF(A61=0,"không đồng.",F64&" "&F65&" "&G64&" "&G65&" "&H64&" "&H65&" "&I64&" "&I65&" "&J64&" "&J65&" "&K64&" "&K65&" "&L64&" "&L65&" "&M64&" "&M65&" "&N64&" "&N65&" "&O64&" "&O65&" "&P64&" "&P65&" "&Q64&" "&Q65)))-1) -> Không đồng.
A67: 收货人 người nhận hàng | C67: 负担人 người lập phiếu | F67: 仓管 Quản kho | J67: 批准 Phê Chuẩn
C70: CHÂU QUANG TRÊN | F70: TRƯƠNG TẤN ĐẠT | I70: =NOW() -> 46126.497
I71: FAN SENG FATT
