Workbook

Sheet Template Guidelines
A1: Do not delete or modify any formulas in this template.
A2: Enter your data only in the designated fields (highlighted in yellow)
A3: After entering data, save the file with a new name to keep the original template unchanged. DO NOT copy/paste the data.

Sheet Invoice
A1: =IF(C8<>"", C8, "COMPANY NAME") -> CONTINENT8 PTE LTD
A2: =IF(COUNTA(C9:C11)>0, C9 & IF(C10<>"", ", " & C10, "") & IF(C11<>"", ", " & C11, ""), "ADDRESS, CITY, STATE, ZIP/POSTAL, COUNTRY") -> 00 TAMPINES AVENUE# 09-02, INCOME AT TAMPINES JUNCTION, SINGAPORE 529693
A3: =IF(C13<>"", C13, "EMAIL/PHONE") -> PHONE : 6221 30205577
A5: INVOICE # | C5: INVOICE DATE | D5: INCOTERMS | E5: PAYMENT TERMS | F5: TRANSPORT MODE | H5: EXPORT REFERENCES
A6: 0417/E/NAG/0726 | C6: 46219 | D6: EXW | E6: T/T | F6: OCEAN
A7: MANUFACTURER | C7: SELLER | D7: BUYER | F7: RECEIVER
A8: COMPANY NAME | B8: PT NIRWANA ALABARE GARMENT | C8: CONTINENT8 PTE LTD | D8: Kith Logistics LLC 25 Kent Ave, Suite 301 Brooklyn, NY 11249 USA ap@kithnyc.com PH: +1 212 473 4654 | F8: KDC4 c/o Omlog USA 1000 Rand Blvd., Building 3 Phillipsburg, NJ, 08865 Carmen Amodio 201-552-7208 Carmen.Amodio@omlog.com
A9: STREET ADDRESS | B9: JL RAYA RANCAEKEK MAJALAYA, 289, SOLOKANJERUK, | C9: 00 TAMPINES AVENUE# 09-02
A10: CITY, STATE, ZIP | B10: BANDUNG | C10: INCOME AT TAMPINES JUNCTION
A11: COUNTRY | B11: INDONESIA | C11: SINGAPORE 529693
A12: CONTACT PERSON | B12: NENG KURNIA / YULIA VIRA | C12: EMAIL : DKURNIATI@CONTINENT-EIGHT.COM
A13: EMAIL/PHONE | B13: 022 8596-2076 | C13: PHONE : 6221 30205577
A14: MANUFACTURER ID (MID) | C14: IMPORTER | D14: FISCAL REPRESENTATIVE | F14: NOTIFY BROKER
A15: IDNAG289BDG | C15: =IFERROR(INDEX('Data Validation'!D18:D35, MATCH(F8, 'Data Validation'!C18:C35, 0)), "") -> Kith Logistics LLC 25 Kent Ave, Suite 301 Brooklyn, NY 11249 USA EIN# 81-0814080 | D15: =IFERROR(INDEX('Data Validation'!G18:G35, MATCH(F8, 'Data Validation'!C18:C35, 0)), "") -> - | F15: =IFERROR( IF(COUNTIF('Data Validation'!C18:C35, F8), IF(OR(F6="AIR", F6="OCEAN"), INDEX('Data Validation'!E18:E35, MATCH(F8, 'Data Validation'!C18:C35, 0)), IF(F6="SMALL PARCEL", INDEX('Data Validation'!F18:F35, MATCH(F8, 'Data Validation'!C18:C35, 0)), "")), ""), "") -> FORWARDER
A16: REGION of ULTIMATE DESTINATION
A17: =IF(F8="KDC20 c/o Bleckmann Industrieweg 38 C 2280 Grobbendonk Belgium Koen Verhoeven customercare.kith.grobbendonk@bleckmann.com",IF(F6="OCEAN","ANTWERP",IF(F6="AIR","BRUSSELS-CAPITAL REGION",IF(F6="SMALL PARCEL","BRUSSELS-CAPITAL REGION",""))),"")
A18: UN/LOCODE
A19: =IF(F8="KDC20 c/o Bleckmann Industrieweg 38 C 2280 Grobbendonk Belgium Koen Verhoeven customercare.kith.grobbendonk@bleckmann.com",IF(F6="OCEAN","BE ANR",IF(F6="AIR","BE BRU",IF(F6="SMALL PARCEL","BE BRU",""))),"")
A20: PO # | B20: PRODUCT ID | C20: DESCRIPTION | D20: COMPOSITION | E20: HTS CODE | F20: COO | G20: QTY | H20: FOB PER UNIT (USD) | I20: EXT COST (USD)
A21: =+'Packing List'!C15 -> 115154 | B21: =+'Packing List'!D15 -> KHM034600 | C21: =+'Packing List'!F15 -> K-TECH | D21: 100% COTTON | E21: 6109.10.0012 | G21: =SUMIF('Packing List'!D15:D28,Invoice!B21,'Packing List'!N15:N28) -> 651 | H21: 2.5 | I21: =G21*H21 -> 1627.5
A22: =+'Packing List'!C25 -> 115154 | B22: =+'Packing List'!D25 -> KHM034601 | C22: =+'Packing List'!F25 -> K-TECH | D22: 100% COTTON | E22: 6109.10.0012 | G22: =SUMIF('Packing List'!D15:D28,Invoice!B22,'Packing List'!N15:N28) -> 205 | H22: 3.5 | I22: =G22*H22 -> 717.5
I23: =G23*H23 -> 0
I24: =G24*H24 -> 0
I25: =G25*H25 -> 0
I26: =G26*H26 -> 0
I27: =G27*H27 -> 0
I28: =G28*H28 -> 0
I29: =G29*H29 -> 0
I30: =G30*H30 -> 0
I31: =G31*H31 -> 0
I32: =G32*H32 -> 0
I33: =G33*H33 -> 0
I34: =G34*H34 -> 0
... I36: =G36*H36 -> 0
F38: TOTALS | G38: =SUM(G21:G37) -> 856 | H38: - | I38: =SUM(I21:I36) -> 2345
A39: GR WGT (kg): | B39: ='Packing List'!P30 -> 148.12
A40: NT WGT (kg): | B40: ='Packing List'!Q30 -> 129.45
A42: =IF(OR( AND( F8="KDC20 c/o Bleckmann Industrieweg 38 C 2280 Grobbendonk Belgium Koen Verhoeven customercare.kith.grobbendonk@bleckmann.com", ISNUMBER(MATCH(F21, {"Bangladesh","BD","Cambodia","KH","India","IN","Indonesia","ID","Japan","JP","Mexico","MX","Myanmar","MM","Philippines","PH","United Kingdom","UK","GB"}, 0)) ), AND( F8="KDC30 c/o Bleckmann UK Ltd Plot MPN1 Westland Way Magna Park, Lutterworth LE17 4UE United Kingdom Mark Gamberini mark.gamberini@bleckmann.com, goodsin.uk4@bleckmann.com", ISNUMBER(MATCH(F21, {"Bangladesh","BD","Cambodia","KH","India","IN","Indonesia","ID","Japan","JP","Myanmar","MM","Philippines","PH","Turkey","TR","Austria","AT","Belgium","BE","Bulgaria","BG","Croatia","HR","Cyprus","CY","Czech Republic","CZ","Denmark","DK","Estonia","EE","Finland","FI","France","FR","Germany","DE","Greece","GR","Hungary","HU","Ireland","IE","Italy","IT","Latvia","LV","Lithuania","LT","Luxembourg","LU","Malta","MT","Netherlands","NL","Poland","PL","Portugal","PT","Romania","RO","Slovakia","SK","Slovenia","SI","Spain","ES","Sweden","SE"}, 0)) ), AND( F8="KDC70 c/o Bergen Logistics 3925 Steelers Ave E Brampton, ON L6T 5W5 Canada Shane Francis 3925canada@bergenlogistics.com", ISNUMBER(MATCH(F21, {"United Kingdom","UK","GB","Austria","AT","Belgium","BE","Bulgaria","BG","Croatia","HR","Cyprus","CY","Czech Republic","CZ","Denmark","DK","Estonia","EE","Finland","FI","France","FR","Germany","DE","Greece","GR","Hungary","HU","Ireland","IE","Italy","IT","Latvia","LV","Lithuania","LT","Luxembourg","LU","Malta","MT","Netherlands","NL","Poland","PL","Portugal","PT","Romania","RO","Slovakia","SK","Slovenia","SI","Spain","ES","Sweden","SE"}, 0)) ), AND( F8="K71 Toronto 78 Yorkville Ave Toronto, ON M5R 1B9 Canada Jon Valdez 647-761-2859 jon.valdez@kithnyc.com", ISNUMBER(MATCH(F21, {"United Kingdom","UK","GB","Austria","AT","Belgium","BE","Bulgaria","BG","Croatia","HR","Cyprus","CY","Czech Republic","CZ","Denmark","DK","Estonia","EE","Finland","FI","France","FR","Germany","DE","Greece","GR","Hungary","HU","Ireland","IE","Italy","IT","Latvia","LV","Lithuania","LT","Luxembourg","LU","Malta","MT","Netherlands","NL","Poland","PL","Portugal","PT","Romania","RO","Slovakia","SK","Slovenia","SI","Spain","ES","Sweden","SE"}, 0)) ) ), "IF APPLICABLE - ENTER PREFERENTIAL ORIGIN DECLARATION HERE", "")
A43: DECLARATION: WE DECLARE THAT THIS INVOICE SHOWS THE ACTUAL PRICE OF THE GOODS DESCRIBED AND THAT ALL PARTICULARS ARE TRUE AND CORRECT
A47: SIGNATURE OF SHIPPER/EXPORTER

Sheet Packing List
A1: =Invoice!A1 -> CONTINENT8 PTE LTD
A2: =Invoice!A2 -> 00 TAMPINES AVENUE# 09-02, INCOME AT TAMPINES JUNCTION, SINGAPORE 529693
A3: =Invoice!A3 -> PHONE : 6221 30205577
A5: PACKING LIST
A7: =Invoice!A7 -> MANUFACTURER | F7: =Invoice!F7 -> RECEIVER | P7: INVOICE#: | Q7: =IF(Invoice!A6=0, "", Invoice!A6) -> 0417/E/NAG/0726
A8: =IF(Invoice!B8=0, "", Invoice!B8) -> PT NIRWANA ALABARE GARMENT | F8: =IF(Invoice!F8=0, "", Invoice!F8) -> KDC4 c/o Omlog USA 1000 Rand Blvd., Building 3 Phillipsburg, NJ, 08865 Carmen Amodio 201-552-7208 Carmen.Amodio@omlog.com
A9: =IF(Invoice!B9=0, "", Invoice!B9) -> JL RAYA RANCAEKEK MAJALAYA, 289, SOLOKANJERUK, | P9: INVOICE DATE: | Q9: =IF(Invoice!C6=0, "", Invoice!C6) -> 46219
A10: =IF(Invoice!B10=0, "", Invoice!B10) -> BANDUNG
A11: =IF(Invoice!B11=0, "", Invoice!B11) -> INDONESIA | P11: GROSS WGT (kg): | Q11: =IF(P30=0, "", P30) -> 148.12
A12: =IF(Invoice!B12=0, "", Invoice!B12) -> NENG KURNIA / YULIA VIRA
A13: =IF(Invoice!B13=0, "", Invoice!B13) -> 022 8596-2076 | P13: NET WGT (kg): | Q13: =IF(Q30=0, "", Q30) -> 129.45
A14: CARTON # | B14: DESTINATION | C14: PO # | D14: PRODUCT ID | E14: COLOR NAME | F14: DESCRIPTION | G14: OS | H14: XS | I14: S | J14: M | K14: L | L14: XL | M14: XXL | N14: TTL PER STYLE | O14: # OF CTNS | P14: GROSS WGT PER CARTON (kg) | Q14: NET WGT PER CARTON (kg) | R14: CARTON DIMENSIONS (cm)
A15: 1 | B15: USA (DC 4) | C15: 115154 | D15: KHM034600 | E15: SHADOW | F15: K-TECH | J15: 71 | N15: =SUM(G15:M15) -> 71 | O15: 1 | P15: 10.92 | Q15: 9.61 | R15: 62 X 43 X 25
A16: 2 | B16: USA (DC 4) | C16: 115154 | D16: KHM034600 | E16: SHADOW | F16: K-TECH | K16: 80 | N16: =SUM(G16:M16) -> 80 | O16: 1 | P16: 12.46 | Q16: 11.15 | R16: 62 X 43 X 25
A17: 3 | B17: USA (DC 4) | C17: 115154 | D17: KHM034600 | E17: SHADOW | F17: K-TECH | L17: 80 | N17: =SUM(G17:M17) -> 80 | O17: 1 | P17: 12.93 | Q17: 11.62 | R17: 62 X 43 X 25
A18: 4 | B18: USA (DC 4) | C18: 115154 | D18: KHM034600 | E18: SHADOW | F18: K-TECH | H18: 23 | I18: 48 | J18: =34-29 -> 5 | N18: =SUM(G18:M18) -> 76 | O18: 1 | P18: 10.93 | Q18: 9.62 | R18: 62 X 43 X 25
A19: 5 | B19: USA (DC 4) | C19: 115154 | D19: KHM034600 | E19: SHADOW | F19: K-TECH | J19: =109-80 -> 29 | K19: 44 | N19: =SUM(G19:M19) -> 73 | O19: 1 | P19: 11.43 | Q19: 10.12 | R19: 62 X 43 X 25
A20: 6 | B20: USA (DC 4) | C20: 115154 | D20: KHM034600 | E20: SHADOW | F20: K-TECH | K20: =97-80 -> 17 | L20: 6 | M20: 38 | N20: =SUM(G20:M20) -> 61 | O20: 1 | P20: 10.71 | Q20: 9.4 | R20: 62 X 43 X 25
A21: 7 | B21: USA (DC 4) | C21: 115154 | D21: KHM034600 | E21: HENNA | F21: K-TECH | K21: 51 | N21: =SUM(G21:M21) -> 51 | O21: 1 | P21: 8.74 | Q21: 7.43 | R21: 62 X 43 X 25
A22: 8 | B22: USA (DC 4) | C22: 115154 | D22: KHM034600 | E22: HENNA | F22: K-TECH | H22: 14 | I22: 30 | J22: 36 | N22: =SUM(G22:M22) -> 80 | O22: 1 | P22: 11.74 | Q22: 10.43 | R22: 62 X 43 X 25
A23: 9 | B23: USA (DC 4) | C23: 115154 | D23: KHM034600 | E23: HENNA | F23: K-TECH | J23: 17 | K23: 5 | L23: 33 | N23: =SUM(G23:M23) -> 55 | O23: 1 | P23: 9.66 | Q23: 8.35 | R23: 62 X 43 X 25
A24: 10 | B24: USA (DC 4) | C24: 115154 | D24: KHM034600 | E24: HENNA | F24: K-TECH | L24: 8 | M24: 16 | N24: =SUM(G24:M24) -> 24 | O24: 1 | P24: 5.41 | Q24: 3.77 | R24: 62 X 43 X 25
A25: 11 | B25: USA (DC 4) | C25: 115154 | D25: KHM034601 | E25: SHADOW | F25: K-TECH | J25: 56 | N25: 56 | O25: 1 | P25: 11.19 | Q25: 9.88 | R25: 62 X 43 X 25
A26: 12 | B26: USA (DC 4) | C26: 115154 | D26: KHM034601 | E26: SHADOW | F26: K-TECH | K26: 57 | N26: 57 | O26: 1 | P26: 11.94 | Q26: 10.63 | R26: 62 X 43 X 25
A27: 13 | B27: USA (DC 4) | C27: 115154 | D27: KHM034601 | E27: SHADOW | F27: K-TECH | H27: 20 | I27: 27 | N27: 47 | O27: 1 | P27: 9.37 | Q27: 8.06 | R27: 62 X 43 X 25
A28: 14 | B28: USA (DC 4) | C28: 115154 | D28: KHM034601 | E28: SHADOW | F28: K-TECH | L28: 25 | M28: 20 | N28: 45 | O28: 1 | P28: 10.69 | Q28: 9.38 | R28: 62 X 43 X 25
M30: TTL | N30: =SUM(N15:N29) -> 856 | O30: =SUM(O15:O29) -> 14 | P30: =SUMPRODUCT(O15:O29,P15:P29) -> 148.12 | Q30: =SUMPRODUCT(O15:O29,Q15:Q29) -> 129.45

Sheet Data Validation
A1: REGION OF ULTIMATE DESTINATION
A2: BRUSSELS-CAPITAL REGION
A3: ANTWERP
A4: UN/LOCODE
A5: BE BRU
A6: BE ANR
A7: INCOTERM
A8: EXW
A9: FOB
A10: DAP
A11: DDP
A12: TRANSPORT MODE
... A15: SMALL PARCEL
A17: REGION | B17: BUYER | C17: RECEIVER | D17: IMPORTER | E17: BROKER - AIR & OCEAN | F17: BROKER - SMALL PARCEL | G17: REPRESENTATIVE
A18: US | B18: Kith Logistics LLC 25 Kent Ave, Suite 301 Brooklyn, NY 11249 USA ap@kithnyc.com PH: +1 212 473 4654 | C18: KDC4 c/o Omlog USA 1000 Rand Blvd., Building 3 Phillipsburg, NJ, 08865 Carmen Amodio 201-552-7208 Carmen.Amodio@omlog.com | D18: Kith Logistics LLC 25 Kent Ave, Suite 301 Brooklyn, NY 11249 USA EIN# 81-0814080 | E18: FORWARDER | F18: DHL Express 77 Comair Blvd Erlanger, KY 41018 USA premierteam@dhl.com | G18: -
A19: CA | B19: Kith Logistics LLC 25 Kent Ave, Suite 301 Brooklyn, NY 11249 USA ap@kithnyc.com PH: +1 212 473 4654 | C19: KDC70 c/o Bergen Logistics 3925 Steelers Ave E Brampton, ON L6T 5W5 Canada Shane Francis 3925canada@bergenlogistics.com | D19: Kith Canada Logistics ULC 25 Kent Ave, Suite 301 Brooklyn, NY 11249 USA Importer# 75233 4144 RM0001 | GST/HST# 75233 4144 RT0001 | E19: Savino Del Benne Canada Corp. 175 Clairville Drive Etobicoke, Ontario, M9W 6K9 Zahid Abbasi customstoronto@savinodelbene.com | F19: DHL Express (Canada) Ltd 18 Parkshore Dr Brampton ON, L6T 5M1 Cecile Yantha ddpbrokerage.ca@dhl.com | G19: -
A20: EU | B20: Kith Logistics LLC 25 Kent Ave, Suite 301 Brooklyn, NY 11249 USA ap@kithnyc.com PH: +1 212 473 4654 | C20: KDC20 c/o Bleckmann Industrieweg 38 C 2280 Grobbendonk Belgium Koen Verhoeven customercare.kith.grobbendonk@bleckmann.com | D20: Kith EU Logistics LLC 25 Kent Ave, Suite 301 Brooklyn, NY 11249 USA VAT: BE0754748090 | EORI: BEUS000414 | E20: Bleckmann Customs Department Korte Mate 7-9 BE 9042 Desteldonk Karolina Mielczarek importteam@bleckmann.com | F20: Bleckmann Customs Department Korte Mate 7-9 BE 9042 Desteldonk Karolina Mielczarek importteam@bleckmann.com | G20: Kreston-VDN, Nering 14 1650 Beersel, Belgium
A21: GB | B21: Kith Logistics LLC 25 Kent Ave, Suite 301 Brooklyn, NY 11249 USA ap@kithnyc.com PH: +1 212 473 4654 | C21: KDC30 c/o Bleckmann UK Ltd Plot MPN1 Westland Way Magna Park, Lutterworth LE17 4UE United Kingdom Mark Gamberini mark.gamberini@bleckmann.com, goodsin.uk4@bleckmann.com | D21: Kith EU Logistics LLC 25 Kent Ave, Suite 301 Brooklyn, NY 11249 USA VAT: GB380473393 | EORI: GB380473393000 | E21: Bleckmann UK Plot 2110 Tornado, Magna ParkWellington Parkway, Lutterworth LE17 4XP Rasa Kebleriene uk.customs@bleckmann.com | F21: Bleckmann UK Plot 2110 Tornado, Magna ParkWellington Parkway, Lutterworth LE17 4XP Rasa Kebleriene uk.customs@bleckmann.com | G21: -
A22: HK | B22: Kith Logistics LLC 25 Kent Ave, Suite 301 Brooklyn, NY 11249 USA ap@kithnyc.com PH: +1 212 473 4654 | C22: KDC c/o Omlog Asia Ltd Unit B 2/F, Goodman Western Plaza No. 3 San On Street, Tuen Mun Hong Kong, New Territories Miriam, PH 852 3511 5388 omlog-kithhk@omlogasia.com | D22: Omlog (Asia) Limited 3/F, EW International Tower 120 Texaco Rd Tsuen Wan NT Business Reg.: 50905626-002 | E22: Omlog (Asia) Limited 3/F, EW International Tower 120 Texaco Rd Tsuen Wan NT omlog-kithhk@omlogasia.com | F22: Omlog (Asia) Limited 3/F, EW International Tower 120 Texaco Rd Tsuen Wan NT omlog-kithhk@omlogasia.com | G22: -
A23: US | B23: Kith Logistics LLC 25 Kent Ave, Suite 301 Brooklyn, NY 11249 USA ap@kithnyc.com PH: +1 212 473 4654 | C23: K01WH Soho 644 Broadway New York, NY 10012 David Levy 646-648-6285 EXT. 202 david@kithnyc.com | D23: Kith Logistics LLC 25 Kent Ave, Suite 301 Brooklyn, NY 11249 USA EIN# 81-0814080 | E23: FORWARDER | F23: DHL Express 77 Comair Blvd Erlanger, KY 41018 USA premierteam@dhl.com | G23: -
A24: US | B24: Kith Logistics LLC 25 Kent Ave, Suite 301 Brooklyn, NY 11249 USA ap@kithnyc.com PH: +1 212 473 4654 | C24: K02 LA 8500 Sunset Blvd Los Angeles, CA 90069 Esther Martinez 424-512-2800 esther.m@kithnyc.com | D24: Kith Logistics LLC 25 Kent Ave, Suite 301 Brooklyn, NY 11249 USA EIN# 81-0814080 | E24: FORWARDER | F24: DHL Express 77 Comair Blvd Erlanger, KY 41018 USA premierteam@dhl.com | G24: -
A25: US | B25: Kith Logistics LLC 25 Kent Ave, Suite 301 Brooklyn, NY 11249 USA ap@kithnyc.com PH: +1 212 473 4654 | C25: K04 Kids 62 Bleecker St New York, NY 10012 Jarleny Pichardo 646-889-2900 jarleny.pichardo@kithnyc.com | D25: Kith Logistics LLC 25 Kent Ave, Suite 301 Brooklyn, NY 11249 USA EIN# 81-0814080 | E25: FORWARDER | F25: DHL Express 77 Comair Blvd Erlanger, KY 41018 USA premierteam@dhl.com | G25: -
A26: US | B26: Kith Logistics LLC 25 Kent Ave, Suite 301 Brooklyn, NY 11249 USA ap@kithnyc.com PH: +1 212 473 4654 | C26: K06 Miami 1931 Collins Ave Miami Beach, FL 33139 Joel Jarquin 954-540-9277 joel.jarquin@kithnyc.com | D26: Kith Logistics LLC 25 Kent Ave, Suite 301 Brooklyn, NY 11249 USA EIN# 81-0814080 | E26: FORWARDER | F26: DHL Express 77 Comair Blvd Erlanger, KY 41018 USA premierteam@dhl.com | G26: -
A27: US | B27: Kith Logistics LLC 25 Kent Ave, Suite 301 Brooklyn, NY 11249 USA ap@kithnyc.com PH: +1 212 473 4654 | C27: K07 Brooklyn 233 Flatbush Ave Brooklyn, NY 11217 Alberto Del Moral 917-742-8524 alberto.delmoral@kithnyc.com | D27: Kith Logistics LLC 25 Kent Ave, Suite 301 Brooklyn, NY 11249 USA EIN# 81-0814080 | E27: FORWARDER | F27: DHL Express 77 Comair Blvd Erlanger, KY 41018 USA premierteam@dhl.com | G27: -
A28: US | B28: Kith Logistics LLC 25 Kent Ave, Suite 301 Brooklyn, NY 11249 USA ap@kithnyc.com PH: +1 212 473 4654 | C28: K08 Hawaii Royal Hawaiian Center, 2301 Kalakaua Ave., Bldg. C, Unit CST215 Honolulu, HI 96815 Daniel Bautista 808-769-7964 daniel.b@kithnyc.com | D28: Kith Logistics LLC 25 Kent Ave, Suite 301 Brooklyn, NY 11249 USA EIN# 81-0814080 | E28: FORWARDER | F28: DHL Express 77 Comair Blvd Erlanger, KY 41018 USA premierteam@dhl.com | G28: -
... A35: CA | B35: Kith Logistics LLC 25 Kent Ave, Suite 301 Brooklyn, NY 11249 USA ap@kithnyc.com PH: +1 212 473 4654 | C35: K71 Toronto 78 Yorkville Ave Toronto, ON M5R 1B9 Canada Jon Valdez 647-761-2859 jon.valdez@kithnyc.com | D35: Kith Canada Logistics ULC 25 Kent Ave, Suite 301 Brooklyn, NY 11249 USA Importer# 75233 4144 RM0001 | GST/HST# 75233 4144 RT0001 | E35: Savino Del Benne Canada Corp. 175 Clairville Drive Etobicoke, Ontario, M9W 6K9 Zahid Abbasi customstoronto@savinodelbene.com | F35: DHL Express (Canada) Ltd 18 Parkshore Dr Brampton ON, L6T 5M1 Cecile Yantha ddpbrokerage.ca@dhl.com | G35: -
