Workbook
Name \z: '[1]COAT&WRAP-QIOT-#3'!#REF!
Name ________________________________________________________cao1: #REF!
Name ________________________________________________________cao1: #REF!
Name ________________________________________________________cao2: #REF!
Name ________________________________________________________cao2: #REF!
Name ________________________________________________________cao3: #REF!
Name ________________________________________________________cao3: #REF!
Name ________________________________________________________cao4: #REF!
Name ________________________________________________________cao4: #REF!
Name ________________________________________________________cao5: #REF!
Name ________________________________________________________cao5: #REF!
Name ________________________________________________________cao6: #REF!
Name ________________________________________________________cao6: #REF!
Name ________________________________________________________dai1: #REF!
Name ________________________________________________________dai1: #REF!
Name ________________________________________________________dai2: #REF!
Name ________________________________________________________dai2: #REF!
Name ________________________________________________________dai3: #REF!
Name ________________________________________________________dai3: #REF!
Name ________________________________________________________dai4: #REF!
Name ________________________________________________________dai4: #REF!
Name ________________________________________________________dai5: #REF!
Name ________________________________________________________dai5: #REF!
Name ________________________________________________________dai6: #REF!
Name ________________________________________________________dai6: #REF!
Name ________________________________________________________dan1: #REF!
Name ________________________________________________________dan1: #REF!
Name ________________________________________________________dan2: #REF!
Name ________________________________________________________dan2: #REF!
Name ________________________________________________________phi10: #REF!
Name ________________________________________________________phi10: #REF!
Name ________________________________________________________phi12: #REF!
Name ________________________________________________________phi12: #REF!
Name ________________________________________________________phi14: #REF!
Name ________________________________________________________phi14: #REF!
Name ________________________________________________________phi16: #REF!
Name ________________________________________________________phi16: #REF!
Name ________________________________________________________phi18: #REF!
Name ________________________________________________________phi18: #REF!
Name ________________________________________________________phi20: #REF!
Name ________________________________________________________phi20: #REF!
Name ________________________________________________________phi22: #REF!
Name ________________________________________________________phi22: #REF!
Name ________________________________________________________phi25: #REF!
Name ________________________________________________________phi25: #REF!
Name ________________________________________________________phi28: #REF!
Name ________________________________________________________phi28: #REF!
Name ________________________________________________________phi6: #REF!
Name ________________________________________________________phi6: #REF!
Name ________________________________________________________phi8: #REF!
Name ________________________________________________________phi8: #REF!
Name ________________________________________________________slg1: #REF!
Name ________________________________________________________slg1: #REF!
Name ________________________________________________________slg2: #REF!
Name ________________________________________________________slg2: #REF!
Name ________________________________________________________slg3: #REF!
Name ________________________________________________________slg3: #REF!
Name ________________________________________________________slg4: #REF!
Name ________________________________________________________slg4: #REF!
Name ________________________________________________________slg5: #REF!

Sheet INV
A1: ADVANCE KNITTING VIETNAM CO., LTD
A2: LOT F5-4, THUAN DAO INDUSTRIAL PARK'S EXPANSION PHASE, LONG CANG COMMUNE, TAY NINH PROVINCE, VIETNAM
A3: TEL:(+84)-723-643-733; (+84)-723-643-734 FAX: (+84)-723-643-735
A4: COMMERCIAL INVOICE
A5: Shipper / Exporter: | F5: No. / Date of Invoice :
A6: ADVANCE KNITTING VIETNAM CO.,LTD | F6: =DPK!J7 -> AK/GDI-20260015 | G6: =DPK!L7 -> 46216
A7: LOT F5-4, THUAN DAO INDUSTRIAL PARK'S EXPANSION PHASE, LONG CANG | F7: Contract No. / Date:
A8: COMMUNE, TAY NINH PROVINCE, VIETNAM
A9: TEL:(+84)-723-643-733; (+84)-723-643-734 FAX: (+84)-723-643-735 | F9: =DPK!J12 -> AK/GDI/CT-202603 | G9: =DPK!L12 -> 46163
A10: Buyer:
A11: GDI HK LIMITED
A12: FLAT H, 2/F MANSION INDUSTRIAL BUILDING,
A13: 8 A KUNG NGAM VILLAGE LANE, SHAU KEI WAN, HONG KONG
A15: Consignee: | F15: Term of Delivery: CFR JAKARTA INDONESIA
A16: =DPK!A17 -> PT NIRWANA ALABARE GARMENT | F16: Origin of Goods: Vietnam
A17: =DPK!A18 -> JL. RAYA RANCAEKEK - MAJALAYA , NO.289, DESA SOLOKAN JERUK,
A18: =DPK!A19 -> KECAMATAN SOLOKAN JERUK, KABUPATEN BANDUNG JAWA BARAT
A19: =DPK!A20 -> 40382, INDONESIA
A20: =DPK!A21 -> TAX ID :0745 4069 2644 4000
A21: EMAIL : LUSI@PTNAG.COM YUS.YULIUS@PTNAG.COM
A23: Loading: | C23: Discharge:
A24: =DPK!A26 -> HO CHI MINH | C24: =DPK!E26 -> JAKARTA
C27: Delivery date | D27: ETA:
C28: =DPK!C29 -> 46221 | D28: =DPK!E29 -> 46224 | F28: Term of Payment: By T/T
A29: PO | B29: REF# | C29: ITEM NO | D29: DESCRIPTION OF GOODS | E29: COLOR | F29: SIZE | G29: QUANTITY | H29: Unit | I29: UNIT PRICE (USD) | J29: AMOUNT (USD)
A30: SIOB260507004 | B30: KD00431 265K0076-Upside Chase (MB) S/416363 | C30: 1051120 | D30: 60% BETTER COTTON (BCI) 40% POLYESTER 32S/1x4 PLY FLAT KNIT COLLAR | E30: RED TAPE 729 正红色 | F30: XS | G30: 420 | H30: PCS | I30: 0.195 | J30: =ROUND(G30*I30,2) -> 81.9
A31: SIOB260507004 | B31: KD00431 265K0076-Upside Chase (MB) S/416363 | C31: 1051120 | D31: 60% BETTER COTTON (BCI) 40% POLYESTER 32S/1x4 PLY FLAT KNIT COLLAR | E31: RED TAPE 729 正红色 | F31: XL | G31: 779 | H31: PCS | I31: 0.195 | J31: =ROUND(G31*I31,2) -> 151.91
A32: SIOB260507004 | B32: KD00431 265K0076-Upside Chase (MB) S/416363 | C32: 1051120 | D32: 60% BETTER COTTON (BCI) 40% POLYESTER 32S/1x4 PLY FLAT KNIT COLLAR | E32: RED TAPE 729 正红色 | F32: S | G32: 468 | H32: PCS | I32: 0.195 | J32: =ROUND(G32*I32,2) -> 91.26
A33: SIOB260507004 | B33: KD00431 265K0076-Upside Chase (MB) S/416363 | C33: 1051120 | D33: 60% BETTER COTTON (BCI) 40% POLYESTER 32S/1x4 PLY FLAT KNIT COLLAR | E33: RED TAPE 729 正红色 | F33: XXL | G33: 526 | H33: PCS | I33: 0.195 | J33: =ROUND(G33*I33,2) -> 102.57
A34: SIOB260507004 | B34: KD00431 265K0076-Upside Chase (MB) S/416363 | C34: 1051120 | D34: 60% BETTER COTTON (BCI) 40% POLYESTER 32S/1x4 PLY FLAT KNIT COLLAR | E34: RED TAPE 729 正红色 | F34: M | G34: 507 | H34: PCS | I34: 0.195 | J34: =ROUND(G34*I34,2) -> 98.87
A35: SIOB260507004 | B35: KD00431 265K0076-Upside Chase (MB) S/416363 | C35: 1051120 | D35: 60% BETTER COTTON (BCI) 40% POLYESTER 32S/1x4 PLY FLAT KNIT COLLAR | E35: RED TAPE 729 正红色 | F35: L HUSKY | G35: 133 | H35: PCS | I35: 0.195 | J35: =ROUND(G35*I35,2) -> 25.94
A36: SIOB260507004 | B36: KD00431 265K0076-Upside Chase (MB) S/416363 | C36: 1051120 | D36: 60% BETTER COTTON (BCI) 40% POLYESTER 32S/1x4 PLY FLAT KNIT COLLAR | E36: RED TAPE 729 正红色 | F36: XL HUSKY | G36: 223 | H36: PCS | I36: 0.195 | J36: =ROUND(G36*I36,2) -> 43.49
A37: SIOB260507004 | B37: KD00431 265K0076-Upside Chase (MB) S/416363 | C37: 1051120 | D37: 60% BETTER COTTON (BCI) 40% POLYESTER 32S/1x4 PLY FLAT KNIT COLLAR | E37: RED TAPE 729 正红色 | F37: XXL HUSKY | G37: 158 | H37: PCS | I37: 0.195 | J37: =ROUND(G37*I37,2) -> 30.81
A38: SIOB260507004 | B38: KD00431 265K0076-Upside Chase (MB) S/416363 | C38: 1051120 | D38: 60% BETTER COTTON (BCI) 40% POLYESTER 32S/1x4 PLY FLAT KNIT COLLAR | E38: RED TAPE 729 正红色 | F38: L | G38: 1100 | H38: PCS | I38: 0.195 | J38: =ROUND(G38*I38,2) -> 214.5
A39: SIOB260507004 | B39: KD00431 265K0076-Upside Chase (MB) S/416363 | C39: 1051120 | D39: 60% BETTER COTTON (BCI) 40% POLYESTER 32S/1x4 PLY FLAT KNIT COLLAR | E39: RED TAPE 729 正红色 | F39: L | G39: 1053 | H39: PCS | I39: 0.195 | J39: =ROUND(G39*I39,2) -> 205.34
A40: SIOB260507002 | B40: KD00430 265K0076-A/A5 S/416363 | C40: 1051120 | D40: 60% BETTER COTTON (BCI) 40% POLYESTER 32S/1x4 PLY FLAT KNIT COLLAR | E40: RED TAPE 729 正红色 | F40: XS | G40: 163 | H40: PCS | I40: 0.182 | J40: =ROUND(G40*I40,2) -> 29.67
A41: SIOB260507002 | B41: KD00430 265K0076-A/A5 S/416363 | C41: 1051120 | D41: 60% BETTER COTTON (BCI) 40% POLYESTER 32S/1x4 PLY FLAT KNIT COLLAR | E41: RED TAPE 729 正红色 | F41: S | G41: 668 | H41: PCS | I41: 0.182 | J41: =ROUND(G41*I41,2) -> 121.58
... A158: SIOB260507004 | B158: KD00431 265K0076-Upside Chase (MB) S/416363 | C158: 1051120 | D158: 60% BETTER COTTON (BCI) 40% POLYESTER 32S/1x4 PLY FLAT KNIT COLLAR | E158: PLANT LIFE 978翡翠绿 | F158: XL | G158: 890 | H158: PCS | I158: 0.195 | J158: =ROUND(G158*I158,2) -> 173.55
D159: TOTAL | G159: =SUM(G30:G158) -> 73785 | H159: PCS | I159: USD | J159: =SUM(J30:J158) -> 14164.48
A160: SAY: | B160: US DOLLARS FOURTEEN THOUSAND ONE HUNDRED SIXTY-FOUR AND FORTY-EIGHT CENTS ONLY
A161: PLEASE MAKE PAYMENT TO OUR BANK : JOINT STOCK COMMERCIAL BANK FOR FOREIGN TRADE OF VIET NAM (VIETCOMBANK)
A162: ACCOUNT NO : 0631370457237
I163: ADVANCE KNITTING VIETNAM CO., LTD
I164: Signature, full name, seal

Sheet DPK
A1: ADVANCE KNITTING VIETNAM CO., LTD
A2: LOT F5-4, THUAN DAO INDUSTRIAL PARK'S EXPANSION PHASE, LONG CANG COMMUNE, TAY NINH PROVINCE, VIETNAM
A3: TEL:(+84)-723-643-733; (+84)-723-643-734 FAX: (+84)-723-643-735
A4: PACKING LIST
A6: Shipper / Exporter: | J6: No. / Date of Packing List :
A7: ADVANCE KNITTING VIETNAM CO.,LTD | J7: AK/GDI-20260015 | L7: 46216
A8: LOT F5-4, THUAN DAO INDUSTRIAL PARK'S EXPANSION PHASE, LONG CANG COMMUNE, TAY NINH PROVINCE, VIETNAM | J8: No. / Date of Invoice :
A9: TEL:(+84)-723-643-733; (+84)-723-643-734 FAX: (+84)-723-643-735 | J9: =J7 -> AK/GDI-20260015 | L9: =L7 -> 46216
A10: Buyer:
A11: GDI HK LIMITED | J11: No. / Date of Contract :
A12: FLAT H, 2/F MANSION INDUSTRIAL BUILDING, | J12: AK/GDI/CT-202603 | L12: 46163
A13: 8 A KUNG NGAM VILLAGE LANE, SHAU KEI WAN, HONG KONG
A16: Consignee:
A17: PT NIRWANA ALABARE GARMENT
A18: JL. RAYA RANCAEKEK - MAJALAYA , NO.289, DESA SOLOKAN JERUK,
A19: KECAMATAN SOLOKAN JERUK, KABUPATEN BANDUNG JAWA BARAT
A20: 40382, INDONESIA
A21: TAX ID :0745 4069 2644 4000
A22: EMAIL : LUSI@PTNAG.COM YUS.YULIUS@PTNAG.COM
A25: Loading: | E25: Discharge: | J25: Term of Delivery: | L25: CFR JAKARTA INDONESIA
A26: HO CHI MINH | E26: JAKARTA | J26: Origin of Goods: | L26: Vietnam
J27: PO No:
C28: Delivery date | E28: ETA:
C29: 46221 | E29: =C29+3 -> 46224 | J29: Term of Payment: | K29: By T/T
C30: POLYESTER KNITTED RIB
A31: CARTON NO | B31: PO | C31: DESCRIPTION OF GOODS | D31: ITEM NO | E31: COLOR | F31: SIZE | H31: REF# | I31: Q'TY | J31: UNIT | K31: Net Weight (Kgs) | L31: Gross Weight (Kgs) | M31: Measurements (CBM)
A32: 1 | B32: SIOB260507004 | C32: 60% BETTER COTTON (BCI) 40% POLYESTER 32S/1x4 PLY FLAT KNIT COLLAR | D32: 1051120 | E32: RED TAPE 729 正红色 | F32: XS | G32: 13-1/4"x3.375” | H32: KD00431 265K0076-Upside Chase (MB) S/416363 | I32: =412+8 -> 420 | J32: PCS | K32: =L32-1.4 -> 29.45 | L32: 30.85 | M32: 0.11
B33: SIOB260507004 | C33: 60% BETTER COTTON (BCI) 40% POLYESTER 32S/1x4 PLY FLAT KNIT COLLAR | D33: 1051120 | E33: RED TAPE 729 正红色 | F33: XL | G33: 16"x3.625” | H33: KD00431 265K0076-Upside Chase (MB) S/416363 | I33: =764+15 -> 779 | J33: PCS
A34: 2 | B34: SIOB260507004 | C34: 60% BETTER COTTON (BCI) 40% POLYESTER 32S/1x4 PLY FLAT KNIT COLLAR | D34: 1051120 | E34: RED TAPE 729 正红色 | F34: S | G34: 13-3/4"x3.375” | H34: KD00431 265K0076-Upside Chase (MB) S/416363 | I34: =459+9 -> 468 | J34: PCS | K34: =L34-1.4 -> 24.85 | L34: 26.25 | M34: 0.11
B35: SIOB260507004 | C35: 60% BETTER COTTON (BCI) 40% POLYESTER 32S/1x4 PLY FLAT KNIT COLLAR | D35: 1051120 | E35: RED TAPE 729 正红色 | F35: XXL | G35: 17"x3.625” | H35: KD00431 265K0076-Upside Chase (MB) S/416363 | I35: =516+10 -> 526 | J35: PCS
A36: 3 | B36: SIOB260507004 | C36: 60% BETTER COTTON (BCI) 40% POLYESTER 32S/1x4 PLY FLAT KNIT COLLAR | D36: 1051120 | E36: RED TAPE 729 正红色 | F36: M | G36: 14-1/4"x3.625” | H36: KD00431 265K0076-Upside Chase (MB) S/416363 | I36: =497+10 -> 507 | J36: PCS | K36: =L36-1.4 -> 26.15 | L36: 27.55 | M36: 0.11
B37: SIOB260507004 | C37: 60% BETTER COTTON (BCI) 40% POLYESTER 32S/1x4 PLY FLAT KNIT COLLAR | D37: 1051120 | E37: RED TAPE 729 正红色 | F37: L HUSKY | G37: 15-1/2"x3.625” | H37: KD00431 265K0076-Upside Chase (MB) S/416363 | I37: =130+3 -> 133 | J37: PCS
B38: SIOB260507004 | C38: 60% BETTER COTTON (BCI) 40% POLYESTER 32S/1x4 PLY FLAT KNIT COLLAR | D38: 1051120 | E38: RED TAPE 729 正红色 | F38: XL HUSKY | G38: 16-1/2"x3.625” | H38: KD00431 265K0076-Upside Chase (MB) S/416363 | I38: =219+4 -> 223 | J38: PCS
B39: SIOB260507004 | C39: 60% BETTER COTTON (BCI) 40% POLYESTER 32S/1x4 PLY FLAT KNIT COLLAR | D39: 1051120 | E39: RED TAPE 729 正红色 | F39: XXL HUSKY | G39: 17-1/2"x3.625” | H39: KD00431 265K0076-Upside Chase (MB) S/416363 | I39: =155+3 -> 158 | J39: PCS
A40: 4 | B40: SIOB260507004 | C40: 60% BETTER COTTON (BCI) 40% POLYESTER 32S/1x4 PLY FLAT KNIT COLLAR | D40: 1051120 | E40: RED TAPE 729 正红色 | F40: L | G40: 15"x3.625” | H40: KD00431 265K0076-Upside Chase (MB) S/416363 | I40: 1100 | J40: PCS | K40: =L40-1.4 -> 27.15 | L40: 28.55 | M40: 0.11
A41: 5 | B41: SIOB260507004 | C41: 60% BETTER COTTON (BCI) 40% POLYESTER 32S/1x4 PLY FLAT KNIT COLLAR | D41: 1051120 | E41: RED TAPE 729 正红色 | F41: L | G41: 15"x3.625” | H41: KD00431 265K0076-Upside Chase (MB) S/416363 | I41: =1011+42 -> 1053 | J41: PCS | K41: =L41-1.4 -> 25.95 | L41: 27.35 | M41: 0.11
A42: 6 | B42: SIOB260507002 | C42: 60% BETTER COTTON (BCI) 40% POLYESTER 32S/1x4 PLY FLAT KNIT COLLAR | D42: 1051120 | E42: RED TAPE 729 正红色 | F42: XS | G42: 13-1/4"x3.375” | H42: KD00430 265K0076-A/A5 S/416363 | I42: =160+3 -> 163 | J42: PCS | K42: =L42-1.4 -> 26.7 | L42: 28.1 | M42: 0.11
B43: SIOB260507002 | C43: 60% BETTER COTTON (BCI) 40% POLYESTER 32S/1x4 PLY FLAT KNIT COLLAR | D43: 1051120 | E43: RED TAPE 729 正红色 | F43: S | G43: 13-3/4"x3.375” | H43: KD00430 265K0076-A/A5 S/416363 | I43: =655+13 -> 668 | J43: PCS
B44: SIOB260507002 | C44: 60% BETTER COTTON (BCI) 40% POLYESTER 32S/1x4 PLY FLAT KNIT COLLAR | D44: 1051120 | E44: RED TAPE 729 正红色 | F44: XL | G44: 16"x3.625” | H44: KD00430 265K0076-A/A5 S/416363 | I44: 300 | J44: PCS
B45: SIOB260507002 | C45: 60% BETTER COTTON (BCI) 40% POLYESTER 32S/1x4 PLY FLAT KNIT COLLAR | D45: 1051120 | E45: RED TAPE 729 正红色 | F45: XL HUSKY | G45: 16-1/2"x3.625” | H45: KD00430 265K0076-A/A5 S/416363 | I45: 20 | J45: PCS
A46: 7 | B46: SIOB260507002 | C46: 60% BETTER COTTON (BCI) 40% POLYESTER 32S/1x4 PLY FLAT KNIT COLLAR | D46: 1051120 | E46: RED TAPE 729 正红色 | F46: XL | G46: 16"x3.625” | H46: KD00430 265K0076-A/A5 S/416363 | I46: =1165+29 -> 1194 | J46: PCS | K46: =L46-1.4 -> 31.25 | L46: 32.65 | M46: 0.11
A47: 8 | B47: SIOB260507002 | C47: 60% BETTER COTTON (BCI) 40% POLYESTER 32S/1x4 PLY FLAT KNIT COLLAR | D47: 1051120 | E47: RED TAPE 729 正红色 | F47: M | G47: 14-1/4"x3.625” | H47: KD00430 265K0076-A/A5 S/416363 | I47: =1044+21 -> 1065 | J47: PCS | K47: =L47-1.4 -> 27.65 | L47: 29.05 | M47: 0.11
B48: SIOB260507002 | C48: 60% BETTER COTTON (BCI) 40% POLYESTER 32S/1x4 PLY FLAT KNIT COLLAR | D48: 1051120 | E48: RED TAPE 729 正红色 | F48: L | G48: 15"x3.625” | H48: KD00430 265K0076-A/A5 S/416363 | I48: 100 | J48: PCS
A49: 9 | B49: SIOB260507002 | C49: 60% BETTER COTTON (BCI) 40% POLYESTER 32S/1x4 PLY FLAT KNIT COLLAR | D49: 1051120 | E49: RED TAPE 729 正红色 | F49: L | G49: 15"x3.625” | H49: KD00430 265K0076-A/A5 S/416363 | I49: =1186+26 -> 1212 | J49: PCS | K49: =L49-1.4 -> 29.25 | L49: 30.65 | M49: 0.11
A50: 10 | B50: SIOB260507002 | C50: 60% BETTER COTTON (BCI) 40% POLYESTER 32S/1x4 PLY FLAT KNIT COLLAR | D50: 1051120 | E50: CALLA LILY 451漂白 | F50: XS | G50: 13-1/4"x3.375” | H50: KD00430 265K0076-A/A5 S/416363 | I50: =160+3 -> 163 | J50: PCS | K50: =L50-1.4 -> 26.25 | L50: 27.65 | M50: 0.11
B51: SIOB260507002 | C51: 60% BETTER COTTON (BCI) 40% POLYESTER 32S/1x4 PLY FLAT KNIT COLLAR | D51: 1051120 | E51: CALLA LILY 451漂白 | F51: L | G51: 15"x3.625” | H51: KD00430 265K0076-A/A5 S/416363 | I51: =904+38 -> 942 | J51: PCS
A52: 11 | B52: SIOB260507002 | C52: 60% BETTER COTTON (BCI) 40% POLYESTER 32S/1x4 PLY FLAT KNIT COLLAR | D52: 1051120 | E52: CALLA LILY 451漂白 | F52: L | G52: 15"x3.625” | H52: KD00430 265K0076-A/A5 S/416363 | I52: 1000 | J52: PCS | K52: =L52-1.4 -> 24.15 | L52: 25.55 | M52: 0.11
A53: 12 | B53: SIOB260507002 | C53: 60% BETTER COTTON (BCI) 40% POLYESTER 32S/1x4 PLY FLAT KNIT COLLAR | D53: 1051120 | E53: CALLA LILY 451漂白 | F53: S | G53: 13-3/4"x3.375” | H53: KD00430 265K0076-A/A5 S/416363 | I53: =558+11 -> 569 | J53: PCS | K53: =L53-1.4 -> 27.35 | L53: 28.75 | M53: 0.11
B54: SIOB260507002 | C54: 60% BETTER COTTON (BCI) 40% POLYESTER 32S/1x4 PLY FLAT KNIT COLLAR | D54: 1051120 | E54: CALLA LILY 451漂白 | F54: XL | G54: 16"x3.625” | H54: KD00430 265K0076-A/A5 S/416363 | I54: 600 | J54: PCS
A55: 13 | B55: SIOB260507002 | C55: 60% BETTER COTTON (BCI) 40% POLYESTER 32S/1x4 PLY FLAT KNIT COLLAR | D55: 1051120 | E55: CALLA LILY 451漂白 | F55: XL | G55: 16"x3.625” | H55: KD00430 265K0076-A/A5 S/416363 | I55: 1200 | J55: PCS | K55: =L55-1.4 -> 31.1 | L55: 32.5 | M55: 0.11
A56: 14 | B56: SIOB260507002 | C56: 60% BETTER COTTON (BCI) 40% POLYESTER 32S/1x4 PLY FLAT KNIT COLLAR | D56: 1051120 | E56: CALLA LILY 451漂白 | F56: M | G56: 14-1/4"x3.625” | H56: KD00430 265K0076-A/A5 S/416363 | I56: =779+16 -> 795 | J56: PCS | K56: =L56-1.4 -> 28.6 | L56: 30 | M56: 0.11
B57: SIOB260507002 | C57: 60% BETTER COTTON (BCI) 40% POLYESTER 32S/1x4 PLY FLAT KNIT COLLAR | D57: 1051120 | E57: CALLA LILY 451漂白 | F57: XL | G57: 16"x3.625” | H57: KD00430 265K0076-A/A5 S/416363 | I57: =363+43 -> 406 | J57: PCS
A58: 15 | B58: SIOB260507004 | C58: 60% BETTER COTTON (BCI) 40% POLYESTER 32S/1x4 PLY FLAT KNIT COLLAR | D58: 1051120 | E58: CALLA LILY 451漂白 | F58: XS | G58: 13-1/4"x3.375” | H58: KD00431 265K0076-Upside Chase (MB) S/416363 | I58: =180+4 -> 184 | J58: PCS | K58: =L58-1.4 -> 26.7 | L58: 28.1 | M58: 0.11
B59: SIOB260507004 | C59: 60% BETTER COTTON (BCI) 40% POLYESTER 32S/1x4 PLY FLAT KNIT COLLAR | D59: 1051120 | E59: CALLA LILY 451漂白 | F59: S | G59: 13-3/4"x3.375” | H59: KD00431 265K0076-Upside Chase (MB) S/416363 | I59: =565+11 -> 576 | J59: PCS
B60: SIOB260507004 | C60: 60% BETTER COTTON (BCI) 40% POLYESTER 32S/1x4 PLY FLAT KNIT COLLAR | D60: 1051120 | E60: CALLA LILY 451漂白 | F60: XXL | G60: 17"x3.625” | H60: KD00431 265K0076-Upside Chase (MB) S/416363 | I60: =200+4 -> 204 | J60: PCS
B61: SIOB260507004 | C61: 60% BETTER COTTON (BCI) 40% POLYESTER 32S/1x4 PLY FLAT KNIT COLLAR | D61: 1051120 | E61: CALLA LILY 451漂白 | F61: L HUSKY | G61: 15-1/2"x3.625” | H61: KD00431 265K0076-Upside Chase (MB) S/416363 | I61: =95+2 -> 97 | J61: PCS
B62: SIOB260507004 | C62: 60% BETTER COTTON (BCI) 40% POLYESTER 32S/1x4 PLY FLAT KNIT COLLAR | D62: 1051120 | E62: CALLA LILY 451漂白 | F62: XL HUSKY | G62: 16-1/2"x3.625” | H62: KD00431 265K0076-Upside Chase (MB) S/416363 | I62: =95+2 -> 97 | J62: PCS
A63: 16 | B63: SIOB260507004 | C63: 60% BETTER COTTON (BCI) 40% POLYESTER 32S/1x4 PLY FLAT KNIT COLLAR | D63: 1051120 | E63: CALLA LILY 451漂白 | F63: M | G63: 14-1/4"x3.625” | H63: KD00431 265K0076-Upside Chase (MB) S/416363 | I63: =695+14 -> 709 | J63: PCS | K63: =L63-1.4 -> 23.3 | L63: 24.7 | M63: 0.11
B64: SIOB260507004 | C64: 60% BETTER COTTON (BCI) 40% POLYESTER 32S/1x4 PLY FLAT KNIT COLLAR | D64: 1051120 | E64: CALLA LILY 451漂白 | F64: L | G64: 15"x3.625” | H64: KD00431 265K0076-Upside Chase (MB) S/416363 | I64: =239+45 -> 284 | J64: PCS
A65: 17 | B65: SIOB260507004 | C65: 60% BETTER COTTON (BCI) 40% POLYESTER 32S/1x4 PLY FLAT KNIT COLLAR | D65: 1051120 | E65: CALLA LILY 451漂白 | F65: L | G65: 15"x3.625” | H65: KD00431 265K0076-Upside Chase (MB) S/416363 | I65: 1000 | J65: PCS | K65: =L65-1.4 -> 24.45 | L65: 25.85 | M65: 0.11
A66: 18 | B66: SIOB260507004 | C66: 60% BETTER COTTON (BCI) 40% POLYESTER 32S/1x4 PLY FLAT KNIT COLLAR | D66: 1051120 | E66: CALLA LILY 451漂白 | F66: L | G66: 15"x3.625” | H66: KD00431 265K0076-Upside Chase (MB) S/416363 | I66: 1000 | J66: PCS | K66: =L66-1.4 -> 24.45 | L66: 25.85 | M66: 0.11
A67: 19 | B67: SIOB260507004 | C67: 60% BETTER COTTON (BCI) 40% POLYESTER 32S/1x4 PLY FLAT KNIT COLLAR | D67: 1051120 | E67: CALLA LILY 451漂白 | F67: XL | G67: 16"x3.625” | H67: KD00431 265K0076-Upside Chase (MB) S/416363 | I67: =1205+24 -> 1229 | J67: PCS | K67: =L67-1.4 -> 32.25 | L67: 33.65 | M67: 0.11
A68: 20 | B68: SIOB260507004 | C68: 60% BETTER COTTON (BCI) 40% POLYESTER 32S/1x4 PLY FLAT KNIT COLLAR | D68: 1051120 | E68: MONET BLUE 744油画蓝 | F68: S | G68: 13-3/4"x3.375” | H68: KD00431 265K0076-Upside Chase (MB) S/416363 | I68: =715+14 -> 729 | J68: PCS | K68: =L68-1.4 -> 23.3 | L68: 24.7 | M68: 0.11
B69: SIOB260507004 | C69: 60% BETTER COTTON (BCI) 40% POLYESTER 32S/1x4 PLY FLAT KNIT COLLAR | D69: 1051120 | E69: MONET BLUE 744油画蓝 | F69: XXL | G69: 17"x3.625” | H69: KD00431 265K0076-Upside Chase (MB) S/416363 | I69: =300+6 -> 306 | J69: PCS
A70: 21 | B70: SIOB260507004 | C70: 60% BETTER COTTON (BCI) 40% POLYESTER 32S/1x4 PLY FLAT KNIT COLLAR | D70: 1051120 | E70: MONET BLUE 744油画蓝 | F70: M | G70: 14-1/4"x3.625” | H70: KD00431 265K0076-Upside Chase (MB) S/416363 | I70: =917+18 -> 935 | J70: PCS | K70: =L70-1.4 -> 24.7 | L70: 26.1 | M70: 0.11
B71: SIOB260507004 | C71: 60% BETTER COTTON (BCI) 40% POLYESTER 32S/1x4 PLY FLAT KNIT COLLAR | D71: 1051120 | E71: MONET BLUE 744油画蓝 | F71: XL HUSKY | G71: 16-1/2"x3.625” | H71: KD00431 265K0076-Upside Chase (MB) S/416363 | I71: =135+3 -> 138 | J71: PCS
A72: 22 | B72: SIOB260507004 | C72: 60% BETTER COTTON (BCI) 40% POLYESTER 32S/1x4 PLY FLAT KNIT COLLAR | D72: 1051120 | E72: MONET BLUE 744油画蓝 | F72: L | G72: 15"x3.625” | H72: KD00431 265K0076-Upside Chase (MB) S/416363 | I72: 1000 | J72: PCS | K72: =L72-1.4 -> 24.45 | L72: 25.85 | M72: 0.11
A73: 23 | B73: SIOB260507004 | C73: 60% BETTER COTTON (BCI) 40% POLYESTER 32S/1x4 PLY FLAT KNIT COLLAR | D73: 1051120 | E73: MONET BLUE 744油画蓝 | F73: L | G73: 15"x3.625” | H73: KD00431 265K0076-Upside Chase (MB) S/416363 | I73: =561+31 -> 592 | J73: PCS | K73: =L73-1.4 -> 28.9 | L73: 30.3 | M73: 0.11
B74: SIOB260507004 | C74: 60% BETTER COTTON (BCI) 40% POLYESTER 32S/1x4 PLY FLAT KNIT COLLAR | D74: 1051120 | E74: MONET BLUE 744油画蓝 | F74: XS | G74: 13-1/4"x3.375” | H74: KD00431 265K0076-Upside Chase (MB) S/416363 | I74: =410+8 -> 418 | J74: PCS
B75: SIOB260507004 | C75: 60% BETTER COTTON (BCI) 40% POLYESTER 32S/1x4 PLY FLAT KNIT COLLAR | D75: 1051120 | E75: MONET BLUE 744油画蓝 | F75: XXL HUSKY | G75: 17-1/2"x3.625” | H75: KD00431 265K0076-Upside Chase (MB) S/416363 | I75: =205+4 -> 209 | J75: PCS
A76: 24 | B76: SIOB260507004 | C76: 60% BETTER COTTON (BCI) 40% POLYESTER 32S/1x4 PLY FLAT KNIT COLLAR | D76: 1051120 | E76: MONET BLUE 744油画蓝 | F76: XL | G76: 16"x3.625” | H76: KD00431 265K0076-Upside Chase (MB) S/416363 | I76: =909+18 -> 927 | J76: PCS | K76: =L76-1.4 -> 27.2 | L76: 28.6 | M76: 0.11
B77: SIOB260507004 | C77: 60% BETTER COTTON (BCI) 40% POLYESTER 32S/1x4 PLY FLAT KNIT COLLAR | D77: 1051120 | E77: MONET BLUE 744油画蓝 | F77: L HUSKY | G77: 15-1/2"x3.625” | H77: KD00431 265K0076-Upside Chase (MB) S/416363 | I77: =115+2 -> 117 | J77: PCS
A78: 25 | B78: SIOB260507008 | C78: 60% BETTER COTTON (BCI) 40% POLYESTER 32S/1x4 PLY FLAT KNIT COLLAR | D78: 1051120 | E78: BLACK JACK 400黑色 | F78: XS | G78: 13"x3.375” | H78: KD00433 265K0077-2ND MB S/767468 | I78: =497+10 -> 507 | J78: PCS | K78: =L78-1.4 -> 28.7 | L78: 30.1 | M78: 0.11
B79: SIOB260507008 | C79: 60% BETTER COTTON (BCI) 40% POLYESTER 32S/1x4 PLY FLAT KNIT COLLAR | D79: 1051120 | E79: BLACK JACK 400黑色 | F79: XXL | G79: 15-1/2"x3.625” | H79: KD00433 265K0077-2ND MB S/767468 | I79: =335+7 -> 342 | J79: PCS
B80: SIOB260507008 | C80: 60% BETTER COTTON (BCI) 40% POLYESTER 32S/1x4 PLY FLAT KNIT COLLAR | D80: 1051120 | E80: BLACK JACK 400黑色 | F80: L HUSKY | G80: 15"x3.625” | H80: KD00433 265K0077-2ND MB S/767468 | I80: =95+2 -> 97 | J80: PCS
B81: SIOB260507008 | C81: 60% BETTER COTTON (BCI) 40% POLYESTER 32S/1x4 PLY FLAT KNIT COLLAR | D81: 1051120 | E81: BLACK JACK 400黑色 | F81: XL HUSKY | G81: 16-1/2"x3.625” | H81: KD00433 265K0077-2ND MB S/767468 | I81: =95+2 -> 97 | J81: PCS
B82: SIOB260507008 | C82: 60% BETTER COTTON (BCI) 40% POLYESTER 32S/1x4 PLY FLAT KNIT COLLAR | D82: 1051120 | E82: BLACK JACK 400黑色 | F82: XXL HUSKY | G82: 16-1/2"x3.625” | H82: KD00433 265K0077-2ND MB S/767468 | I82: =145+3 -> 148 | J82: PCS
A83: 26 | B83: SIOB260507008 | C83: 60% BETTER COTTON (BCI) 40% POLYESTER 32S/1x4 PLY FLAT KNIT COLLAR | D83: 1051120 | E83: BLACK JACK 400黑色 | F83: S | G83: 13"x3.375” | H83: KD00433 265K0077-2ND MB S/767468 | I83: =1092+22 -> 1114 | J83: PCS | K83: =L83-1.4 -> 22.2 | L83: 23.6 | M83: 0.11
A84: 27 | B84: SIOB260507008 | C84: 60% BETTER COTTON (BCI) 40% POLYESTER 32S/1x4 PLY FLAT KNIT COLLAR | D84: 1051120 | E84: BLACK JACK 400黑色 | F84: M | G84: 14"x3.625” | H84: KD00433 265K0077-2ND MB S/767468 | I84: =1139+23 -> 1162 | J84: PCS | K84: =L84-1.4 -> 26.9 | L84: 28.3 | M84: 0.11
A85: 28 | B85: SIOB260507008 | C85: 60% BETTER COTTON (BCI) 40% POLYESTER 32S/1x4 PLY FLAT KNIT COLLAR | D85: 1051120 | E85: BLACK JACK 400黑色 | F85: L | G85: 14"x3.625” | H85: KD00433 265K0077-2ND MB S/767468 | I85: =990+20 -> 1010 | J85: PCS | K85: =L85-1.4 -> 23.65 | L85: 25.05 | M85: 0.11
A86: 29 | B86: SIOB260507008 | C86: 60% BETTER COTTON (BCI) 40% POLYESTER 32S/1x4 PLY FLAT KNIT COLLAR | D86: 1051120 | E86: BLACK JACK 400黑色 | F86: XL | G86: 15-1/2"x3.625” | H86: KD00433 265K0077-2ND MB S/767468 | I86: =516+10 -> 526 | J86: PCS | K86: =L86-1.1 -> 13.85 | L86: 14.95 | M86: =65*49*20/1000000 -> 0.0637
A87: 30 | B87: SIOB260507008 | C87: 60% BETTER COTTON (BCI) 40% POLYESTER 32S/1x7 PLY FLAT KNIT COLLAR | D87: 1051123 | E87: CALLA LILY 451漂白 | F87: XS | G87: 13"x3.375” | H87: KD00433 265K0077-2ND MB S/767468 | I87: =618+12 -> 630 | J87: PCS | K87: =L87-1.4 -> 28.7 | L87: 30.1 | M87: 0.11
B88: SIOB260507008 | C88: 60% BETTER COTTON (BCI) 40% POLYESTER 32S/1x7 PLY FLAT KNIT COLLAR | D88: 1051123 | E88: CALLA LILY 451漂白 | F88: XXL | G88: 15-1/2"x3.625” | H88: KD00433 265K0077-2ND MB S/767468 | I88: =385+8 -> 393 | J88: PCS
A89: 31 | B89: SIOB260507008 | C89: 60% BETTER COTTON (BCI) 40% POLYESTER 32S/1x7 PLY FLAT KNIT COLLAR | D89: 1051123 | E89: CALLA LILY 451漂白 | F89: S | G89: 13"x3.375” | H89: KD00433 265K0077-2ND MB S/767468 | I89: 1200 | J89: PCS | K89: =L89-1.4 -> 23.65 | L89: 25.05 | M89: 0.11
A90: 32 | B90: SIOB260507008 | C90: 60% BETTER COTTON (BCI) 40% POLYESTER 32S/1x7 PLY FLAT KNIT COLLAR | D90: 1051123 | E90: CALLA LILY 451漂白 | F90: S | G90: 13"x3.375” | H90: KD00433 265K0077-2ND MB S/767468 | I90: =155+27 -> 182 | J90: PCS | K90: =L90-1.4 -> 30.85 | L90: 32.25 | M90: 0.11
B91: SIOB260507008 | C91: 60% BETTER COTTON (BCI) 40% POLYESTER 32S/1x7 PLY FLAT KNIT COLLAR | D91: 1051123 | E91: CALLA LILY 451漂白 | F91: M | G91: 14"x3.625” | H91: KD00433 265K0077-2ND MB S/767468 | I91: =128+27 -> 155 | J91: PCS
B92: SIOB260507008 | C92: 60% BETTER COTTON (BCI) 40% POLYESTER 32S/1x7 PLY FLAT KNIT COLLAR | D92: 1051123 | E92: CALLA LILY 451漂白 | F92: XL | G92: 15-1/2"x3.625” | H92: KD00433 265K0077-2ND MB S/767468 | I92: =559+11 -> 570 | J92: PCS
B93: SIOB260507008 | C93: 60% BETTER COTTON (BCI) 40% POLYESTER 32S/1x7 PLY FLAT KNIT COLLAR | D93: 1051123 | E93: CALLA LILY 451漂白 | F93: L HUSKY | G93: 15"x3.625” | H93: KD00433 265K0077-2ND MB S/767468 | I93: 102 | J93: PCS
B94: SIOB260507008 | C94: 60% BETTER COTTON (BCI) 40% POLYESTER 32S/1x7 PLY FLAT KNIT COLLAR | D94: 1051123 | E94: CALLA LILY 451漂白 | F94: XL HUSKY | G94: 16-1/2"x3.625” | H94: KD00433 265K0077-2ND MB S/767468 | I94: 102 | J94: PCS
B95: SIOB260507008 | C95: 60% BETTER COTTON (BCI) 40% POLYESTER 32S/1x7 PLY FLAT KNIT COLLAR | D95: 1051123 | E95: CALLA LILY 451漂白 | F95: XXL HUSKY | G95: 16-1/2"x3.625” | H95: KD00433 265K0077-2ND MB S/767468 | I95: =165+3 -> 168 | J95: PCS
A96: 33 | B96: SIOB260507008 | C96: 60% BETTER COTTON (BCI) 40% POLYESTER 32S/1x7 PLY FLAT KNIT COLLAR | D96: 1051123 | E96: CALLA LILY 451漂白 | F96: M | G96: 14"x3.625” | H96: KD00433 265K0077-2ND MB S/767468 | I96: 1200 | J96: PCS | K96: =L96-1.4 -> 27.7 | L96: 29.1 | M96: 0.11
A97: 34 | B97: SIOB260507008 | C97: 60% BETTER COTTON (BCI) 40% POLYESTER 32S/1x7 PLY FLAT KNIT COLLAR | D97: 1051123 | E97: CALLA LILY 451漂白 | F97: L | G97: 14"x3.625” | H97: KD00433 265K0077-2ND MB S/767468 | I97: =1137+23 -> 1160 | J97: PCS | K97: =L97-1.4 -> 26.75 | L97: 28.15 | M97: 0.11
A98: 35 | B98: SIOB260507002 | C98: 60% BETTER COTTON (BCI) 40% POLYESTER 32S/1x4 PLY FLAT KNIT COLLAR | D98: 1051120 | E98: MONET BLUE 744油画蓝 | F98: XS | G98: 13-1/4"x3.375” | H98: KD00430 265K0076-A/A5 S/416363 | I98: =160+3 -> 163 | J98: PCS | K98: =L98-1.4 -> 23.55 | L98: 24.95 | M98: 0.11
B99: SIOB260507002 | C99: 60% BETTER COTTON (BCI) 40% POLYESTER 32S/1x4 PLY FLAT KNIT COLLAR | D99: 1051120 | E99: MONET BLUE 744油画蓝 | F99: S | G99: 13-3/4"x3.375” | H99: KD00430 265K0076-A/A5 S/416363 | I99: =935+19 -> 954 | J99: PCS
A100: 36 | B100: SIOB260507002 | C100: 60% BETTER COTTON (BCI) 40% POLYESTER 32S/1x4 PLY FLAT KNIT COLLAR | D100: 1051120 | E100: MONET BLUE 744油画蓝 | F100: M | G100: 14-1/4"x3.625” | H100: KD00430 265K0076-A/A5 S/416363 | I100: =1208+24 -> 1232 | J100: PCS | K100: =L100-1.4 -> 28.4 | L100: 29.8 | M100: 0.11
A101: 37 | B101: SIOB260507002 | C101: 60% BETTER COTTON (BCI) 40% POLYESTER 32S/1x4 PLY FLAT KNIT COLLAR | D101: 1051120 | E101: MONET BLUE 744油画蓝 | F101: L | G101: 15"x3.625” | H101: KD00430 265K0076-A/A5 S/416363 | I101: 1100 | J101: PCS | K101: =L101-1.4 -> 26.4 | L101: 27.8 | M101: 0.11
A102: 38 | B102: SIOB260507002 | C102: 60% BETTER COTTON (BCI) 40% POLYESTER 32S/1x4 PLY FLAT KNIT COLLAR | D102: 1051120 | E102: MONET BLUE 744油画蓝 | F102: L | G102: 15"x3.625” | H102: KD00430 265K0076-A/A5 S/416363 | I102: =558+33 -> 591 | J102: PCS | K102: =L102-1.4 -> 28.6 | L102: 30 | M102: 0.11
B103: SIOB260507002 | C103: 60% BETTER COTTON (BCI) 40% POLYESTER 32S/1x4 PLY FLAT KNIT COLLAR | D103: 1051120 | E103: MONET BLUE 744油画蓝 | F103: XL | G103: 16"x3.625” | H103: KD00430 265K0076-A/A5 S/416363 | I103: =503+32 -> 535 | J103: PCS
A104: 39 | B104: SIOB260507002 | C104: 60% BETTER COTTON (BCI) 40% POLYESTER 32S/1x4 PLY FLAT KNIT COLLAR | D104: 1051120 | E104: MONET BLUE 744油画蓝 | F104: XL | G104: 16"x3.625” | H104: KD00430 265K0076-A/A5 S/416363 | I104: 1100 | J104: PCS | K104: =L104-1.4 -> 28.6 | L104: 30 | M104: 0.11
A105: 40 | B105: SIOB260507008 | C105: 60% BETTER COTTON (BCI) 40% POLYESTER 32S/1x5 PLY FLAT KNIT COLLAR | D105: 1051121 | E105: PLANT LIFE 978翡翠绿 | F105: XS | G105: 13"x3.375” | H105: KD00433 265K0077-2ND MB S/767468 | I105: =563+11 -> 574 | J105: PCS | K105: =L105-1.4 -> 25.75 | L105: 27.15 | M105: 0.11
...

Sheet PKL 
A1: ADVANCE KNITTING VIETNAM CO., LTD
A2: LOT F5-4, THUAN DAO INDUSTRIAL PARK'S EXPANSION PHASE, LONG CANG COMMUNE, TAY NINH PROVINCE, VIETNAM
A3: TEL:(+84)-723-643-733; (+84)-723-643-734 FAX: (+84)-723-643-735
A4: PACKING LIST
A6: Shipper / Exporter: | I6: No. / Date of Packing List :
A7: ADVANCE KNITTING VIETNAM CO.,LTD | I7: AK/GDI-20260015 | K7: 46216
A8: LOT F5-4, THUAN DAO INDUSTRIAL PARK'S EXPANSION PHASE, LONG CANG COMMUNE, TAY NINH PROVINCE, VIETNAM | I8: No. / Date of Invoice :
A9: TEL:(+84)-723-643-733; (+84)-723-643-734 FAX: (+84)-723-643-735 | I9: =I7 -> AK/GDI-20260015 | K9: =K7 -> 46216
A10: Buyer:
A11: GDI HK LIMITED | I11: No. / Date of Contract :
A12: FLAT H, 2/F MANSION INDUSTRIAL BUILDING, | I12: AK/GDI/CT-202603 | K12: 46163
A13: 8 A KUNG NGAM VILLAGE LANE, SHAU KEI WAN, HONG KONG
A16: Consignee:
A17: PT NIRWANA ALABARE GARMENT
A18: JL. RAYA RANCAEKEK - MAJALAYA , NO.289, DESA SOLOKAN JERUK,
A19: KECAMATAN SOLOKAN JERUK, KABUPATEN BANDUNG JAWA BARAT
A20: 40382, INDONESIA
A21: TAX ID :0745 4069 2644 4000
A22: EMAIL : LUSI@PTNAG.COM YUS.YULIUS@PTNAG.COM
A25: Loading: | E25: Discharge: | I25: Term of Delivery: | K25: CFR JAKARTA INDONESIA
A26: HO CHI MINH | E26: JAKARTA | I26: Origin of Goods: | K26: Vietnam
I27: PO No:
C28: Delivery date | E28: ETA:
C29: 46221 | E29: =C29+3 -> 46224 | I29: Term of Payment: | J29: By T/T
C30: POLYESTER KNITTED RIB
A31: CARTON NO | B31: PO | C31: DESCRIPTION OF GOODS | D31: ITEM NO | E31: COLOR | F31: REF# | G31: TTL CARTONS | H31: Q'TY | I31: UNIT | J31: Net Weight (Kgs) | K31: Gross Weight (Kgs)
B32: SIOB260507002 | C32: 60% BETTER COTTON (BCI) 40% POLYESTER 32S/1x4 PLY FLAT KNIT COLLAR | D32: 1051120 | E32: RED TAPE 729 正红色 | F32: KD00430 265K0076-A/A5 S/416363 | G32: 4 | H32: 4722 | I32: PCS | J32: 114.85 | K32: 120.45
B33: SIOB260507002 | C33: 60% BETTER COTTON (BCI) 40% POLYESTER 32S/1x4 PLY FLAT KNIT COLLAR | D33: 1051120 | E33: CALLA LILY 451漂白 | F33: KD00430 265K0076-A/A5 S/416363 | G33: 5 | H33: 5675 | I33: PCS | J33: 137.45 | K33: 144.45
B34: SIOB260507002 | C34: 60% BETTER COTTON (BCI) 40% POLYESTER 32S/1x4 PLY FLAT KNIT COLLAR | D34: 1051120 | E34: MONET BLUE 744油画蓝 | F34: KD00430 265K0076-A/A5 S/416363 | G34: 5 | H34: 5675 | I34: PCS | J34: 135.55 | K34: 142.55
B35: SIOB260507002 | C35: 60% BETTER COTTON (BCI) 40% POLYESTER 32S/1x4 PLY FLAT KNIT COLLAR | D35: 1051120 | E35: IN THE NAVY 172宝蓝色 | F35: KD00430 265K0076-A/A5 S/416363 | G35: 4 | H35: 4639 | I35: PCS | J35: 115.9 | K35: 121.5
B36: SIOB260507004 | C36: 60% BETTER COTTON (BCI) 40% POLYESTER 32S/1x4 PLY FLAT KNIT COLLAR | D36: 1051120 | E36: RED TAPE 729 正红色 | F36: KD00431 265K0076-Upside Chase (MB) S/416363 | G36: 5 | H36: 5367 | I36: PCS | J36: 133.55 | K36: 140.55
B37: SIOB260507004 | C37: 60% BETTER COTTON (BCI) 40% POLYESTER 32S/1x4 PLY FLAT KNIT COLLAR | D37: 1051120 | E37: CALLA LILY 451漂白 | F37: KD00431 265K0076-Upside Chase (MB) S/416363 | G37: 5 | H37: 5380 | I37: PCS | J37: 131.15 | K37: 138.15
B38: SIOB260507004 | C38: 60% BETTER COTTON (BCI) 40% POLYESTER 32S/1x4 PLY FLAT KNIT COLLAR | D38: 1051120 | E38: MONET BLUE 744油画蓝 | F38: KD00431 265K0076-Upside Chase (MB) S/416363 | G38: 5 | H38: 5371 | I38: PCS | J38: 128.55 | K38: 135.55
B39: SIOB260507004 | C39: 60% BETTER COTTON (BCI) 40% POLYESTER 32S/1x4 PLY FLAT KNIT COLLAR | D39: 1051120 | E39: IN THE NAVY 172宝蓝 | F39: KD00431 265K0076-Upside Chase (MB) S/416363 | G39: 5 | H39: 5355 | I39: PCS | J39: 135.55 | K39: 142.55
B40: SIOB260507004 | C40: 60% BETTER COTTON (BCI) 40% POLYESTER 32S/1x4 PLY FLAT KNIT COLLAR | D40: 1051120 | E40: PLANT LIFE 978翡翠绿 | F40: KD00431 265K0076-Upside Chase (MB) S/416363 | G40: 5 | H40: 5375 | I40: PCS | J40: 128.8 | K40: 135.8
B41: SIOB260507008 | C41: 60% BETTER COTTON (BCI) 40% POLYESTER 32S/1x4 PLY FLAT KNIT COLLAR | D41: 1051120 | E41: BLACK JACK 400黑色 | F41: KD00433 265K0077-2ND MB S/767468 | G41: 5 | H41: 5003 | I41: PCS | J41: 115.3 | K41: 122
B42: SIOB260507008 | C42: 60% BETTER COTTON (BCI) 40% POLYESTER 32S/1x7 PLY FLAT KNIT COLLAR | D42: 1051123 | E42: CALLA LILY 451漂白 | F42: KD00433 265K0077-2ND MB S/767468 | G42: 5 | H42: 5862 | I42: PCS | J42: 137.65 | K42: 144.65
B43: SIOB260507008 | C43: 60% BETTER COTTON (BCI) 40% POLYESTER 32S/1x5 PLY FLAT KNIT COLLAR | D43: 1051121 | E43: PLANT LIFE 978翡翠绿 | F43: KD00433 265K0077-2ND MB S/767468 | G43: 5 | H43: 5551 | I43: PCS | J43: 128.15 | K43: 135.15
... B45: SIOB260507008 | C45: 60% BETTER COTTON (BCI) 40% POLYESTER 32S/1x4 PLY FLAT KNIT COLLAR | D45: 1051120 | E45: IN THE NAVY 172宝蓝 | F45: KD00433 265K0077-2ND MB S/767468 | G45: 4 | H45: 5027 | I45: PCS | J45: 115.95 | K45: 121.55
A46: TOTAL | G46: =SUM(G32:G45) -> 66 | H46: =SUM(H32:H45) -> 73785 | I46: PCS | J46: =SUM(J32:J45) -> 1768.5 | K46: =SUM(K32:K45) -> 1860.6
A47: MADE IN VIETNAM
H48: ADVANCE KNITTING VIETNAM CO., LTD
H49: Signature, full name, seal

Sheet TEM
A1: SHIMADA 4
A2: Carton No | B2: PO NUMBER | D2: DESCRIPTION OF GOODS | E2: PRODUCT CODE | F2: COLOR | H2: SIZE | I2: LOT | J2: Q'TY | K2: UNIT | L2: Net Weight (Kgs) | M2: Gross Weight (Kgs) | N2: Measurements (CBM)
A3: 14 | B3: PO-DMBK-I-2435/25 | C3: ĐƠN 4 | D3: (H25234206(TL-1)) POLYESTER KNITTED RIB SIZE S 100% POLYESTER | E3: H25234206(TL-1) | F3: 1030 | G3: S | H3: 7.5*37.5 CM | I3: GT250128 | J3: 98 | K3: PCS | L3: =M3-1.35 -> 28.95 | M3: 30.3 | N3: 0.11
B4: PO-DMBK-I-2435/25 | C4: ĐƠN 4 | D4: (H25234206(TL-1)) POLYESTER KNITTED RIB SIZE S 100% POLYESTER | E4: H25234206(TL-1) | F4: 1030 | G4: M | H4: 7.5*38.5 CM | I4: GT250128 | J4: 219 | K4: PCS
B5: PO-DMBK-I-2435/25 | C5: ĐƠN 4 | D5: (H25234206(TL-1)) POLYESTER KNITTED RIB SIZE S 100% POLYESTER | E5: H25234206(TL-1) | F5: 1030 | G5: L | H5: 7.5*39.5 CM | I5: GT250128 | J5: 208 | K5: PCS
B6: PO-DMBK-I-2435/25 | C6: ĐƠN 4 | D6: (H25234206(TL-1)) POLYESTER KNITTED RIB SIZE S 100% POLYESTER | E6: H25234206(TL-1) | F6: 1030 | G6: LL | H6: 7.5*40.5 CM | I6: GT250128 | J6: 84 | K6: PCS
B7: PO-DMBK-I-2432/25 | C7: ĐƠN 4 | D7: (H25234110(TM-1)) POLYESTER KNITTED RIB SIZE 3L 100% POLYESTER | E7: H25234110(TM-1) | F7: 1030 | G7: M | H7: 8*41 CM | I7: GT250128 | J7: 209 | K7: PCS
B8: PO-DMBK-I-2432/25 | C8: ĐƠN 4 | D8: (H25234110(TM-1)) POLYESTER KNITTED RIB SIZE 3L 100% POLYESTER | E8: H25234110(TM-1) | F8: 1030 | G8: L | H8: 8*42.5 CM | I8: GT250128 | J8: 412 | K8: PCS
B9: PO-DMBK-I-2432/25 | C9: ĐƠN 4 | D9: (H25234110(TM-1)) POLYESTER KNITTED RIB SIZE 3L 100% POLYESTER | E9: H25234110(TM-1) | F9: 1030 | G9: LL | H9: 8*44 CM | I9: GT250128 | J9: 330 | K9: PCS
B10: PO-DMBK-I-2432/25 | C10: ĐƠN 4 | D10: (H25234110(TM-1)) POLYESTER KNITTED RIB SIZE 3L 100% POLYESTER | E10: H25234110(TM-1) | F10: 1030 | G10: 3L | H10: 8*45.5 CM | I10: GT250128 | J10: 199 | K10: PCS
A11: =COUNT(A3:A10) -> 1 | J11: =SUM(J3:J10) -> 1759 | K11: PCS | L11: =SUM(L3:L10) -> 28.95 | M11: =SUM(M3:M10) -> 30.3 | N11: =SUM(N3:N10) -> 0.11
A12: MADE IN VIETNAM
F13: ADVANCE KNITTING VIETNAM CO., LTD
J14: Signature, full name, seal

Sheet DELIVERY INSTRUCTION
A2: DELIVERY INSTRUCTION
A3: No. | B3: : | C3: =DPK!J7 -> AK/GDI-20260015
A4: Date | B4: : | C4: =DPK!L7 -> 46216
A6: Pursuant to Contract No. | B6: : | C6: AK/GDI/CT-202603 on May. 21, 2025
A9: We (Buyer) hereby | B9: : | C9: =DPK!A11 -> GDI HK LIMITED
C10: ADD: FLAT H, 2/F MANSION INDUSTRIAL BUILDING, 8 A KUNG NGAM VILLAGE LANE, SHAU KEI WAN, HONG KONG
A12: To appoint to Seller | C12: ADVANCE KNITTING VIETNAM CO.,LTD
C13: LOT F5-4, THUAN DAO INDUSTRIAL PARK'S EXPANSION PHASE, LONG CANG COMMUNE, TAY NINH PROVINCE, VIETNAM
C14: TEL:(+84)-723-643-733; (+84)-723-643-734 FAX: (+84)-723-643-735
A15: To release cargo to Consignee | B15: : | C15: =DPK!A17 -> PT NIRWANA ALABARE GARMENT
C16: NO.18 THONG NHAT ROAD, SONG THAN INDUSTRIAL ZONE II,DI AN WARD,
C17: HO CHI MINH CITY, VIETNAM.
C18: TAX CODE :3700346873
C19: TEL :0084-274.3790.780|Ext.:260
A20: Notify party: | C20: KANMAX ENTERPRISES LIMITED
C21: ADD: 60 PAYA LEBAR ROAD, #04-21 PAYA LEBAR SQUARE, SINGAPORE 409051, SINGAPORE.
C22: TEL: 65 6702 1179 FAX : FAX: 65 6702 1182
A23: As the followings
A25: PO | B25: REF# | D25: ITEM NO | E25: DESCRIPTION OF GOODS | F25: COLOR | G25: SIZE | H25: QUANTITY | I25: Unit | J25: UNIT PRICE (USD) | K25: AMOUNT (USD)
A26: SIOB251105016 | B26: KV06800 263K0033-B~E4(3RD MB)/ S/416363 | D26: 1051120 | E26: 60% BETTER COTTON (BCI) 40% POLYESTER 32S/1x4 PLY FLAT KNIT COLLAR | F26: BLACK JACK 400黑色 | G26: XS | H26: 1152 | I26: PCS | J26: 0.17 | K26: =ROUND(H26*J26,3) -> 195.84
A27: SIOB251105016 | B27: KV06800 263K0033-B~E4(3RD MB)/ S/416363 | D27: 1051120 | E27: 60% BETTER COTTON (BCI) 40% POLYESTER 32S/1x4 PLY FLAT KNIT COLLAR | F27: BLACK JACK 400黑色 | G27: S | H27: 2703 | I27: PCS | J27: 0.17 | K27: =ROUND(H27*J27,3) -> 459.51
A28: SIOB251105016 | B28: KV06800 263K0033-B~E4(3RD MB)/ S/416363 | D28: 1051120 | E28: 60% BETTER COTTON (BCI) 40% POLYESTER 32S/1x4 PLY FLAT KNIT COLLAR | F28: BLACK JACK 400黑色 | G28: M | H28: 1869 | I28: PCS | J28: 0.17 | K28: =ROUND(H28*J28,3) -> 317.73
A29: SIOB251105016 | B29: KV06800 263K0033-B~E4(3RD MB)/ S/416363 | D29: 1051120 | E29: 60% BETTER COTTON (BCI) 40% POLYESTER 32S/1x4 PLY FLAT KNIT COLLAR | F29: BLACK JACK 400黑色 | G29: L | H29: 3823 | I29: PCS | J29: 0.17 | K29: =ROUND(H29*J29,3) -> 649.91
A30: SIOB251105016 | B30: KV06800 263K0033-B~E4(3RD MB)/ S/416363 | D30: 1051120 | E30: 60% BETTER COTTON (BCI) 40% POLYESTER 32S/1x4 PLY FLAT KNIT COLLAR | F30: BLACK JACK 400黑色 | G30: XL | H30: 2332 | I30: PCS | J30: 0.17 | K30: =ROUND(H30*J30,3) -> 396.44
A31: SIOB251105016 | B31: KV06800 263K0033-B~E4(3RD MB)/ S/416363 | D31: 1051120 | E31: 60% BETTER COTTON (BCI) 40% POLYESTER 32S/1x4 PLY FLAT KNIT COLLAR | F31: BLACK JACK 400黑色 | G31: XXL | H31: 1744 | I31: PCS | J31: 0.17 | K31: =ROUND(H31*J31,3) -> 296.48
A32: SIOB251105016 | B32: KV06800 263K0033-B~E4(3RD MB)/ S/416363 | D32: 1051120 | E32: 60% BETTER COTTON (BCI) 40% POLYESTER 32S/1x4 PLY FLAT KNIT COLLAR | F32: BLACK JACK 400黑色 | G32: L HUSKY | H32: 205 | I32: PCS | J32: 0.17 | K32: =ROUND(H32*J32,3) -> 34.85
A33: SIOB251105016 | B33: KV06800 263K0033-B~E4(3RD MB)/ S/416363 | D33: 1051120 | E33: 60% BETTER COTTON (BCI) 40% POLYESTER 32S/1x4 PLY FLAT KNIT COLLAR | F33: BLACK JACK 400黑色 | G33: XL HUSKY | H33: 147 | I33: PCS | J33: 0.17 | K33: =ROUND(H33*J33,3) -> 24.99
A34: SIOB251105016 | B34: KV06800 263K0033-B~E4(3RD MB)/ S/416363 | D34: 1051120 | E34: 60% BETTER COTTON (BCI) 40% POLYESTER 32S/1x4 PLY FLAT KNIT COLLAR | F34: BLACK JACK 400黑色 | G34: XXL HUSKY | H34: 186 | I34: PCS | J34: 0.17 | K34: =ROUND(H34*J34,3) -> 31.62
B35: TOTAL | H35: =SUM(H26:H34) -> 14161 | I35: PCS | J35: USD | K35: =SUM(K26:K34) -> 2407.37
A38: AMOUNT IN WORDS | C38: =INV!#REF! -> #REF!
A39: ARTICLE 2: ORIGIN OF VIETNAM
A40: ARTICLE 3: PACKING | C40: Export Standard Packing
A41: ARTICLE 4: DELIVERY AND PAYMENT
A42: *Delivery | C42: By Truck/ Lalamove
A43: *Delivery Time | C43: =DPK!E29 -> 46224
A44: *Delivery Term | C44: DAP HO CHI MINH
A45: *Bill To | C45: =C9 -> GDI HK LIMITED
A46: We kindly request the relevant parties to perform the delivery and receipt of goods in accordance with the above instruction and comply with the customs
A48: For and on behalf of Buyer

Sheet SC
A1: ADVANCE KNITTING VIETNAM CO., LTD
A2: LOT F5-4, THUAN DAO INDUSTRIAL PARK'S EXPANSION PHASE, LONG CANG COMMUNE, TAY NINH PROVINCE, VIETNAM
A3: TEL:(+84)-723-643-733; (+84)-723-643-734 FAX: (+84)-723-643-735
A4: SALE CONTRACT
A6: BUYER: GDI HK LIMITED | H6: No: | I6: SIOB251103005-1
A7: FLAT H, 2/F MANSION INDUSTRIAL BUILDING, 8 A KUNG NGAM VILLAGE LANE, SHAU KEI WAN, HONG KONG | H7: Date: | I7: 46018
A9: BASE ON PO NO SIOB251103005 SIGNED ON NOVEMBER 03, 2025 ; ADVANCE KNITTING VIETNAM CO.,LTD AS SELLER , HEREBY CONFIRMS HAVING SOLD THE REMAIN QUANTITY OF THIS PO TO YOUR FIRM
A10: THE FOLLOWING GOODS BY CONTRACT OF SALE MADE ON THE ABOVE DATE AND ON THE TERNMS AND
A11: CONDITIONS HEREAFTER SET FORTH:
A12: COMMODITY | C12: : | D12: CLOTHING ACCESSORIES
A14: PO | B14: REF# | C14: ITEM NO | D14: DESCRIPTION OF GOODS | E14: COLOR | F14: SIZE | G14: QUANTITY | H14: Unit | I14: UNIT PRICE (USD) | J14: AMOUNT (USD)
A15: SIOB251103005 | B15: KV06798 263K0033-A2+~A4(1ST LOT)/S/416363 | C15: 1051120 | D15: 60% BETTER COTTON (BCI) 40% POLYESTER 32S/1x4 PLY FLAT KNIT COLLAR | E15: MONET BLUE 744油画蓝 | F15: XL | G15: 41 | H15: PCS | I15: 0.17 | J15: 6.97
A16: SIOB251103005 | B16: KV06798 263K0033-A2+~A4(1ST LOT)/S/416363 | C16: 1051120 | D16: 60% BETTER COTTON (BCI) 40% POLYESTER 32S/1x4 PLY FLAT KNIT COLLAR | E16: MONET BLUE 744油画蓝 | F16: XXL | G16: 12 | H16: PCS | I16: 0.17 | J16: 2.04
A17: SIOB251103005 | B17: KV06798 263K0033-A2+~A4(1ST LOT)/S/416363 | C17: 1051120 | D17: 60% BETTER COTTON (BCI) 40% POLYESTER 32S/1x4 PLY FLAT KNIT COLLAR | E17: BLACK JACK 400黑色 | F17: S | G17: 123 | H17: PCS | I17: 0.17 | J17: 20.91
A18: SIOB251103005 | B18: KV06798 263K0033-A2+~A4(1ST LOT)/S/416363 | C18: 1051120 | D18: 60% BETTER COTTON (BCI) 40% POLYESTER 32S/1x4 PLY FLAT KNIT COLLAR | E18: BLACK JACK 400黑色 | F18: XL HUSKY | G18: 52 | H18: PCS | I18: 0.17 | J18: 8.84
A19: SIOB251103005 | B19: KV06798 263K0033-A2+~A4(1ST LOT)/S/416363 | C19: 1051120 | D19: 60% BETTER COTTON (BCI) 40% POLYESTER 32S/1x4 PLY FLAT KNIT COLLAR | E19: BLACK JACK 400黑色 | F19: XXL HUSKY | G19: 31 | H19: PCS | I19: 0.17 | J19: 5.27
C20: TOTAL | G20: =SUM(G15:G19) -> 259 | H20: PCS | I20: USD | J20: =SUM(J15:J19) -> 44.03
A23: QUALITY | C23: : | D23: AS PER ADVANCE KNITTING VIETNAM'S STANDARD GRADE
A24: QUANTITY | C24: : | D24: =G20 -> 259 | E24: PCS
A25: PACKING MARKING | C25: : | D25: EXPORT STANDARD PACKING IN TRUCK
A26: TOTAL AMOUNT OF CONTRACT | C26: : | D26: =J20 -> 44.03
D27: US DOLLAR FORTY FOUR AND THREE CENTS ONLY.
A28: TERMS OF PAYMENT | C28: : | D28: T/T 100% PAYMENT WITHIN 30 DAYS DELIVERY
A29: DELIVERY PLACE: | C29: : | D29: BUYER NOMINATE SELLER DELIVER GOODS TO CONSIGNEE BELOW:
D30: CHUTEX INTERNATIONAL CO.,LTD
D31: NO.18 THONG NHAT ROAD, SONG THAN INDUSTRIAL ZONE II,DI AN WARD,
D32: HO CHI MINH CITY, VIETNAM.
A33: DELIVERY TERM: | D33: DAP HO CHI MINH
A34: NOTIFY PARTY (IF NEEDED) | D34: =DPK!#REF! -> #REF!
D35: =DPK!#REF! -> #REF!
D36: =DPK!#REF! -> #REF!
A37: OUR BANK | C37: : | D37: JOINT STOCK COMMERCIAL BANK FOR FOREIGN TRADE OF VIET NAM (VIETCOMBANK)
A38: BRANCH | C38: : | D38: 2A PHAM VAN NGU STREET, BEN LUC DISTRICT, LONG AN PROVINCE, VIET NAM
A39: ACCOUNT NO. | C39: : | D39: 0631370457237
A40: SWIFT CODE | C40: : | D40: BFTVVNVX
A41: TIME OF SHIPMENT | C41: : | D41: =DPK!C29 -> 46221
A42: FROM | C42: : | D42: TAY NINH
A43: DESTINATION : | C43: : | D43: HO CHI MINH
A44: INSPECTION | C44: : | D44: ADVANCE KNITTING VIETNAM FACTORY 'S INSPECTION TO BE TAKEN AS FINAL
A45: OTHER CONDITIONS | C45: : | D45: PRICE ADJUSTMENT FOR INFERIOR PRODUCTS IF ANY SHALL BE SETTLED BY THE
D46: SELLER BASED ON MUTUAL BENEFIT AND AMICABLE NEGOTIATION DURING TRANSACTION
D47: TERMS OF PAYMENT ALSO CAN BE MADE BY BALANCE SETTLE.
A48: Accepted and confirmed by | F48: Accepted and confirmed by
A49: ( BUYER) | F49: ( SELLER)

Sheet IN PHIẾU XUẤT 
I1: Mẫu số: 02-VT
D2: 出货明细 PHIẾU XUẤT KHO | I2: (Ban hành theo TT số: 200/2014/TT-BTC)
A3: Lô F5-4, KCN Thuận Đạo, huyện Cần Đước, tỉnh Long An | I3: Ngày 22/12/2014 của bộ trưởng BTC
C4: =NOW() -> 46218.415 | I4: Nợ……………...........
C5: PXK:SH28032025 | I5: Có……………............
A6: Họ tên người nhận hàng 领料员: | H6: PO:
A7: Khách hàng/ Bộ phận 部门SHIMADA SHOJI (VIETNAM) CO., LTD | H7: Biển kiểm soát :
A8: Địa chỉ 地址Lô số 21-1, 21-2 và 21-3, Đường số 8B, Khu Công Nghiệp Quốc Tế Protrade,Xã An Tây, Thị xã Bến Cát, T.BD.VN
A9: Lý do xuất kho: | C9: XUẤT THÀNH PHẨM 出口成品
A10: Xuất tại kho: | C10: CÔNG TY TNHH ADVANCE KNITTING VIỆT NAM
A11: Ghi chú备注: 15 THÙNG
A12: STT | B12: PO | C12: 色號 Mã màu | D12: 缸号 Mã Lot | E12: 尺寸 Quy cách | G12: 单位 Đơn vị | H12: 数量 Số lượng | I12: Ghi chú 备注
H13: 良品数量 Thực xuất
A14: 1 | B14: PO-DMBK-I-1669(HN)/25 | C14: NVY | D14: GT240114 | E14: 140MMX500MM | G14: PCS | H14: 238
A15: 2 | B15: PO-DMBK-I-1669(HN)/25 | C15: WHT | D15: GT240815 | E15: 140MMX500MM | G15: PCS | H15: 361
A16: 3 | B16: PO-DMBK-I-1669(HN)/25 | C16: ABN | D16: GT250221 | E16: 140MMX500MM | G16: PCS | H16: 64
A17: 4 | B17: PO-DMBK-I-2418/25 | C17: 1120(NAVY) | D17: GT250204 | E17: M | F17: 6.5X50CM | G17: PCS | H17: 214
A18: 5 | B18: PO-DMBK-I-2418/25 | C18: 1120(NAVY) | D18: GT250204 | E18: L | F18: 6.5X50CM | G18: PCS | H18: 353
A19: 6 | B19: PO-DMBK-I-2418/25 | C19: 1120(NAVY) | D19: GT250204 | E19: LL | F19: 6.5X50CM | G19: PCS | H19: 177
A20: 7 | B20: PO-DMBK-I-2418/25 | C20: 1120(NAVY) | D20: GT250204 | E20: 3L | F20: 6.5X50CM | G20: PCS | H20: 96
A21: 8 | B21: PO-DMBK-I-2418/25 | C21: 1030(WHITE) | D21: GT250204 | E21: M | F21: 6.5X50CM | G21: PCS | H21: 298
A22: 9 | B22: PO-DMBK-I-2418/25 | C22: 1030(WHITE) | D22: GT250204 | E22: L | F22: 6.5X50CM | G22: PCS | H22: 496
A23: 10 | B23: PO-DMBK-I-2418/25 | C23: 1030(WHITE) | D23: GT250204 | E23: LL | F23: 6.5X50CM | G23: PCS | H23: 247
A24: 11 | B24: PO-DMBK-I-2418/25 | C24: 1030(WHITE) | D24: GT250204 | E24: 3L | F24: 6.5X50CM | G24: PCS | H24: 129
A25: 12 | B25: PO-DMBK-I-2418/25 | C25: 1140(GREEN) | D25: GT250204 | E25: M | F25: 6.5X50CM | G25: PCS | H25: 162
A26: 13 | B26: PO-DMBK-I-2418/25 | C26: 1140(GREEN) | D26: GT250204 | E26: L | F26: 6.5X50CM | G26: PCS | H26: 272
A27: 14 | B27: PO-DMBK-I-2418/25 | C27: 1140(GREEN) | D27: GT250204 | E27: LL | F27: 6.5X50CM | G27: PCS | H27: 135
A28: 15 | B28: PO-DMBK-I-2418/25 | C28: 1140(GREEN) | D28: GT250204 | E28: 3L | F28: 6.5X50CM | G28: PCS | H28: 71
... A32: 19 | B32: PO-DMBK-I-2418/25 | C32: 1110(RED) | D32: GT250204 | E32: 3L | F32: 6.5X50CM | G32: PCS | H32: 47
A33: 20 | B33: PO-DMBK-I-2435/25 | C33: 1030 | D33: GT250128 | E33: S | F33: 7.5*37.5 CM | G33: PCS | H33: 98
A34: 21 | B34: PO-DMBK-I-2435/25 | C34: 1030 | D34: GT250128 | E34: M | F34: 7.5*38.5 CM | G34: PCS | H34: 219
A35: 22 | B35: PO-DMBK-I-2435/25 | C35: 1030 | D35: GT250128 | E35: L | F35: 7.5*39.5 CM | G35: PCS | H35: 208
A36: 23 | B36: PO-DMBK-I-2435/25 | C36: 1030 | D36: GT250128 | E36: LL | F36: 7.5*40.5 CM | G36: PCS | H36: 84
A37: 24 | B37: PO-DMBK-I-2432/25 | C37: 1030 | D37: GT250128 | E37: M | F37: 8*41 CM | G37: PCS | H37: 209
A38: 25 | B38: PO-DMBK-I-2432/25 | C38: 1030 | D38: GT250128 | E38: L | F38: 8*42.5 CM | G38: PCS | H38: 412
A39: 26 | B39: PO-DMBK-I-2432/25 | C39: 1030 | D39: GT250128 | E39: LL | F39: 8*44 CM | G39: PCS | H39: 330
A40: 27 | B40: PO-DMBK-I-2432/25 | C40: 1030 | D40: GT250128 | E40: 3L | F40: 8*45.5 CM | G40: PCS | H40: 199
A41: 28 | B41: PO-DMBK-I-2435/25 | C41: 1120 | D41: GT250128 | E41: S | F41: 7.5*37.5 CM | G41: PCS | H41: 42
A42: 29 | B42: PO-DMBK-I-2435/25 | C42: 1120 | D42: GT250128 | E42: M | F42: 7.5*38.5 CM | G42: PCS | H42: 112
A43: 30 | B43: PO-DMBK-I-2435/25 | C43: 1120 | D43: GT250128 | E43: L | F43: 7.5*39.5 CM | G43: PCS | H43: 105
A44: 31 | B44: PO-DMBK-I-2435/25 | C44: 1120 | D44: GT250128 | E44: LL | F44: 7.5*40.5 CM | G44: PCS | H44: 40
... A53: 40 | B53: PO-DMBK-I-2435/25 | C53: 1120 | D53: GT250204 | E53: LL | F53: 7.5*40.5 CM | G53: PCS | H53: 7
A54: 41 | B54: PO-DMBK-I-1668/25 | C54: ABN | D54: GT250218 GT240815 | E54: 100MM*600MM | G54: PCS | H54: 1917 | I54: THIẾU 800
A55: 42 | B55: PO-DMBK-I-1668/25 | C55: DBL | D55: GT250114 GT240815 | E55: 100MM*600MM | G55: PCS | H55: 1231
A56: 43 | B56: PO-DMBK-I-1668/25 | C56: WHT | D56: GT250114 GT240815 | E56: 100MM*600MM | G56: PCS | H56: 1658 | I56: THIẾU 200
A57: 44 | B57: PO-DMBK-I-1668/25 | C57: BLK | D57: GT250218 GT240815 | E57: 100MM*600MM | G57: PCS | H57: 3545 | L57: =1300+16749 -> 18049
A58: 45 | B58: PO-DMBK-I-1668/25 | C58: BLK | D58: GT250218 | E58: 110MM*800MM | G58: PCS | H58: 1907 | I58: THIẾU 300
A59: 金额 Tổng | H59: =SUM(H14:H58) -> 16749
B60: Tổng Tiền: | C60: =F66 -> Không đồng.
A61: =J59 -> 0 | C61: =RIGHT("000000000000"&ROUND(A61,0),12) -> 000000000000 | F61: 1 | G61: 2 | H61: 3 | I61: 4 | J61: 5 | K61: 6 | L61: 7 | M61: 8 | N61: 9 | O61: 10 | P61: 11 | Q61: 12
F62: =VALUE(MID(C61,F61,1)) -> 0 | G62: =VALUE(MID(C61,G61,1)) -> 0 | H62: =VALUE(MID(C61,H61,1)) -> 0 | I62: =VALUE(MID(C61,I61,1)) -> 0 | J62: =VALUE(MID(C61,J61,1)) -> 0 | K62: =VALUE(MID(C61,K61,1)) -> 0 | L62: =VALUE(MID(C61,L61,1)) -> 0 | M62: =VALUE(MID(C61,M61,1)) -> 0 | N62: =VALUE(MID(C61,N61,1)) -> 0 | O62: =VALUE(MID(C61,O61,1)) -> 0 | P62: =VALUE(MID(C61,P61,1)) -> 0 | Q62: =VALUE(MID(C61,Q61,1)) -> 0
F63: =SUM(F62:F62) -> 0 | G63: =SUM(F62:G62) -> 0 | H63: =SUM(F62:H62) -> 0 | I63: =SUM(I62:I62) -> 0 | J63: =SUM(I62:J62) -> 0 | K63: =SUM(I62:K62) -> 0 | L63: =SUM(L62:L62) -> 0 | M63: =SUM(L62:M62) -> 0 | N63: =SUM(L62:N62) -> 0 | O63: =SUM(O62:O62) -> 0 | P63: =SUM(O62:P62) -> 0 | Q63: =SUM(O62:Q62) -> 0
F64: =IF(F62=0,"",CHOOSE(F62,"một","hai","ba","bốn","năm","sáu","bảy","tám","chín")) | G64: =IF(G62=0,IF(AND(F62<>0,H62<>0),"lẻ",""),CHOOSE(G62,"mười","hai","ba","bốn","năm","sáu","bảy","tám","chín")) | H64: =IF(H62=0,"",CHOOSE(H62,IF(G62>1,"mốt","một"),"hai","ba","bốn",IF(G62=0,"năm","lăm"),"sáu","bảy","tám","chín")) | I64: =IF(I62=0,"",CHOOSE(I62,"một","hai","ba","bốn","năm","sáu","bảy","tám","chín")) | J64: =IF(J62=0,IF(AND(I62<>0,K62<>0),"lẻ",""),CHOOSE(J62,"mười","hai","ba","bốn","năm","sáu","bảy","tám","chín")) | K64: =IF(K62=0,"",CHOOSE(K62,IF(J62>1,"mốt","một"),"hai","ba","bốn",IF(J62=0,"năm","lăm"),"sáu","bảy","tám","chín")) | L64: =IF(L62=0,"",CHOOSE(L62,"một","hai","ba","bốn","năm","sáu","bảy","tám","chín")) | M64: =IF(M62=0,IF(AND(L62<>0,N62<>0),"lẻ",""),CHOOSE(M62,"mười","hai","ba","bốn","năm","sáu","bảy","tám","chín")) | N64: =IF(N62=0,"",CHOOSE(N62,IF(M62>1,"mốt","một"),"hai","ba","bốn",IF(M62=0,"năm","lăm"),"sáu","bảy","tám","chín")) | O64: =IF(O62=0,"",CHOOSE(O62,"một","hai","ba","bốn","năm","sáu","bảy","tám","chín")) | P64: =IF(P62=0,IF(AND(O62<>0,Q62<>0),"lẻ",""),CHOOSE(P62,"mười","hai","ba","bốn","năm","sáu","bảy","tám","chín")) | Q64: =IF(Q62=0,"",CHOOSE(Q62,IF(P62>1,"mốt","một"),"hai","ba","bốn",IF(P62=0,"năm","lăm"),"sáu","bảy","tám","chín"))
F65: =IF(F62=0,"","trăm") | G65: =IF(G62=0,"",IF(G62=1,"","mươi")) | H65: =IF(AND(H62=0,H63=0),"","tỷ") | I65: =IF(I62=0,"","trăm") | J65: =IF(J62=0,"",IF(J62=1,"","mươi")) | K65: =IF(AND(K62=0,K63=0),"","triệu") | L65: =IF(L62=0,"","trăm") | M65: =IF(M62=0,"",IF(M62=1,"","mươi")) | N65: =IF(AND(N62=0,N63=0),"","nghìn") | O65: =IF(O62=0,"","trăm") | P65: =IF(P62=0,"",IF(P62=1,"","mươi")) | Q65: đồng./.
F66: =UPPER(LEFT(TRIM(IF(A61=0,"không đồng.",F64&" "&F65&" "&G64&" "&G65&" "&H64&" "&H65&" "&I64&" "&I65&" "&J64&" "&J65&" "&K64&" "&K65&" "&L64&" "&L65&" "&M64&" "&M65&" "&N64&" "&N65&" "&O64&" "&O65&" "&P64&" "&P65&" "&Q64&" "&Q65)),1))&RIGHT(TRIM(IF(A61=0,"không đồng.",F64&" "&F65&" "&G64&" "&G65&" "&H64&" "&H65&" "&I64&" "&I65&" "&J64&" "&J65&" "&K64&" "&K65&" "&L64&" "&L65&" "&M64&" "&M65&" "&N64&" "&N65&" "&O64&" "&O65&" "&P64&" "&P65&" "&Q64&" "&Q65)),LEN(TRIM(IF(A61=0,"không đồng.",F64&" "&F65&" "&G64&" "&G65&" "&H64&" "&H65&" "&I64&" "&I65&" "&J64&" "&J65&" "&K64&" "&K65&" "&L64&" "&L65&" "&M64&" "&M65&" "&N64&" "&N65&" "&O64&" "&O65&" "&P64&" "&P65&" "&Q64&" "&Q65)))-1) -> Không đồng.
A67: 收货人 người nhận hàng | C67: 负担人 người lập phiếu | F67: 仓管 Quản kho | J67: 批准 Phê Chuẩn
C70: CHÂU QUANG TRÊN | F70: TRƯƠNG TẤN ĐẠT | I70: =NOW() -> 46218.415
I71: FAN SENG FATT
