Workbook
Name \d: '[7]??-BLDG'!#REF!
Name \d: '[7]??-BLDG'!#REF!
Name \e: '[7]??-BLDG'!#REF!
Name \e: '[7]??-BLDG'!#REF!
Name \f: '[7]??-BLDG'!#REF!
Name \f: '[7]??-BLDG'!#REF!
Name \g: '[7]??-BLDG'!#REF!
Name \g: '[7]??-BLDG'!#REF!
Name \h: '[7]??-BLDG'!#REF!
Name \h: '[7]??-BLDG'!#REF!
Name \i: '[7]??-BLDG'!#REF!
Name \i: '[7]??-BLDG'!#REF!
Name \j: '[7]??-BLDG'!#REF!
Name \j: '[7]??-BLDG'!#REF!
Name \k: '[7]??-BLDG'!#REF!
Name \k: '[7]??-BLDG'!#REF!
Name \l: '[7]??-BLDG'!#REF!
Name \l: '[7]??-BLDG'!#REF!
Name \m: '[7]??-BLDG'!#REF!
Name \m: '[7]??-BLDG'!#REF!
Name \n: '[7]??-BLDG'!#REF!
Name \n: '[7]??-BLDG'!#REF!
Name \o: '[7]??-BLDG'!#REF!
Name \o: '[7]??-BLDG'!#REF!
Name \p: '[8]FA-LISTING'!#REF!
Name \p: '[8]FA-LISTING'!#REF!
Name ____CON1: #REF!
Name ____CON2: #REF!
Name ____lap1: #REF!
Name ____lap2: #REF!
Name ____SHR1: #REF!
Name ____SHR2: #REF!
Name ____tax1: #REF!
Name ____tax2: #REF!
Name ____tax3: #REF!
Name ____tax4: #REF!
Name ___BTM250: #REF!
Name ___CON1: #REF!
Name ___CON2: #REF!
Name ___gon4: #REF!
Name ___lap1: #REF!
Name ___lap2: #REF!
Name ___NET2: #REF!
Name ___SHR1: #REF!
Name ___SHR2: #REF!
Name ___tax1: #REF!
Name ___tax2: #REF!
Name ___tax3: #REF!
Name ___tax4: #REF!
Name __A65700: '[1]MTO REV.2(ARMOR)'!#REF!
Name __A65800: '[1]MTO REV.2(ARMOR)'!#REF!
Name __A66000: '[1]MTO REV.2(ARMOR)'!#REF!
Name __A67000: '[1]MTO REV.2(ARMOR)'!#REF!
Name __A68000: '[1]MTO REV.2(ARMOR)'!#REF!
Name __A70000: '[1]MTO REV.2(ARMOR)'!#REF!
Name __A75000: '[1]MTO REV.2(ARMOR)'!#REF!
Name __A85000: '[1]MTO REV.2(ARMOR)'!#REF!
Name __BTM250: #REF!
Name __BTM250: #REF!
Name __BTM250: #REF!

Sheet INV 
F1: COMMERCIAL INVOICE
A4: 1.Seller | F4: 8.No and date of invoice
A5: SEWANG TEXTILE CO., LTD. | F5: SW-PTNI-260828-P | M5: 46262
A6: DAEHWA B/D, 10,YEONGDONG-DAERO 112-GIL, | F6: 9.Term of payment
A7: GANGNAM-GU, SEOUL, 06083, KOREA | F7: TT
A8: TEL: 82 2 546 6066 FAX: 82 2 546 1134
A9: 2.Buyer / For Account and Risk of Messrs | F9: FILE VN : | G9: SW26-2-0008-029
A10: EPOCH LAY ENTERPRISE LTD | F10: STYLE : | G10: 265E0123/0124 WC7SK033RS/PS(2-8-29)
A11: 6A, JALAN HARMONIUM 35/2, TAMAN DESA TERBAU | F11: FILE NO : | G11: SW2620008029
A12: 81100 JOHOR BAHRU, JOHOR, MALAYSIA
A13: TEL: (+607) 8613568 FAX: (+607) 8614568
A14: 3.Processer of Seller/ Exporter | F14: 4.Consignee & Notity
A15: SEWANG VINA CO. LTD. | F15: PT NIRWANA ALABARE GARMENT
A16: LOT B_3A_CN, LOT B_2B_CN,LOT B_1C_CN, BAU BANG INDUSTRIAL PARK, | F16: JL. RAYA RANCAEKEK-MAJALAYA NO.289, DESA SOLOKAN JERUK,
A17: BAU BANG COMMUNE, HOCHIMINH CITY, VIETNAM | F17: KECAMATAN SOLOKAN JERUK,
A18: TEL: +84-274-2221982-83 FAX: +84-274-2221984 | F18: KABUPATEN BANDUNG JAWA BARAT 40382, INDONESIA
F19: NPWP.74.540.692.6-444.000
A20: 4.Port of loading | D20: 5.Final destination | F20: Tel 6222-85962076
A21: HOCHIMINH , VIETNAM | D21: JAKARTA, INDONESIA
A22: 6.Carrier | D22: 7.Sailing on boat
A23: GREEN PACIFIC 2624S | D23: =+M5+7 -> 46269 | F23: * COUNTRY OF ORIGIN : VIETNAM
A24: CONT: UETU 5971757 // SEAL: SITR742681 * 40'
A25: DESCRIPTION OF GOODS | F25: FOB HO CHI MINH
A26: NO | B26: PO NO | C26: KNITTED FABRIC | D26: COLOR | E26: STYLE | F26: Quantity (Bale) | G26: Quantity (KG) | H26: Quantity (Yard) | I26: Processing Price (USD/KG) | J26: Processign Amount (USD) | K26: MTR | L26: Unit price (USD) / Yard | M26: Amount (USD)
A27: 1 | B27: EPD 00075 | C27: 100% COTTON BCI CM 40/1 INTERLOCK, WIDTH: 66/68", WEIGHT: 195G/M2 | D27: PARROT CORAL(265E0123 A/A4/AA RS) | E27: 265E0123/0124 WC7SK033RS/PS(2-8-29) | F27: 128 | G27: 2461.6 | H27: 7700 | I27: 1.93 | J27: =ROUND((I27*G27),2) -> 4750.89 | K27: =ROUND((H27*0.9144),2) -> 7040.88 | L27: 1.94 | M27: =+ROUND(L27*H27,2) -> 14938
A28: 2 | B28: EPD 00075 | C28: 100% COTTON BCI CM 40/1 INTERLOCK, WIDTH: 66/68", WEIGHT: 195G/M2 | D28: PARROT CORAL(265E0123 B/B4/BA RS) | E28: 265E0123/0124 WC7SK033RS/PS(2-8-29) | F28: 46 | G28: 884.56 | H28: 2790 | I28: 1.93 | J28: =ROUND((I28*G28),2) -> 1707.2 | K28: =ROUND((H28*0.9144),2) -> 2551.18 | L28: 1.94 | M28: =+ROUND(L28*H28,2) -> 5412.6
A29: 3 | B29: EPD 00075 | C29: 100% COTTON BCI CM 40/1 INTERLOCK, WIDTH: 66/68", WEIGHT: 195G/M2 | D29: PARROT CORAL(265E0124 A/A4 PS) | E29: 265E0123/0124 WC7SK033RS/PS(2-8-29) | F29: 105 | G29: 2013 | H29: 6315 | I29: 1.93 | J29: =ROUND((I29*G29),2) -> 3885.09 | K29: =ROUND((H29*0.9144),2) -> 5774.44 | L29: 1.94 | M29: =+ROUND(L29*H29,2) -> 12251.1
A30: 4 | B30: EPD 00075 | C30: 100% COTTON BCI CM 40/1 INTERLOCK, WIDTH: 66/68", WEIGHT: 195G/M2 | D30: PARROT CORAL(265E0124 B4 PS) | E30: 265E0123/0124 WC7SK033RS/PS(2-8-29) | F30: 7 | G30: 140.52 | H30: 440 | I30: 1.93 | J30: =ROUND((I30*G30),2) -> 271.2 | K30: =ROUND((H30*0.9144),2) -> 402.34 | L30: 1.94 | M30: =+ROUND(L30*H30,2) -> 853.6
A31: 5 | B31: EPD 00075 | C31: 100% COTTON BCI CM 40/1 INTERLOCK, WIDTH: 66/68", WEIGHT: 195G/M2 | D31: PARROT CORAL(265E0123 A/A4/AA RS) | E31: 265E0123/0124 WC7SK033RS/PS(2-8-29) | F31: 1 | G31: 19.2 | H31: 61 | I31: 1.93 | J31: =ROUND((I31*G31),2) -> 37.06 | K31: =ROUND((H31*0.9144),2) -> 55.78 | L31: 1.94 | M31: =+ROUND(L31*H31,2) -> 118.34 | N31: FOC
A32: 6 | B32: EPD 00075 | C32: 100% COTTON BCI CM 40/1 INTERLOCK, WIDTH: 66/68", WEIGHT: 195G/M2 | D32: PARROT CORAL(265E0123 B/B4/BA RS) | E32: 265E0123/0124 WC7SK033RS/PS(2-8-29) | F32: 1 | G32: 22.94 | H32: 72 | I32: 1.93 | J32: =ROUND((I32*G32),2) -> 44.27 | K32: =ROUND((H32*0.9144),2) -> 65.84 | L32: 1.94 | M32: =+ROUND(L32*H32,2) -> 139.68 | N32: FOC
A33: 7 | B33: EPD 00075 | C33: 100% COTTON BCI CM 40/1 INTERLOCK, WIDTH: 66/68", WEIGHT: 195G/M2 | D33: PARROT CORAL(265E0124 A/A4 PS) | E33: 265E0123/0124 WC7SK033RS/PS(2-8-29) | F33: 2 | G33: 46.6 | H33: 143 | I33: 1.93 | J33: =ROUND((I33*G33),2) -> 89.94 | K33: =ROUND((H33*0.9144),2) -> 130.76 | L33: 1.94 | M33: =+ROUND(L33*H33,2) -> 277.42 | N33: FOC
A34: 8 | B34: EPD 00075 | C34: 100% COTTON BCI CM 40/1 INTERLOCK, WIDTH: 66/68", WEIGHT: 195G/M2 | D34: PARROT CORAL(265E0124 B4 PS) | E34: 265E0123/0124 WC7SK033RS/PS(2-8-29) | F34: 1 | G34: 14.08 | H34: 44 | I34: 1.93 | J34: =ROUND((I34*G34),2) -> 27.17 | K34: =ROUND((H34*0.9144),2) -> 40.23 | L34: 1.94 | M34: =+ROUND(L34*H34,2) -> 85.36 | N34: FOC
C35: TOTAL | F35: =SUM(F27:F34) -> 291 | G35: =SUM(G27:G34) -> 5602.5 | H35: =SUM(H27:H34) -> 17565 | J35: =SUM(J27:J34) -> 10812.82 | K35: =SUM(K27:K34) -> 16061.45 | M35: =SUM(M27:M34) -> 34076.1
A37: S/#: AS ROLL STICKER
A38: ITEM: AS ROLL STICKER | F38: SEWANG VINA CO., LTD
A39: COLOR: AS ROLL STICKER
A40: ORDER WIDTH: AS ROLL STICKER
A41: LOT: AS ROLL STICKER
A42: R/NO: AS ROLL STICKER
A43: FINISH WEIGHT: AS ROLL STICKER
A44: LENGTH: AS ROLL STICKER
A45: CUT: AS ROLL STICKER
F46: Signed by | G46: KWON YEOKYUNG

Sheet PLK 
E1: PACKING LIST
A4: ='INV '!A4 -> 1.Seller | E4: 8.No and date of invoice
A5: ='INV '!A5 -> SEWANG TEXTILE CO., LTD. | E5: ='INV '!F5 -> SW-PTNI-260828-P | I5: ='INV '!M5 -> 46262
A6: ='INV '!A6 -> DAEHWA B/D, 10,YEONGDONG-DAERO 112-GIL, | E6: ='INV '!F6 -> 9.Term of payment
A7: ='INV '!A7 -> GANGNAM-GU, SEOUL, 06083, KOREA | E7: ='INV '!F7 -> TT
A8: ='INV '!A8 -> TEL: 82 2 546 6066 FAX: 82 2 546 1134
A9: 2.Buyer / For Account and Risk of Messrs | E9: ='INV '!F9 -> FILE VN : | F9: ='INV '!G9 -> SW26-2-0008-029
A10: ='INV '!A10:C10 -> EPOCH LAY ENTERPRISE LTD | E10: ='INV '!F10 -> STYLE : | F10: ='INV '!G10 -> 265E0123/0124 WC7SK033RS/PS(2-8-29)
A11: ='INV '!A11:C11 -> 6A, JALAN HARMONIUM 35/2, TAMAN DESA TERBAU | E11: ='INV '!F11 -> FILE NO : | F11: ='INV '!G11 -> SW2620008029
A12: ='INV '!A12:C12 -> 81100 JOHOR BAHRU, JOHOR, MALAYSIA
A13: ='INV '!A14 -> 3.Processer of Seller/ Exporter | E13: ='INV '!F14 -> 4.Consignee & Notity
A14: ='INV '!A15 -> SEWANG VINA CO. LTD. | E14: ='INV '!F15 -> PT NIRWANA ALABARE GARMENT
A15: ='INV '!A16 -> LOT B_3A_CN, LOT B_2B_CN,LOT B_1C_CN, BAU BANG INDUSTRIAL PARK, | E15: ='INV '!F16 -> JL. RAYA RANCAEKEK-MAJALAYA NO.289, DESA SOLOKAN JERUK,
A16: ='INV '!A17 -> BAU BANG COMMUNE, HOCHIMINH CITY, VIETNAM | E16: ='INV '!F17 -> KECAMATAN SOLOKAN JERUK,
A17: ='INV '!A18 -> TEL: +84-274-2221982-83 FAX: +84-274-2221984 | E17: ='INV '!F18 -> KABUPATEN BANDUNG JAWA BARAT 40382, INDONESIA
A18: ='INV '!A20 -> 4.Port of loading | C18: ='INV '!D20 -> 5.Final destination | E18: ='INV '!F19 -> NPWP.74.540.692.6-444.000
A19: ='INV '!A21 -> HOCHIMINH , VIETNAM | C19: ='INV '!D21 -> JAKARTA, INDONESIA | E19: ='INV '!F20 -> Tel 6222-85962076
A20: ='INV '!A22 -> 6.Carrier | C20: ='INV '!D22 -> 7.Sailing on boat
A21: ='INV '!A23 -> GREEN PACIFIC 2624S | C21: ='INV '!D23:E23 -> #VALUE!
G22: ='INV '!F25 -> FOB HO CHI MINH
A23: NO | B23: ='INV '!C26 -> KNITTED FABRIC | C23: ='INV '!D26 -> COLOR | D23: ='INV '!E26 -> STYLE | E23: Lot | F23: ='INV '!F26 -> Quantity (Bale) | G23: =+'INV '!H26 -> Quantity (Yard) | H23: MTR | I23: Net.W (KGS) | J23: Gross Weight
A24: ='INV '!A27 -> 1 | B24: ='INV '!C27 -> 100% COTTON BCI CM 40/1 INTERLOCK, WIDTH: 66/68", WEIGHT: 195G/M2 | C24: ='INV '!D27 -> PARROT CORAL(265E0123 A/A4/AA RS) | D24: ='INV '!E27 -> 265E0123/0124 WC7SK033RS/PS(2-8-29) | E24: 2/3/4/4-1Y/5C/5C-1Y | F24: ='INV '!F27 -> 128 | G24: =+'INV '!H27 -> 7700 | H24: ='INV '!K27 -> 7040.88 | I24: ='INV '!G27 -> 2461.6 | J24: =F24*0.1+I24 -> 2474.4
A25: ='INV '!A28 -> 2 | B25: ='INV '!C28 -> 100% COTTON BCI CM 40/1 INTERLOCK, WIDTH: 66/68", WEIGHT: 195G/M2 | C25: ='INV '!D28 -> PARROT CORAL(265E0123 B/B4/BA RS) | D25: ='INV '!E28 -> 265E0123/0124 WC7SK033RS/PS(2-8-29) | E25: 11/11-1Y/13C/13C-1Y | F25: ='INV '!F28 -> 46 | G25: =+'INV '!H28 -> 2790 | H25: ='INV '!K28 -> 2551.18 | I25: ='INV '!G28 -> 884.56 | J25: =F25*0.1+I25 -> 889.16
A26: ='INV '!A29 -> 3 | B26: ='INV '!C29 -> 100% COTTON BCI CM 40/1 INTERLOCK, WIDTH: 66/68", WEIGHT: 195G/M2 | C26: ='INV '!D29 -> PARROT CORAL(265E0124 A/A4 PS) | D26: ='INV '!E29 -> 265E0123/0124 WC7SK033RS/PS(2-8-29) | E26: 6/7/8C/8C-1Y | F26: ='INV '!F29 -> 105 | G26: =+'INV '!H29 -> 6315 | H26: ='INV '!K29 -> 5774.44 | I26: ='INV '!G29 -> 2013 | J26: =F26*0.1+I26 -> 2023.5
A27: ='INV '!A30 -> 4 | B27: ='INV '!C30 -> 100% COTTON BCI CM 40/1 INTERLOCK, WIDTH: 66/68", WEIGHT: 195G/M2 | C27: ='INV '!D30 -> PARROT CORAL(265E0124 B4 PS) | D27: ='INV '!E30 -> 265E0123/0124 WC7SK033RS/PS(2-8-29) | E27: 14C/14C-1Y | F27: ='INV '!F30 -> 7 | G27: =+'INV '!H30 -> 440 | H27: ='INV '!K30 -> 402.34 | I27: ='INV '!G30 -> 140.52 | J27: =F27*0.1+I27 -> 141.22
A28: ='INV '!A31 -> 5 | B28: ='INV '!C31 -> 100% COTTON BCI CM 40/1 INTERLOCK, WIDTH: 66/68", WEIGHT: 195G/M2 | C28: ='INV '!D31 -> PARROT CORAL(265E0123 A/A4/AA RS) | D28: ='INV '!E31 -> 265E0123/0124 WC7SK033RS/PS(2-8-29) | E28: 2 | F28: ='INV '!F31 -> 1 | G28: =+'INV '!H31 -> 61 | H28: ='INV '!K31 -> 55.78 | I28: ='INV '!G31 -> 19.2 | J28: =F28*0.1+I28 -> 19.3
A29: ='INV '!A32 -> 6 | B29: ='INV '!C32 -> 100% COTTON BCI CM 40/1 INTERLOCK, WIDTH: 66/68", WEIGHT: 195G/M2 | C29: ='INV '!D32 -> PARROT CORAL(265E0123 B/B4/BA RS) | D29: ='INV '!E32 -> 265E0123/0124 WC7SK033RS/PS(2-8-29) | E29: 13C | F29: ='INV '!F32 -> 1 | G29: =+'INV '!H32 -> 72 | H29: ='INV '!K32 -> 65.84 | I29: ='INV '!G32 -> 22.94 | J29: =F29*0.1+I29 -> 23.04
A30: ='INV '!A33 -> 7 | B30: ='INV '!C33 -> 100% COTTON BCI CM 40/1 INTERLOCK, WIDTH: 66/68", WEIGHT: 195G/M2 | C30: ='INV '!D33 -> PARROT CORAL(265E0124 A/A4 PS) | D30: ='INV '!E33 -> 265E0123/0124 WC7SK033RS/PS(2-8-29) | E30: 8C | F30: ='INV '!F33 -> 2 | G30: =+'INV '!H33 -> 143 | H30: ='INV '!K33 -> 130.76 | I30: ='INV '!G33 -> 46.6 | J30: =F30*0.1+I30 -> 46.8
A31: ='INV '!A34 -> 8 | B31: ='INV '!C34 -> 100% COTTON BCI CM 40/1 INTERLOCK, WIDTH: 66/68", WEIGHT: 195G/M2 | C31: ='INV '!D34 -> PARROT CORAL(265E0124 B4 PS) | D31: ='INV '!E34 -> 265E0123/0124 WC7SK033RS/PS(2-8-29) | E31: 14C | F31: ='INV '!F34 -> 1 | G31: =+'INV '!H34 -> 44 | H31: ='INV '!K34 -> 40.23 | I31: ='INV '!G34 -> 14.08 | J31: =F31*0.1+I31 -> 14.18
B32: TOTAL | F32: =SUM(F24:F31) -> 291 | G32: =SUM(G24:G31) -> 17565 | H32: =SUM(H24:H31) -> 16061.45 | I32: =SUM(I24:I31) -> 5602.5 | J32: =SUM(J24:J31) -> 5631.6
A34: S/#: AS ROLL STICKER
A35: ITEM: AS ROLL STICKER | F35: SEWANG VINA CO., LTD
A36: COLOR: AS ROLL STICKER
A37: ORDER WIDTH: AS ROLL STICKER
A38: LOT: AS ROLL STICKER
A39: R/NO: AS ROLL STICKER
A40: FINISH WEIGHT: AS ROLL STICKER
A41: LENGTH: AS ROLL STICKER
A42: CUT: AS ROLL STICKER
F44: KWON YEOKYUNG
C57: AMERICAN NAVY-BSD | D57: 253 | E57: 1138 | F57: 262.2 | G57: KGS | I57: =F57+0.1*#REF! -> #REF! | J57: KGS
C58: AMERICAN NAVY-BSD | D58: 254 | E58: 895 | F58: 198.7 | G58: KGS | I58: =F58+0.1*#REF! -> #REF! | J58: KGS | M58: 1 | N58: 73 | O58: 16.8
E59: =SUM(E54:E58) -> 2033 | F59: =SUM(F54:F58) -> 460.9 | G59: KGS | I59: =SUM(I54:I58) -> #REF! | J59: KGS
B62: #4 | C62: 0 | M62: 1 | N62: 10 | O62: 23.02
C63: 0 | M63: 2 | N63: 136 | O63: 31.31
C64: 0 | M64: 2 | N64: 144 | O64: 33.15
C65: 0 | M65: 2 | N65: 195 | O65: 44.89
C66: COLOR | D66: LOT | E66: Q'TY(YDS) | F66: N.W(KGS) | I66: G.W(KGS) | M66: 1 | N66: 120 | O66: 6.95
C67: DUSTED CLAY-BSD | D67: 1 | E67: 1781 | F67: 408.9 | G67: KGS | I67: =F67+0.1*#REF! -> #REF! | J67: KGS
C68: DUSTED CLAY-BSD | D68: 2 | E68: 1803 | F68: 414.8 | G68: KGS | I68: =F68+0.1*#REF! -> #REF! | J68: KGS
C69: DUSTED CLAY-BSD | D69: 3 | E69: 1700 | F69: 391.2 | G69: KGS | I69: =F69+0.1*#REF! -> #REF! | J69: KGS
C70: DUSTED CLAY-BSD | D70: 5 | E70: 1767 | F70: 406.6 | G70: KGS | I70: =F70+0.1*#REF! -> #REF! | J70: KGS
E71: =SUM(E67:E70) -> 7051 | F71: =SUM(F67:F70) -> 1621.5 | G71: KGS | I71: =SUM(I67:I70) -> #REF! | J71: KGS
B73: #5 | C73: 0
C74: 0
C75: 0
C76: 0
C77: COLOR | D77: LOT | E77: Q'TY(YDS) | F77: N.W(KGS) | I77: G.W(KGS)
C78: COLOR | D78: LOT | E78: Q'TY(YDS) | F78: N.W(KGS) | I78: G.W(KGS)
C79: BRILLIANT TEAL-BSD | D79: 1 | E79: 1633 | F79: 392.1 | G79: KGS | I79: =F79+0.1*#REF! -> #REF! | J79: KGS
E80: =SUM(E79:E79) -> 1633 | F80: =SUM(F79:F79) -> 392.1 | G80: KGS | I80: =SUM(I79:I79) -> #REF!
B81: #6 | C81: 0
C82: 0
C83: 0
C84: 0
C85: 0
C86: COLOR | D86: LOT | E86: Q'TY(YDS) | F86: N.W(KGS) | I86: G.W(KGS)
C87: NEON BERRY | D87: 1 | E87: 1644 | F87: 411.1 | G87: KGS | I87: =F87+0.1*#REF! -> #REF! | J87: KGS
C88: BC09 S/D | D88: 26 | E88: 1615 | F88: 379 | G88: KGS | I88: =F88+0.1*#REF! -> #REF! | J88: KGS
E89: =+E87 -> 1644 | F89: =+F87 -> 411.1 | G89: KGS | I89: =+I87 -> #REF! | J89: KGS
C91: SEASON: SPRING 2019, PPK NO. 122660-840 / SUB-LOT: 840-3083 CAT(1) (AC-5574C-CAT(1))
C92: COMPOSITION: 65PCT POLYESTER 35PCT RAYON JERSEY
C93: WIDTH: 64" WEIGHT: 150GM/M2
C94: COLOR | D94: LOT | E94: Q'TY(YDS) | F94: N.W(KGS) | I94: G.W(KGS)
C95: CYBER RED | D95: 34 | E95: 10 | F95: 23.02 | G95: KGS | I95: =F95+0.1*#REF! -> #REF! | J95: KGS
E96: =SUM(E95) -> 10 | F96: =SUM(F95) -> 23.02 | G96: KGS | I96: =SUM(I95) -> #REF! | J96: KGS
C98: SEASON: SPRING 2019, PPK NO. 122660-840 / SUB-LOT: 840-3083 CAT(2) (AC-5574C-CAT(2))
C99: COMPOSITION: 65PCT POLYESTER 35PCT RAYON JERSEY
C100: WIDTH: 64" WEIGHT: 150GM/M2
C101: COLOR | D101: LOT | E101: Q'TY(YDS) | F101: N.W(KGS) | I101: G.W(KGS)
C102: CYBER RED | D102: 34 | E102: 136 | F102: 31.31 | G102: KGS | I102: =F102+0.1*#REF! -> #REF! | J102: KGS
E103: =SUM(E102) -> 136 | F103: =SUM(F102) -> 31.31 | G103: KGS | I103: =SUM(I102) -> #REF! | J103: KGS
C106: SEASON: SPRING 2019, PPK NO. 122660-240 / SUB-LOT: 240-1018,1019,1020,1021 CAT(1) (AC-5575C-CAT(1))
C107: COMPOSITION: 65PCT POLYESTER 35PCT RAYON JERSEY
C108: WIDTH: 64" WEIGHT: 150GM/M2
C109: COLOR | D109: LOT | E109: Q'TY(YDS) | F109: N.W(KGS) | I109: G.W(KGS)
C110: CYBER RED | D110: 34 | E110: 144 | F110: 33.15 | G110: KGS | I110: =F110+0.1*#REF! -> #REF! | J110: KGS
E111: =SUM(E110) -> 144 | F111: =SUM(F110) -> 33.15 | G111: KGS | I111: =SUM(I110) -> #REF! | J111: KGS
A113: I
C114: CONTRACT NO.: SW2018-AT002-VN
C115: SEASON: SPRING 2019, PPK NO. 195874-240 / SUB-LOT: 240-1008,1010,1015 CAT(1) (AC-5573C-CAT(1))
C116: COMPOSITION: 65PCT POLYESTER 35PCT RAYON JERSEY
A117: I | C117: WIDTH: 64" WEIGHT: 150GM/M2
C118: COLOR | D118: LOT | E118: Q'TY(YDS) | F118: N.W(KGS) | I118: G.W(KGS)
C119: CYBER RED | D119: 34 | E119: 195 | F119: 44.89 | G119: KGS | I119: =F119+0.1*#REF! -> #REF! | J119: KGS
E120: =SUM(E119) -> 195 | F120: =SUM(F119) -> 44.89 | G120: KGS | I120: =SUM(I119) -> #REF! | J120: KGS
C123: SEASON: SPRING 2019, PPK NO. 195874-760 / SUB-LOT: 760-4142 CAT(1) (AC-5578C-CAT(1))
C124: COMPOSITION: 65PCT POLYESTER 35PCT RAYON JERSEY
C125: WIDTH: 64" WEIGHT: 150GM/M2
C126: COLOR | D126: LOT | E126: Q'TY(YDS) | F126: N.W(KGS) | I126: G.W(KGS)
...

Sheet AGREEMENT (ACC)
D2: AGREEMENT
D3: No : | E3: ='INV '!F5 -> SW-PTNI-260828-P | I3: Date : | J3: ='INV '!M5-14 -> 46248
D4: Appertain on Processing Contract No | E4: SWVN-2026-10 | I4: Date : | J4: 46113
B6: Today, | C6: =J4 -> 46113 | D6: at SEWANG VINA’s office, we are include:
B8: Party A: SEWANG TEXTILE CO., LTD
B9: ='INV '!A6 -> DAEHWA B/D, 10,YEONGDONG-DAERO 112-GIL,
B10: ='INV '!A7 -> GANGNAM-GU, SEOUL, 06083, KOREA
B11: TEL: 82 2 546 0066 FAX: 82 2 546 1134
B12: REPRESENTED BY MR. CHOI JAE RAK | H12: POSITION: | I12: CHAIRMAN
B14: PARTY B : SEWANG VINA CO., LTD
B15: ='INV '!A16 -> LOT B_3A_CN, LOT B_2B_CN,LOT B_1C_CN, BAU BANG INDUSTRIAL PARK,
B16: ='INV '!A17 -> BAU BANG COMMUNE, HOCHIMINH CITY, VIETNAM
B17: ='INV '!A18 -> TEL: +84-274-2221982-83 FAX: +84-274-2221984
B18: REPRESENTED BY MR. KWON YEOKYUNG | H18: POSITION: | I18: IMPORT EXPORT MANAGER
B20: Consignee & Notity : SAE-A TRADING CO. LTD
B21: Sea A Bldg, 429 Yeongdong- Dearo, Gangnam- Gu, Seoul, Korea
B22: TEL 82-2-6252-7121/ Fax: 82-2-6252-7011
B23: REPRESENTED BY MR.J.S.HA | F23: POSITION : | I23: DIRECTOR
B25: Receiver : HAIANHTEX JOINT STOCK COMPANY
B26: BA DONG-BINH MINH-BINH GIANG-HAI DUONG-VIET NAM
B27: Tax code: 0800447164
B28: REPRESENTED BY MR. VU XUAN HAI | F28: POSITION : | I28: DIRECTOR
B30: After negotiation and discussion, all the parties have agreed to sign this contract with terms and condition as follows:
B31: ARTICLE I: COMMODITY, QUANTITY, PRICE
B32: No | C32: Description | E32: Q'TY | G32: PROCESSING PRICE (USD/KG) | H32: PROCESSING AMOUNT (USD) | I32: SALE PRICE ( USD/YARD) | J32: SALE AMOUNT ( USD )
C33: =[26]INV!B26 -> KNITTED FABRIC | E33: YARD | F33: KG
B34: ='INV '!A27 -> 1 | C34: ='INV '!C27 -> 100% COTTON BCI CM 40/1 INTERLOCK, WIDTH: 66/68", WEIGHT: 195G/M2 | E34: =+'INV '!H27 -> 7700 | F34: ='INV '!G27 -> 2461.6 | G34: ='INV '!I27 -> 1.93 | H34: ='INV '!J27 -> 4750.89 | I34: ='INV '!L27 -> 1.94 | J34: =ROUND(I34*E34,2) -> 14938
B35: ='INV '!A28 -> 2 | C35: ='INV '!C28 -> 100% COTTON BCI CM 40/1 INTERLOCK, WIDTH: 66/68", WEIGHT: 195G/M2 | E35: =+'INV '!H28 -> 2790 | F35: ='INV '!G28 -> 884.56 | G35: ='INV '!I28 -> 1.93 | H35: ='INV '!J28 -> 1707.2 | I35: ='INV '!L28 -> 1.94 | J35: =ROUND(I35*E35,2) -> 5412.6
B36: ='INV '!A29 -> 3 | C36: ='INV '!C29 -> 100% COTTON BCI CM 40/1 INTERLOCK, WIDTH: 66/68", WEIGHT: 195G/M2 | E36: =+'INV '!H29 -> 6315 | F36: ='INV '!G29 -> 2013 | G36: ='INV '!I29 -> 1.93 | H36: ='INV '!J29 -> 3885.09 | I36: ='INV '!L29 -> 1.94 | J36: =ROUND(I36*E36,2) -> 12251.1
B37: ='INV '!A30 -> 4 | C37: ='INV '!C30 -> 100% COTTON BCI CM 40/1 INTERLOCK, WIDTH: 66/68", WEIGHT: 195G/M2 | E37: =+'INV '!H30 -> 440 | F37: ='INV '!G30 -> 140.52 | G37: ='INV '!I30 -> 1.93 | H37: ='INV '!J30 -> 271.2 | I37: ='INV '!L30 -> 1.94 | J37: =ROUND(I37*E37,2) -> 853.6
B38: ='INV '!A31 -> 5 | C38: ='INV '!C31 -> 100% COTTON BCI CM 40/1 INTERLOCK, WIDTH: 66/68", WEIGHT: 195G/M2 | E38: =+'INV '!H31 -> 61 | F38: ='INV '!G31 -> 19.2 | G38: ='INV '!I31 -> 1.93 | H38: ='INV '!J31 -> 37.06 | I38: ='INV '!L31 -> 1.94 | J38: =ROUND(I38*E38,2) -> 118.34
B39: ='INV '!A32 -> 6 | C39: ='INV '!C32 -> 100% COTTON BCI CM 40/1 INTERLOCK, WIDTH: 66/68", WEIGHT: 195G/M2 | E39: =+'INV '!H32 -> 72 | F39: ='INV '!G32 -> 22.94 | G39: ='INV '!I32 -> 1.93 | H39: ='INV '!J32 -> 44.27 | I39: ='INV '!L32 -> 1.94 | J39: =ROUND(I39*E39,2) -> 139.68
B40: ='INV '!A33 -> 7 | C40: ='INV '!C33 -> 100% COTTON BCI CM 40/1 INTERLOCK, WIDTH: 66/68", WEIGHT: 195G/M2 | E40: =+'INV '!H33 -> 143 | F40: ='INV '!G33 -> 46.6 | G40: ='INV '!I33 -> 1.93 | H40: ='INV '!J33 -> 89.94 | I40: ='INV '!L33 -> 1.94 | J40: =ROUND(I40*E40,2) -> 277.42
B41: ='INV '!A34 -> 8 | C41: ='INV '!C34 -> 100% COTTON BCI CM 40/1 INTERLOCK, WIDTH: 66/68", WEIGHT: 195G/M2 | E41: =+'INV '!H34 -> 44 | F41: ='INV '!G34 -> 14.08 | G41: ='INV '!I34 -> 1.93 | H41: ='INV '!J34 -> 27.17 | I41: ='INV '!L34 -> 1.94 | J41: =ROUND(I41*E41,2) -> 85.36
B42: TOTAL | E42: =SUM(E34:E41) -> 17565 | F42: =SUM(F34:F41) -> 5602.5 | H42: =SUM(H34:H41) -> 10812.82 | J42: 33455.3
B44: ARTICLE II : DELIVERY
B46: The cargo is a transitional sourcing products of Processing Contract no | F46: =+E4&" "&"date" -> SWVN-2026-10 date | G46: =+J4 -> 46113 | H46: between SEWANG TEXTILE CO., LTD
B47: with SEWANG VINA CO., LTD
B48: Party B (SEWANG VINA CO., LTD) will deliver to Consignee of Party A: PT NIRWANA ALABARE GARMENT
B49: at: JL. RAYA RANCAEKEK-MAJALAYA NO.289, DESA SOLOKAN JERUK,KECAMATAN SOLOKAN JERUK,
B50: KABUPATEN BANDUNG JAWA BARAT 40382, INDONESIA
B51: with delivery term is | D51: FOB HO CHI MINH
B52: PARTIAL SHIPMENT IS ALLOWED
B53: PACKING | D53: : FLAT PACKED
B54: TRANSPORTATION | D54: VESSEL
B55: SHIP TO | D55: =[26]INV!D20 -> JAKARTA,INDONESIA
B56: ARTICLE III : PAYMENT TERM
B57: PAYMENT | D57: TT
B58: THE CURRENCY FOR PAYMENT WILL BE USD.
B59: Consignee of Party A-PT NIRWANA ALABARE GARMENT only recieves the cargo and doesn’t have to take responsibility for paying sale's amount
B60: Party A: SEWANG TEXTILE CO., LTD have to take responsibility for paying PROCESSING FEE
B61: ALL BANKING CHARGE ARE FOR ACCOUNT OF BENEFICIARY
C62: BENEFICIARY : | D62: SEWANG VINA CO., LTD
C63: BANK : | D63: SHINHAN BANK VIETNAM-BINH DUONG BRANCH
C64: SWIFT CODE : | D64: SHBKVNVX
C65: ACC NO | D65: USD 700-008-419560
B69: PARTY A | H69: BUYER
B70: SEWANG TEXTILE CO., LTD | H70: SEWANG VINA CO., LTD
H78: KWON YEOKYUNG

Sheet INV(TTL)_A
E1: COMMERCIAL INVOICE
A4: 1.Seller | E4: 8.No and date of invoice
A5: SEWANG TEXTILE CO.,LTD. | E5: SW-HSIN190102-NCV | I5: 43467
A6: 302 DAEHWA BLDG. 107-5, | E6: 9.NO and date of Credit
A7: SAMSUNGDONG, KANGNAMGU, | E7: TT
A8: SEOUL, 135-090, KOREA
A10: 2. Buyer/ For account and risk of messrs | E10: P/O NO | F10: : K01-00287530-Purch/K01-00281901-Purch
A11: HANSOLL TEXTILE LTD
A12: HANSOLL TEXTILE BLDG., 268, SONGPA-DAERO, | E12: VN FILE NO. | F12: SV18-2-0258-001/SV18-2-0285-001
A13: SONGPA-GU, SEOUL, KOREA | E13: STYLE NO | F13: 660/159233-007/660-197230-001
A15: 3.PROCESSER OF PARTY A : | E15: 11.Remarks
A16: SEWANG VINA CO., LTD
A17: Lot B_3A_CN, Lot B_2B_CN, Bau Bang Industrial Park, | E17: * CONSIGNED TO / SHIP TO
A18: Lai Uyen Town, Bau Bang District, | E18: PT. HANDSOME
A19: Binh Duong province, Vietnam | E19: KP. CIELA RT.01 RW.01 DS. WANAKERTA KEC. PURWADADI KAB. SUBANG, JAWA BARAT, INDONESIA
L20: KP. CIELA RT.01 RW.01 DS. WANAKERTA KEC. PURWADADI KAB. SUBANG, JAWA BARAT, INDONESIA
A21: 4.Port of loading | C21: 5.Final destination | E21: TEL. : 62-260-460-690 FAX. : 62-260-462-086
A22: HO CHI MINH, VIET NAM | C22: Jakarta, Indonesia
A23: 6.Carrier | C23: 7.Sailing on about | E23: * COUNTRY OF ORIGIN : Vietnam
A24: FX5194 | C24: 43469 | L24: TEL. : 62-260-460-690 FAX. : 62-260-462-086
A25: 12.Marks and numbers of PKGS | C25: 13.Description of goods | E25: 14.Quantity/Unit | G25: 15.Unit-Price | I25: 16.Amount
H26: CPT. JAKARTA
C28: KNITTED FABRIC
B29: # 1 | C29: STYLE NO.660/159233-007/660-197230-001 | L29: PT. HANDSOME
C30: 100 PCT COTTON 30'S/1 SINGLE JERSEY SOLID
C31: CUTTABLE WIDTH : 70", WEIGHT :150G/M2, 244G/YD
C32: COLOR | D32: BALES | E32: Q'TY(KGS) | F32: Q'TY(YDS) | G32: UN/PRICE | I32: AMOUNT
C35: BLUE DEPTHS | D35: 1 | E35: 19.6 | F35: 50 | G35: 1.49 | H35: /YD | I35: =ROUND(G35*F35,2) -> 74.5
C36: PANAMANIAN GOLD | D36: 2 | E36: 33.9 | F36: 142 | G36: 1.49 | H36: /YD | I36: =ROUND(G36*F36,2) -> 211.58
C37: TRUE CHAMBRAY BLUE | D37: 1 | E37: 16.9 | F37: 69 | G37: 1.49 | H37: /YD | I37: =ROUND(G37*F37,2) -> 102.81
B39: # 2 | C39: 100 PCT COTTON CM 30S/1 Y/D FEEDER STRIPE SINGLE JERSEY
C40: CUTTABLE WIDTH : 70", WEIGHT :150G/M2, 244G/YD
C41: COLOR | D41: BALES | E41: Q'TY(KGS) | F41: Q'TY(YDS) | G41: UN/PRICE | I41: AMOUNT
C44: STRIPE 1407A | D44: 3 | E44: 47.9 | F44: 214 | G44: 2.59 | H44: /YD | I44: =ROUND(G44*F44,2) -> 554.26
B46: # 3 | C46: 60 PCT COTTON 40 PCT POLYESTER CVC(60/40) 30S/1 SLUB SINGLE JERSEY
C47: CUTTABLE WIDTH : 70", WEIGHT :150G/M2, 244G/YD
C48: COLOR | D48: BALES | E48: Q'TY(KGS) | F48: Q'TY(YDS) | G48: UN/PRICE | I48: AMOUNT
C51: PALE MINT | D51: 3 | E51: 56.7 | F51: 246 | G51: 1.51 | H51: /YD | I51: =ROUND(G51*F51,2) -> 371.46
C52: PARKER PINK | D52: 3 | E52: 58.3 | F52: 247 | G52: 1.51 | H52: /YD | I52: =ROUND(G52*F52,2) -> 372.97
C56: TOTAL | D56: =D52+D51+D44+D37+D36+D35 -> 13 | E56: =E52+E51+E44+E37+E36+E35 -> 233.3 | F56: =F52+F51+F44+F37+F36+F35 -> 968 | I56: =I52+I51+I44+I37+I36+I35 -> 1687.58
G69: CHUNG JEA MOON

Sheet PCK(TTL)_A
E1: PACKING LIST
A4: 1.Seller | E4: 8.No and date of invoice
A5: SEWANG TEXTILE CO.,LTD. | E5: ='INV(TTL)_A'!E5 -> SW-HSIN190102-NCV | H5: ='INV(TTL)_A'!I5 -> 43467
A6: 302 DAEHWA BLDG. 107-5, | E6: 9.NO and date of Credit
A7: SAMSUNGDONG, KANGNAMGU, | E7: TT
A8: SEOUL, 135-090, KOREA
A10: 2. Buyer/ For account and risk of messrs | E10: P/O NO | F10: ='INV(TTL)_A'!F10 -> : K01-00287530-Purch/K01-00281901-Purch
A11: HANSOLL TEXTILE LTD
A12: HANSOLL TEXTILE BLDG., 268, SONGPA-DAERO, | E12: VN FILE NO. | F12: ='INV(TTL)_A'!F12 -> SV18-2-0258-001/SV18-2-0285-001
A13: SONGPA-GU, SEOUL, KOREA | E13: STYLE NO | F13: ='INV(TTL)_A'!F13 -> 660/159233-007/660-197230-001
A15: 3.PROCESSER OF PARTY A : | E15: 11.Remarks
A16: SEWANG VINA CO., LTD
A17: Lot B_3A_CN, Lot B_2B_CN, Bau Bang Industrial Park, | E17: * CONSIGNED TO / SHIP TO
A18: Lai UyenTown, Bau Bang District, | E18: ='INV(TTL)_A'!E18 -> PT. HANDSOME
A19: Binh Duong province, Vietnam | E19: ='INV(TTL)_A'!E19:I20 -> KP. CIELA RT.01 RW.01 DS. WANAKERTA KEC. PURWADADI KAB. SUBANG, JAWA BARAT, INDONESIA
A21: 4.Port of loading | C21: 5.Final destination | E21: ='INV(TTL)_A'!E21 -> TEL. : 62-260-460-690 FAX. : 62-260-462-086
A22: ='INV(TTL)_A'!A22:B22 -> HO CHI MINH, VIET NAM | C22: Jakarta, Indonesia
A23: 6.Carrier | C23: 7.Sailing on about | E23: * COUNTRY OF ORIGIN : Vietnam
A24: ='INV(TTL)_A'!A24:B24 -> FX5194 | C24: ='INV(TTL)_A'!C24:D24 -> 43469 | E24: =+'INV(TTL)_A'!E24 -> 0
A25: 12.Marks and numbers of PKGS | C25: 13.Description of goods | E25: 14.Quantity | G25: 15.Net-weight | H25: 16.Gross-weight
G27: ='INV(TTL)_A'!H26 -> CPT. JAKARTA
C29: KNITTED FABRIC
B30: # 1 | C30: ='INV(TTL)_A'!C29 -> STYLE NO.660/159233-007/660-197230-001
C31: ='INV(TTL)_A'!C30 -> 100 PCT COTTON 30'S/1 SINGLE JERSEY SOLID
C32: ='INV(TTL)_A'!C31 -> CUTTABLE WIDTH : 70", WEIGHT :150G/M2, 244G/YD
C36: ='INV(TTL)_A'!C32 -> COLOR | D36: LOT | E36: Bales | F36: Yards | G36: Net( KG) | H36: Gross ( KG)
C38: ='INV(TTL)_A'!C35 -> BLUE DEPTHS | D38: 3 | E38: ='INV(TTL)_A'!D35 -> 1 | F38: ='INV(TTL)_A'!F35 -> 50 | G38: ='INV(TTL)_A'!E35 -> 19.6 | H38: =G38 -> 19.6
C39: ='INV(TTL)_A'!C36 -> PANAMANIAN GOLD | D39: 6 | E39: ='INV(TTL)_A'!D36 -> 2 | F39: ='INV(TTL)_A'!F36 -> 142 | G39: ='INV(TTL)_A'!E36 -> 33.9 | H39: =G39 -> 33.9
C40: ='INV(TTL)_A'!C37 -> TRUE CHAMBRAY BLUE | D40: 4 | E40: ='INV(TTL)_A'!D37 -> 1 | F40: ='INV(TTL)_A'!F37 -> 69 | G40: ='INV(TTL)_A'!E37 -> 16.9 | H40: =G40 -> 16.9
B42: # 2 | C42: ='INV(TTL)_A'!C39 -> 100 PCT COTTON CM 30S/1 Y/D FEEDER STRIPE SINGLE JERSEY
C43: ='INV(TTL)_A'!C40 -> CUTTABLE WIDTH : 70", WEIGHT :150G/M2, 244G/YD
C46: ='INV(TTL)_A'!C41 'INV(TTL)_A'!C41 -> COLOR | D46: LOT | E46: Bales | F46: Yards | G46: Net( KG) | H46: Gross ( KG)
C48: ='INV(TTL)_A'!C44 -> STRIPE 1407A | D48: 3 | E48: ='INV(TTL)_A'!D44 -> 3 | F48: ='INV(TTL)_A'!F44 -> 214 | G48: ='INV(TTL)_A'!E44 -> 47.9 | H48: =G48 -> 47.9
B50: # 3 | C50: ='INV(TTL)_A'!C46 -> 60 PCT COTTON 40 PCT POLYESTER CVC(60/40) 30S/1 SLUB SINGLE JERSEY
C51: ='INV(TTL)_A'!C47 -> CUTTABLE WIDTH : 70", WEIGHT :150G/M2, 244G/YD
C56: ='INV(TTL)_A'!C48 -> COLOR | D56: LOT | E56: Bales | F56: Yards | G56: Net( KG) | H56: Gross ( KG)
C58: ='INV(TTL)_A'!C51 -> PALE MINT | D58: 4/5 | E58: ='INV(TTL)_A'!D51 -> 3 | F58: ='INV(TTL)_A'!F51 -> 246 | G58: ='INV(TTL)_A'!E51 -> 56.7 | H58: =G58 -> 56.7
C59: ='INV(TTL)_A'!C52 -> PARKER PINK | D59: 5 | E59: ='INV(TTL)_A'!D52 -> 3 | F59: ='INV(TTL)_A'!F52 -> 247 | G59: ='INV(TTL)_A'!E52 -> 58.3 | H59: =G59 -> 58.3
C61: TOTAL | E61: =E59+E58+E48+E40+E39+E38 -> 13 | F61: =F59+F58+F48+F40+F39+F38 -> 968 | G61: =G59+G58+G48+G40+G39+G38 -> 233.3 | H61: =H59+H58+H48+H40+H39+H38 -> 233.3
F65: SEWANG VINA CO.,LTD
G72: CHUNG JEA MOON

Sheet INV(TTL)_B
E1: COMMERCIAL INVOICE
A4: 1.Seller | E4: 8.No and date of invoice
A5: SEWANG TEXTILE CO.,LTD. | E5: VN-KME-18014B | J5: 43238
A6: 302 DAEHWA BLDG. 107-5, | E6: 9.NO and date of Credit
A7: SAMSUNGDONG, KANGNAMGU, | E7: LCIC800193 | J7: 43215
A8: SEOUL, 135-090, KOREA
A10: 2. Buyer/ For account and risk of messrs | E10: 10.L/C issuing bank
A11: KANMAX ENTERPRISES LTD. | E11: BANGKOK BANK PUBLIC COMPANY LIMITED HONG KONG BRANCH
A12: PALM GROVE HOUSE, P.O.BOX 438, | E12: 28 DES VOEUX ROAD, CENTRAL
A13: ROAD TOWN, TORTOLA, BRITISH VIRGIN ISLANDS
A15: 3.PROCESSER OF PARTY A : | E15: 11.Remarks
A16: SEWANG VINA CO., LTD | E16: * CONSIGNED TO / SHIP TO
A17: Lot B_3A_CN, Lot B_2B_CN, Bau Bang Industrial Park, | E17: CHUTEX INTERNATIONAL CO.,LTD.
A18: Lai Uyen Ward, Bau Bang District, | E18: NO.18 THONG NHAT ROAD, SONG THAN INDUSTRIAL ZONE II
A19: Binh Duong province, Vietnam | E19: DI AN TOWN BINH DUONG PROVINCE VIETNAM
A21: 4.Port of loading | C21: 5.Final destination
A22: Bau bang, Vietnam | C22: Binh Dương, Vietnam
A23: 6.Carrier | C23: 7.Sailing on about | E23: * COUNTRY OF ORIGIN : Vietnam
A24: TRUCK | C24: 43238
A25: 12.Marks and numbers of PKGS | C25: 13.Description of goods | E25: 14.Quantity/Unit | H25: 15.Unit-Price | J25: 16.Amount
I27: CPT.BINH DUONG
C28: KNITTED FABRIC
B29: # 1 | C29: RE: REF NO.183K0734-A-B2+ OLD NAVY LADIES KNIT FAL'18 STYLE 286498
C30: (PO NO.:KV03943)
C31: 100PCT COTTON 30S/1 SLUB JERSEY
C32: 150GM/M2 (AFTER WASHED)
C33: USABLE WIDTH: 68'' TOTAL WIDTH: 70''
C34: JUST CHILL
C35: . | E35: 305 | F35: 23225 | G35: 12328.49 | H35: 1.51 | I35: /YD | J35: =ROUND(F35*H35,2) -> 35069.75
C38: TOTAL | E38: =SUM(E29:E36) -> 305 | F38: =SUM(F29:F36) -> 23225 | G38: =SUM(G29:G37) -> 12328.49 | J38: =SUM(J29:J36) -> 35069.75
G44: Signed by

Sheet PCK(TTL)_B
E1: PACKING LIST
A4: 1.Seller | E4: 8.No and date of invoice
A5: SEWANG TEXTILE CO.,LTD. | E5: VN-KME-18014B | I5: 43238
A6: 302 DAEHWA BLDG. 107-5, | E6: 9.NO and date of Credit
A7: SAMSUNGDONG, KANGNAMGU, | E7: LCIC800193 | I7: 43215
A8: SEOUL, 135-090, KOREA
A10: 2. Buyer/ For account and risk of messrs | E10: 10.L/C issuing bank
A11: KANMAX ENTERPRISES LTD. | E11: BANGKOK BANK PUBLIC COMPANY LIMITED HONG KONG BRANCH
A12: PALM GROVE HOUSE, P.O.BOX 438, | E12: 28 DES VOEUX ROAD, CENTRAL
A13: ROAD TOWN, TORTOLA, BRITISH VIRGIN ISLANDS
A15: 3.PROCESSER OF PARTY A : | E15: 11.Remarks
A16: SEWANG VINA CO., LTD | E16: * CONSIGNED TO / SHIP TO
A17: Lot B_3A_CN, Lot B_2B_CN, Bau Bang Industrial Park, | E17: CHUTEX INTERNATIONAL CO.,LTD.
A18: Lai Uyen Ward, Bau Bang District, | E18: NO.18 THONG NHAT ROAD, SONG THAN INDUSTRIAL ZONE II
A19: Binh Duong province, Vietnam | E19: DI AN TOWN BINH DUONG PROVINCE VIETNAM
A21: 4.Port of loading | C21: 5.Final destination
A22: Bau bang, Vietnam | C22: Binh Dương, Vietnam
A23: 6.Carrier | C23: 7.Sailing on about | E23: * COUNTRY OF ORIGIN : Vietnam
A24: TRUCK | C24: 43238 | E24: =+'INV(TTL)_A'!E24 -> 0
A25: 12.Marks and numbers of PKGS | C25: 13.Description of goods | E25: 14.Quantity | H25: 15.Net-weight | I25: 16.Gross-weight
C28: KNITTED FABRIC
B29: # 1 | C29: RE: REF NO.183K0734-A-B2+ OLD NAVY LADIES KNIT FAL'18 STYLE 286498
C30: (PO NO.:KV03943)
C31: 100PCT COTTON 30S/1 SLUB JERSEY
C32: 150GM/M2 (AFTER WASHED)
C33: USABLE WIDTH: 68'' TOTAL WIDTH: 70''
C34: JUST CHILL
D35: LOT | E35: Roll | F35: Yards | G35: LBS | H35: Net( KG) | I35: Gross ( KG)
D36: 12 | E36: 48 | F36: 3682 | G36: =ROUND(+H36/0.4536,2) -> 1980.38 | H36: 898.3 | I36: =E36*0.1+H36 -> 903.1
D37: 13 | E37: 48 | F37: 3728 | G37: =ROUND(+H37/0.4536,2) -> 1970.9 | H37: 894 | I37: =E37*0.1+H37 -> 898.8
D38: 15 | E38: 48 | F38: 3715 | G38: =ROUND(+H38/0.4536,2) -> 1998.68 | H38: 906.6 | I38: =E38*0.1+H38 -> 911.4
D39: 16 | E39: 43 | F39: 3374 | G39: =ROUND(+H39/0.4536,2) -> 1786.16 | H39: 810.2 | I39: =E39*0.1+H39 -> 814.5
D40: 18-5 | E40: 47 | F40: 3327 | G40: =ROUND(+H40/0.4536,2) -> 1758.6 | H40: 797.7 | I40: =E40*0.1+H40 -> 802.4
D41: 19-5 | E41: 48 | F41: 3593 | G41: =ROUND(+H41/0.4536,2) -> 1861.77 | H41: 844.5 | I41: =E41*0.1+H41 -> 849.3
D42: 20-6 | E42: 23 | F42: 1806 | G42: =ROUND(+H42/0.4536,2) -> 972 | H42: 440.9 | I42: =E42*0.1+H42 -> 443.2
D43: SUB TOTAL | E43: =SUM(E36:E42) -> 305 | F43: =SUM(F36:F42) -> 23225 | G43: =SUM(G36:G42) -> 12328.49 | H43: =SUM(H36:H42) -> 5592.2 | I43: =SUM(I36:I42) -> 5622.7
C45: TOTAL | E45: =SUM(E34:E43)/2 -> 305 | F45: =SUM(F34:F43)/2 -> 23225 | G45: =ROUND(SUM(G34:G43)/2,2) -> 12328.49 | H45: =SUM(H33:H44)/2 -> 5592.2 | I45: =SUM(I34:I43)/2 -> 5622.7
G50: Signed by

Sheet INV(TTL)_C
E1: COMMERCIAL INVOICE
A4: 1.Seller | E4: 8.No and date of invoice
A5: SEWANG TEXTILE CO.,LTD. | E5: VN-KME-18013NCV | J5: 43236
A6: 302 DAEHWA BLDG. 107-5, | E6: 9.NO and date of Credit
A7: SAMSUNGDONG, KANGNAMGU, | E7: LCIC800193 | J7: 43215
A8: SEOUL, 135-090, KOREA | E8: ** NON COMMERCIAL VALUE **
A10: 2. Buyer/ For account and risk of messrs | E10: 10.L/C issuing bank
A11: KANMAX ENTERPRISES LTD. | E11: BANGKOK BANK PUBLIC COMPANY LIMITED HONG KONG BRANCH
A12: PALM GROVE HOUSE, P.O.BOX 438, | E12: 28 DES VOEUX ROAD, CENTRAL
A13: ROAD TOWN, TORTOLA, BRITISH VIRGIN ISLANDS
A15: 3.PROCESSER OF PARTY A : | E15: 11.Remarks
A16: SEWANG VINA CO., LTD | E16: * CONSIGNED TO / SHIP TO
A17: Lot B_3A_CN, Lot B_2B_CN, Bau Bang Industrial Park, | E17: CHUTEX INTERNATIONAL CO.,LTD.
A18: Lai Uyen Ward, Bau Bang District, | E18: NO.18 THONG NHAT ROAD, SONG THAN INDUSTRIAL ZONE II
A19: Binh Duong province, Vietnam | E19: DI AN TOWN BINH DUONG PROVINCE VIETNAM
A21: 4.Port of loading | C21: 5.Final destination
A22: Bau bang, Vietnam | C22: Binh Dương, Vietnam
A23: 6.Carrier | C23: 7.Sailing on about | E23: * COUNTRY OF ORIGIN : Vietnam
A24: TRUCK | C24: 43236
A25: 12.Marks and numbers of PKGS | C25: 13.Description of goods | E25: 14.Quantity/Unit | H25: 15.Unit-Price | J25: 16.Amount
I27: CPT.BINH DUONG
C28: KNITTED FABRIC
B29: # 1 | C29: RE: REF NO.183K0734-A-B2+ OLD NAVY LADIES KNIT FAL'18 STYLE 286498
C30: (PO NO.:KV03943)
C31: 100PCT COTTON 30S/1 SLUB JERSEY
C32: 150GM/M2 (AFTER WASHED)
C33: USABLE WIDTH: 68'' TOTAL WIDTH: 70''
C34: ROUGE VERMILLION 932
E35: 1 | F35: 77 | G35: 42.55 | H35: 1.51 | I35: /YD | J35: FOC
B38: #2 | C38: RE: REF NO.183K0735-A-B2+ OLD NAVY LADIES KNIT FAL'18 STYLE 286503
C39: (PO NO.:KV03915)
C40: 100PCT COTTON 30S/1 SLUB JERSEY
C41: 150GM/M2 (AFTER WASHED)
C42: USABLE WIDTH: 68'' TOTAL WIDTH: 70''
C43: BUST A MAUVE 103
E44: 1 | F44: 76 | G44: 41.01 | H44: 1.51 | I44: /YD | J44: FOC
C47: TOTAL | E47: =SUM(E29:E45) -> 2 | F47: =SUM(F29:F45) -> 153 | G47: =SUM(G34:G46) -> 83.56 | J47: =SUM(J29:J45) -> 0
G53: Signed by

Sheet PCK(TTL)_C
E1: PACKING LIST
A4: 1.Seller | E4: 8.No and date of invoice
A5: SEWANG TEXTILE CO.,LTD. | E5: VN-KME-18013NCV | I5: 43236
A6: 302 DAEHWA BLDG. 107-5, | E6: 9.NO and date of Credit
A7: SAMSUNGDONG, KANGNAMGU, | E7: LCIC800193 | I7: 43215
A8: SEOUL, 135-090, KOREA | E8: ** NON COMMERCIAL VALUE **
A10: 2. Buyer/ For account and risk of messrs | E10: 10.L/C issuing bank
A11: KANMAX ENTERPRISES LTD. | E11: BANGKOK BANK PUBLIC COMPANY LIMITED HONG KONG BRANCH
A12: PALM GROVE HOUSE, P.O.BOX 438, | E12: 28 DES VOEUX ROAD, CENTRAL
A13: ROAD TOWN, TORTOLA, BRITISH VIRGIN ISLANDS
A15: 3.PROCESSER OF PARTY A : | E15: 11.Remarks
A16: SEWANG VINA CO., LTD | E16: * CONSIGNED TO / SHIP TO
A17: Lot B_3A_CN, Lot B_2B_CN, Bau Bang Industrial Park, | E17: CHUTEX INTERNATIONAL CO.,LTD.
A18: Lai Uyen Ward, Bau Bang District, | E18: NO.18 THONG NHAT ROAD, SONG THAN INDUSTRIAL ZONE II
A19: Binh Duong province, Vietnam | E19: DI AN TOWN BINH DUONG PROVINCE VIETNAM
A21: 4.Port of loading | C21: 5.Final destination
A22: Bau bang, Vietnam | C22: Binh Dương, Vietnam
A23: 6.Carrier | C23: 7.Sailing on about | E23: * COUNTRY OF ORIGIN : Vietnam
A24: TRUCK | C24: 43236 | E24: =+'INV(TTL)_A'!E24 -> 0
A25: 12.Marks and numbers of PKGS | C25: 13.Description of goods | E25: 14.Quantity | H25: 15.Net-weight | I25: 16.Gross-weight
C28: KNITTED FABRIC
B29: # 1 | C29: RE: REF NO.183K0734-A-B2+ OLD NAVY LADIES KNIT FAL'18 STYLE 286498
C30: (PO NO.:KV03943)
C31: 100PCT COTTON 30S/1 SLUB JERSEY
C32: 150GM/M2 (AFTER WASHED)
C33: USABLE WIDTH: 68'' TOTAL WIDTH: 70''
C34: ROUGE VERMILLION 932
D35: LOT | E35: Roll | F35: Yards | G35: LBS | H35: Net( KG) | I35: Gross ( KG)
D36: 14 | E36: 1 | F36: 77 | G36: =+H36/0.4536 -> 42.548501 | H36: 19.3 | I36: =E36*0.1+H36 -> 19.4
D37: . | E37: =SUM(E36:E36) -> 1 | F37: =SUM(F36:F36) -> 77 | G37: =SUM(G36:G36) -> 42.548501 | H37: =SUM(H36:H36) -> 19.3 | I37: =SUM(I36:I36) -> 19.4
B40: # 2 | C40: RE: REF NO.183K0735-A-B2+ OLD NAVY LADIES KNIT FAL'18 STYLE 286503
C41: (PO NO.:KV03915)
C42: 100PCT COTTON 30S/1 SLUB JERSEY
C43: 150GM/M2 (AFTER WASHED)
C44: USABLE WIDTH: 68'' TOTAL WIDTH: 70''
C45: BUST A MAUVE 103
D46: LOT | E46: Roll | F46: Yards | G46: LBS | H46: Net( KG) | I46: Gross ( KG)
D47: 17-1 | E47: 1 | F47: 76 | G47: =+H47/0.4536 -> 41.005291 | H47: 18.6 | I47: =E47*0.1+H47 -> 18.7
D48: . | E48: =SUM(E47:E47) -> 1 | F48: =SUM(F47:F47) -> 76 | G48: =SUM(G47:G47) -> 41.005291 | H48: =SUM(H47:H47) -> 18.6 | I48: =SUM(I47:I47) -> 18.7
C51: TOTAL | E51: =SUM(E36:E48)/2 -> 2 | F51: =SUM(F36:F48)/2 -> 153 | G51: 83.56 | H51: =SUM(H36:H48)/2 -> 37.9 | I51: =SUM(I36:I48)/2 -> 38.1
G56: Signed by

Sheet INV(payable)_A
E1: COMMERCIAL INVOICE
A4: 1.Seller | E4: 8.No and date of invoice
A5: SEWANG TEXTILE CO.,LTD. | E5: SW-HSIN180925 | I5: 43368
A6: 302 DAEHWA BLDG. 107-5, | E6: 9.NO and date of Credit
A7: SAMSUNGDONG, KANGNAMGU, | E7: TT
A8: SEOUL, 135-090, KOREA
A10: 2. Buyer/ For account and risk of messrs | E10: 10.L/C issuing bank
A11: HANSOLL TEXTILE LTD
A12: HANSOLL TEXTILE BLDG., 268, SONGPA-DAERO,
A13: SONGPA-GU, SEOUL, KOREA
A15: 3.PROCESSER OF PARTY A : | E15: 11.Remarks
A16: SEWANG VINA CO., LTD
A17: Lot B_3A_CN, Lot B_2B_CN, Bau Bang Industrial Park, | E17: * CONSIGNED TO / SHIP TO
A18: Lai Uyen Ward, Bau Bang District, | E18: PT. SADUA INDO
A19: Binh Duong province, Vietnam | E19: DUSUN GINTUNGAN, RT.19 RW. II DESA BUTUH, KEC, TEN GARAN, KAB. SEMARANG, JA WA TENGAH, INDONESIA
A21: 4.Port of loading | C21: 5.Final destination | E21: ATTN : ARYO(62-298-610-337)
A22: Cat Lai , Vietnam | C22: Jakarta, Indonesia
A23: 6.Carrier | C23: 7.Sailing on about | E23: * COUNTRY OF ORIGIN : Vietnam
A24: KMTC PENANG 1805S | C24: 43375
A25: 12.Marks and numbers of PKGS | C25: 13.Description of goods | E25: 14.Quantity/Unit | H25: 15.Unit-Price | I25: 16.Amount
H27: FOB.HCMC
C29: KNITTED FABRIC
B30: # 1 | C30: STYLE NO. 980/194294-001
C31: 65PCT POLYESTER + 35PCT RAYON, TR(65/35) 26'S/1 SINGLE JERSEY SOLID
C32: WIDTH : 62", WEIGHT : 170G/M2, 245G/YD
C33: BLACK
E35: 29 | F35: 2530 | G35: 1.23 | H35: /YD | I35: =ROUND(G35*F35,2) -> 3111.9
B38: # 2 | C38: STYLE NO. 980/194294-001
C39: 65PCT POLYESTER + 35PCT RAYON, TR(65/35) 26'S/1 SINGLE JERSEY SOLID
C40: WIDTH : 62", WEIGHT : 170G/M2, 245G/YD
C41: FRESH BLUE
E43: 26 | F43: 2184 | G43: 1.23 | H43: /YD | I43: =ROUND(G43*F43,2) -> 2686.32
A44: CONT/SEAL(1*20GP)
A45: SKLU1205840/980934
C48: TOTAL | E48: =SUM(E30:E47) -> 55 | F48: =SUM(F30:F47) -> 4714 | I48: =SUM(I30:I47) -> 5798.22
G59: CHUNG JEA MOON

Sheet PCK (payable)_A
E1: PACKING LIST
A4: 1.Seller | E4: 8.No and date of invoice
A5: SEWANG TEXTILE CO.,LTD. | E5: SW-HSIN180925 | H5: 43368
A6: 302 DAEHWA BLDG. 107-5, | E6: 9.NO and date of Credit
A7: SAMSUNGDONG, KANGNAMGU, | E7: TT
A8: SEOUL, 135-090, KOREA
A10: 2. Buyer/ For account and risk of messrs | E10: 10.L/C issuing bank
A11: HANSOLL TEXTILE LTD
A12: HANSOLL TEXTILE BLDG., 268, SONGPA-DAERO,
A13: SONGPA-GU, SEOUL, KOREA
A15: 3.PROCESSER OF PARTY A : | E15: 11.Remarks
A16: SEWANG VINA CO., LTD
A17: Lot B_3A_CN, Lot B_2B_CN, Bau Bang Industrial Park, | E17: * CONSIGNED TO / SHIP TO
A18: Lai Uyen Ward, Bau Bang District, | E18: PT. SADUA INDO
A19: Binh Duong province, Vietnam | E19: DUSUN GINTUNGAN, RT.19 RW. II DESA BUTUH, KEC, TEN GARAN, KAB. SEMARANG, JA WA TENGAH, INDONESIA
A21: 4.Port of loading | C21: 5.Final destination | E21: ATTN : ARYO(62-298-610-337)
A22: Cat Lai , Vietnam | C22: Jakarta, Indonesia
A23: 6.Carrier | C23: 7.Sailing on about | E23: * COUNTRY OF ORIGIN : Vietnam
A24: KMTC PENANG 1805S | C24: 43375
A25: 12.Marks and numbers of PKGS | C25: 13.Description of goods | E25: 14.Quantity | G25: 15.Net-weight | H25: 16.Gross-weight
C28: KNITTED FABRIC
B29: # 1 | C29: STYLE NO. 980/194294-001
C30: 65PCT POLYESTER + 35PCT RAYON, TR(65/35) 26'S/1 SINGLE JERSEY SOLID
C31: WIDTH : 62", WEIGHT : 170G/M2, 245G/YD
C32: BLACK
D34: LOT | E34: Bales | F34: Yards | G34: Net( KG) | H34: Gross ( KG)
D35: 10 | E35: 29 | F35: 2530 | G35: 606.51 | H35: =G35+0.1*E35 -> 609.41
D36: SUB TOTAL | E36: =SUM(E35:E35) -> 29 | F36: =SUM(F35:F35) -> 2530 | G36: =SUM(G35:G35) -> 606.51 | H36: =SUM(H35:H35) -> 609.41
B40: # 2 | C40: STYLE NO. 980/194294-001
C41: 65PCT POLYESTER + 35PCT RAYON, TR(65/35) 26'S/1 SINGLE JERSEY SOLID
C42: WIDTH : 62", WEIGHT : 170G/M2, 245G/YD
C43: FRESH BLUE
D45: LOT | E45: Bales | F45: Yards | G45: Net( KG) | H45: Gross ( KG)
D46: 1 | E46: 26 | F46: 2184 | G46: 535.3 | H46: =G46+0.1*E46 -> 537.9
D47: SUB TOTAL | E47: =SUM(E46:E46) -> 26 | F47: =SUM(F46:F46) -> 2184 | G47: =SUM(G46:G46) -> 535.3 | H47: =SUM(H46:H46) -> 537.9
C50: TOTAL | E50: =SUM(E29:E49)/2 -> 55 | F50: =SUM(F29:F49)/2 -> 4714 | G50: =SUM(G29:G49)/2 -> 1141.81 | H50: =SUM(H29:H49)/2 -> 1147.31
G58: CHUNG JEA MOON

Sheet INV(payable)_B
E1: COMMERCIAL INVOICE
A4: 1.Seller | E4: 8.No and date of invoice
A5: SEWANG TEXTILE CO.,LTD. | E5: VN-KME-18014B | J5: 43238
A6: 302 DAEHWA BLDG. 107-5, | E6: 9.NO and date of Credit
A7: SAMSUNGDONG, KANGNAMGU, | E7: LCIC800193 | J7: 43215
A8: SEOUL, 135-090, KOREA
A10: 2. Buyer/ For account and risk of messrs | E10: 10.L/C issuing bank
A11: KANMAX ENTERPRISES LTD. | E11: BANGKOK BANK PUBLIC COMPANY LIMITED HONG KONG BRANCH
A12: PALM GROVE HOUSE, P.O.BOX 438, | E12: 28 DES VOEUX ROAD, CENTRAL
A13: ROAD TOWN, TORTOLA, BRITISH VIRGIN ISLANDS
A15: 3.PROCESSER OF PARTY A : | E15: 11.Remarks
A16: SEWANG VINA CO., LTD | E16: * CONSIGNED TO / SHIP TO
A17: Lot B_3A_CN, Lot B_2B_CN, Bau Bang Industrial Park, | E17: CHUTEX INTERNATIONAL CO.,LTD.
A18: Lai Uyen Ward, Bau Bang District, | E18: NO.18 THONG NHAT ROAD, SONG THAN INDUSTRIAL ZONE II
A19: Binh Duong province, Vietnam | E19: DI AN TOWN BINH DUONG PROVINCE VIETNAM
A21: 4.Port of loading | C21: 5.Final destination
A22: Bau bang, Vietnam | C22: Binh Dương, Vietnam
A23: 6.Carrier | C23: 7.Sailing on about | E23: * COUNTRY OF ORIGIN : Vietnam
A24: TRUCK | C24: 43238
A25: 12.Marks and numbers of PKGS | C25: 13.Description of goods | E25: 14.Quantity/Unit | H25: 15.Unit-Price | J25: 16.Amount
I27: CPT.BINH DUONG
C28: KNITTED FABRIC
B29: # 1 | C29: RE: REF NO.183K0734-A-B2+ OLD NAVY LADIES KNIT FAL'18 STYLE 286498
C30: (PO NO.:KV03943)
C31: 100PCT COTTON 30S/1 SLUB JERSEY
C32: 150GM/M2 (AFTER WASHED)
C33: USABLE WIDTH: 68'' TOTAL WIDTH: 70''
C34: JUST CHILL
E35: 305 | F35: 23225 | G35: 12328.49 | H35: 1.51 | I35: /YD | J35: =ROUND(F35*H35,2) -> 35069.75
C39: TOTAL | E39: =E35 -> 305 | F39: =SUM(F29:F38) -> 23225 | G39: =G35 -> 12328.49 | J39: =J35 -> 35069.75
G41: Signed by

Sheet PCK (payable)_B
E1: PACKING LIST
A4: 1.Seller | E4: 8.No and date of invoice
A5: SEWANG TEXTILE CO.,LTD. | E5: VN-KME-18014B | I5: 43238
A6: 302 DAEHWA BLDG. 107-5, | E6: 9.NO and date of Credit
A7: SAMSUNGDONG, KANGNAMGU, | E7: LCIC800193 | I7: 43215
A8: SEOUL, 135-090, KOREA
A10: 2. Buyer/ For account and risk of messrs | E10: 10.L/C issuing bank
A11: KANMAX ENTERPRISES LTD. | E11: BANGKOK BANK PUBLIC COMPANY LIMITED HONG KONG BRANCH
A12: PALM GROVE HOUSE, P.O.BOX 438, | E12: 28 DES VOEUX ROAD, CENTRAL
A13: ROAD TOWN, TORTOLA, BRITISH VIRGIN ISLANDS
A15: 3.PROCESSER OF PARTY A : | E15: 11.Remarks
A16: SEWANG VINA CO., LTD | E16: * CONSIGNED TO / SHIP TO
A17: Lot B_3A_CN, Lot B_2B_CN, Bau Bang Industrial Park, | E17: CHUTEX INTERNATIONAL CO.,LTD.
A18: Lai Uyen Ward, Bau Bang District, | E18: NO.18 THONG NHAT ROAD, SONG THAN INDUSTRIAL ZONE II
A19: Binh Duong province, Vietnam | E19: DI AN TOWN BINH DUONG PROVINCE VIETNAM
A21: 4.Port of loading | C21: 5.Final destination
A22: Bau bang, Vietnam | C22: Binh Dương, Vietnam
A23: 6.Carrier | C23: 7.Sailing on about | E23: * COUNTRY OF ORIGIN : Vietnam
A24: TRUCK | C24: 43238
A25: 12.Marks and numbers of PKGS | C25: 13.Description of goods | E25: 14.Quantity | H25: 15.Net-weight | I25: 16.Gross-weight
C29: KNITTED FABRIC
B30: # 1 | C30: RE: REF NO.183K0734-A-B2+ OLD NAVY LADIES KNIT FAL'18 STYLE 286498
C31: (PO NO.:KV03943)
C32: 100PCT COTTON 30S/1 SLUB JERSEY
C33: 150GM/M2 (AFTER WASHED)
C34: USABLE WIDTH: 68'' TOTAL WIDTH: 70''
C35: JUST CHILL
D36: LOT | E36: Roll | F36: Yards | G36: LBS | H36: Net( KG) | I36: Gross ( KG)
D37: 12 | E37: 48 | F37: 3682 | G37: =ROUND(+H37/0.4536,2) -> 1980.38 | H37: 898.3 | I37: =E37*0.1+H37 -> 903.1
D38: 13 | E38: 48 | F38: 3728 | G38: =ROUND(+H38/0.4536,2) -> 1970.9 | H38: 894 | I38: =E38*0.1+H38 -> 898.8
D39: 15 | E39: 48 | F39: 3715 | G39: =ROUND(+H39/0.4536,2) -> 1998.68 | H39: 906.6 | I39: =E39*0.1+H39 -> 911.4
D40: 16 | E40: 43 | F40: 3374 | G40: =ROUND(+H40/0.4536,2) -> 1786.16 | H40: 810.2 | I40: =E40*0.1+H40 -> 814.5
D41: 18-5 | E41: 47 | F41: 3327 | G41: =ROUND(+H41/0.4536,2) -> 1758.6 | H41: 797.7 | I41: =E41*0.1+H41 -> 802.4
D42: 19-5 | E42: 48 | F42: 3593 | G42: =ROUND(+H42/0.4536,2) -> 1861.77 | H42: 844.5 | I42: =E42*0.1+H42 -> 849.3
D43: 20-6 | E43: 23 | F43: 1806 | G43: =ROUND(+H43/0.4536,2) -> 972 | H43: 440.9 | I43: =E43*0.1+H43 -> 443.2
D44: SUB TOTAL | E44: =SUM(E37:E43) -> 305 | F44: =SUM(F37:F43) -> 23225 | G44: =SUM(G37:G43) -> 12328.49 | H44: =SUM(H37:H43) -> 5592.2 | I44: =SUM(I37:I43) -> 5622.7
C46: TOTAL | E46: =SUM(E35:E44)/2 -> 305 | F46: =SUM(F35:F44)/2 -> 23225 | G46: =ROUND(SUM(G35:G44)/2,2) -> 12328.49 | H46: =SUM(H34:H44)/2 -> 5592.2 | I46: =SUM(I35:I44)/2 -> 5622.7
G49: Signed by

Sheet INV_A(NCV)
E1: COMMERCIAL INVOICE
A4: 1.Seller | E4: 8.No and date of invoice
A5: SEWANG TEXTILE CO.,LTD. | E5: SW-HSIN180925 | I5: 43368
A6: 302 DAEHWA BLDG. 107-5, | E6: 9.NO and date of Credit
A7: SAMSUNGDONG, KANGNAMGU, | E7: TT
A8: SEOUL, 135-090, KOREA | E8: ** NON COMMERCIAL VALUE **
A10: 2. Buyer/ For account and risk of messrs | E10: 10.L/C issuing bank
A11: HANSOLL TEXTILE LTD
A12: HANSOLL TEXTILE BLDG., 268, SONGPA-DAERO,
A13: SONGPA-GU, SEOUL, KOREA
A15: 3.PROCESSER OF PARTY A : | E15: 11.Remarks
A16: SEWANG VINA CO., LTD
A17: Lot B_3A_CN, Lot B_2B_CN, Bau Bang Industrial Park, | E17: * CONSIGNED TO / SHIP TO
A18: Lai Uyen Ward, Bau Bang District, | E18: PT. SADUA INDO
A19: Binh Duong province, Vietnam | E19: DUSUN GINTUNGAN, RT.19 RW. II DESA BUTUH, KEC, TEN GARAN, KAB. SEMARANG, JA WA TENGAH, INDONESIA
A21: 4.Port of loading | C21: 5.Final destination | E21: ATTN : ARYO(62-298-610-337)
A22: Cat Lai , Vietnam | C22: Jakarta, Indonesia
A23: 6.Carrier | C23: 7.Sailing on about | E23: * COUNTRY OF ORIGIN : Vietnam
A24: KMTC PENANG 1805S | C24: 43375
A25: 12.Marks and numbers of PKGS | C25: 13.Description of goods | E25: 14.Quantity/Unit | G25: 15.Unit-Price | I25: 16.Amount
H27: FOB.HCMC
C29: KNITTED FABRIC
B30: # 1 | C30: STYLE NO. 980/194294-001
C31: 65PCT POLYESTER + 35PCT RAYON, TR(65/35) 26'S/1 SINGLE JERSEY SOLID
C32: WIDTH : 62", WEIGHT : 170G/M2, 245G/YD
C33: BLACK
E35: 1 | F35: 52 | G35: 1.23 | H35: /YD | I35: FOC
B38: # 2 | C38: STYLE NO. 980/194294-001
C39: 65PCT POLYESTER + 35PCT RAYON, TR(65/35) 26'S/1 SINGLE JERSEY SOLID
C40: WIDTH : 62", WEIGHT : 170G/M2, 245G/YD
C41: FRESH BLUE
E43: 1 | F43: 31 | G43: 1.23 | H43: /YD | I43: FOC
A44: CONT/SEAL(1*20GP)
A45: SKLU1205840/980934
C48: TOTAL | E48: =SUM(E30:E47) -> 2 | F48: =SUM(F30:F47) -> 83 | I48: =SUM(I30:I47) -> 0
G56: CHUNG JEA MOON

Sheet PCK (NCV)
E1: PACKING LIST
A4: 1.Seller | E4: 8.No and date of invoice
A5: SEWANG TEXTILE CO.,LTD. | E5: SW-HSIN180925 | H5: 43368
A6: 302 DAEHWA BLDG. 107-5, | E6: 9.NO and date of Credit
A7: SAMSUNGDONG, KANGNAMGU, | E7: TT
A8: SEOUL, 135-090, KOREA | E8: ** NON COMMERCIAL VALUE **
A10: 2. Buyer/ For account and risk of messrs | E10: 10.L/C issuing bank
A11: HANSOLL TEXTILE LTD
A12: HANSOLL TEXTILE BLDG., 268, SONGPA-DAERO,
A13: SONGPA-GU, SEOUL, KOREA
A15: 3.PROCESSER OF PARTY A : | E15: 11.Remarks
A16: SEWANG VINA CO., LTD
A17: Lot B_3A_CN, Lot B_2B_CN, Bau Bang Industrial Park, | E17: * CONSIGNED TO / SHIP TO
A18: Lai Uyen Ward, Bau Bang District, | E18: PT. SADUA INDO
A19: Binh Duong province, Vietnam | E19: DUSUN GINTUNGAN, RT.19 RW. II DESA BUTUH, KEC, TEN GARAN, KAB. SEMARANG, JA WA TENGAH, INDONESIA
A21: 4.Port of loading | C21: 5.Final destination | E21: ATTN : ARYO(62-298-610-337)
A22: Cat Lai , Vietnam | C22: Jakarta, Indonesia
A23: 6.Carrier | C23: 7.Sailing on about | E23: * COUNTRY OF ORIGIN : Vietnam
A24: KMTC PENANG 1805S | C24: 43375 | E24: =+'INV(TTL)_A'!E24 -> 0
A25: 12.Marks and numbers of PKGS | C25: 13.Description of goods | E25: 14.Quantity | G25: 15.Net-weight | H25: 16.Gross-weight
C28: KNITTED FABRIC
B29: # 1 | C29: STYLE NO. 980/194294-001
C30: 65PCT POLYESTER + 35PCT RAYON, TR(65/35) 26'S/1 SINGLE JERSEY SOLID
C31: WIDTH : 62", WEIGHT : 170G/M2, 245G/YD
C32: BLACK
D34: LOT | E34: Bales | F34: Yards | G34: Net( KG) | H34: Gross ( KG)
D35: 10 | E35: 1 | F35: 52 | G35: 12.47 | H35: =G35+0.1*E35 -> 12.57
D36: SUB TOTAL | E36: =SUM(E35:E35) -> 1 | F36: =SUM(F35:F35) -> 52 | G36: =SUM(G35:G35) -> 12.47 | H36: =SUM(H35:H35) -> 12.57
B40: # 2 | C40: STYLE NO. 980/194294-001
C41: 65PCT POLYESTER + 35PCT RAYON, TR(65/35) 26'S/1 SINGLE JERSEY SOLID
C42: WIDTH : 62", WEIGHT : 170G/M2, 245G/YD
C43: FRESH BLUE
D45: LOT | E45: Bales | F45: Yards | G45: Net( KG) | H45: Gross ( KG)
D46: 1 | E46: 1 | F46: 31 | G46: 7.6 | H46: =G46+0.1*E46 -> 7.7
D47: SUB TOTAL | E47: =SUM(E46:E46) -> 1 | F47: =SUM(F46:F46) -> 31 | G47: =SUM(G46:G46) -> 7.6 | H47: =SUM(H46:H46) -> 7.7
C49: TOTAL | E49: =SUM(E29:E48)/2 -> 2 | F49: =SUM(F29:F48)/2 -> 83 | G49: =SUM(G29:G48)/2 -> 20.07 | H49: =SUM(H29:H48)/2 -> 20.27
G57: CHUNG JEA MOON

Sheet WN
F1: WEIGHT NOTE
A4: 1.Shipper/exporter | E4: 8.No and date of invoice
A5: SEWANG TEXTILE CO.,LTD. | E5: SW-KME-18029 | L5: 43203
A6: 302 DAEHWA BLDG. 107-5, | E6: 9.NO and date of Credit
A7: SAMSUNGDONG, KANGNAMGU, | E7: LCIC800117 | L7: 43178
A8: SEOUL, 135-090, KOREA
A10: 2.For Account and Risk of Messrs | E10: 10.L/C issuing bank
A11: KANMAX ENTERPRISES LTD. | E11: BANGKOK BANK PUBLIC COMPANY LIMITED HONG KONG BRANCH
A12: PALM GROVE HOUSE, P.O.BOX 438, | E12: 28 DES VOEUX ROAD, CENTRAL
A13: ROAD TOWN, TORTOLA, BRITISH VIRGIN ISLANDS
A14: 3.Notify party | E14: 11.Remarks
A15: CHUTEX INTERNATIONAL CO.,LTD. | E15: * CONSIGNED TO / SHIP TO
A16: NO.18 THONG NHAT ROAD, SONG THAN INDUSTRIAL ZONE II | E16: CHUTEX INTERNATIONAL CO.,LTD.
A17: DI AN TOWN BINH DUONG PROVINCE VIETNAM | E17: NO.18 THONG NHAT ROAD, SONG THAN INDUSTRIAL ZONE II
E18: DI AN TOWN BINH DUONG PROVINCE VIETNAM
E19: * B/L NO. DFS050040230
E20: * CTNR NO.
E21: HJMU1514901/156925/40HQ
A22: 4.Port of loading | C22: 5.Final destination | E22: SEGU6492191/140166/40HQ
A23: BUSAN, KOREA | C23: HOCHIMINH, VIETNAM
A24: 6.Carrier | C24: 7.Sailing on about | E24: * COUNTRY OF ORIGIN : SOUTH KOREA
A25: SKY CHALLENGE 1806S | C25: 43206 | E25: * TOTAL : 973 PACKAGES
A26: P.O.NO. | B26: REF NO. | C26: DESCRIPTION | D26: COLOR | F26: LOT | G26: ROLL NO. | H26: YDS | I26: LBS | J26: N.W. | K26: G.W. | L26: CON. NO.
A27: KV03847/290889 | B27: 183K0738-A-B4 | C27: CM30S SLUB SINGLE | D27: SIMPLY SAGE | F27: 37-12 | G27: 1 | H27: 58 | I27: =+J27/0.4536 -> 30.202821 | J27: 13.7 | K27: =+J27*1.01 -> 13.837 | L27: HJMU1514901
A28: KV03847/290889 | B28: 183K0738-A-B4 | C28: CM30S SLUB SINGLE | D28: SIMPLY SAGE | F28: 37-12 | G28: 2 | H28: 74 | I28: =+J28/0.4536 -> 38.580247 | J28: 17.5 | K28: =+J28*1.01 -> 17.675 | L28: HJMU1514901
A29: KV03847/290889 | B29: 183K0738-A-B4 | C29: CM30S SLUB SINGLE | D29: SIMPLY SAGE | F29: 37-12 | G29: 3 | H29: 72 | I29: =+J29/0.4536 -> 37.698414 | J29: 17.1 | K29: =+J29*1.01 -> 17.271 | L29: HJMU1514901
A30: KV03847/290889 | B30: 183K0738-A-B4 | C30: CM30S SLUB SINGLE | D30: SIMPLY SAGE | F30: 37-12 | G30: 4 | H30: 73 | I30: =+J30/0.4536 -> 38.139328 | J30: 17.299999 | K30: =+J30*1.01 -> 17.472999 | L30: HJMU1514901
A31: KV03847/290889 | B31: 183K0738-A-B4 | C31: CM30S SLUB SINGLE | D31: SIMPLY SAGE | F31: 37-12 | G31: 5 | H31: 71 | I31: =+J31/0.4536 -> 36.81658 | J31: 16.700001 | K31: =+J31*1.01 -> 16.867001 | L31: HJMU1514901
A32: KV03847/290889 | B32: 183K0738-A-B4 | C32: CM30S SLUB SINGLE | D32: SIMPLY SAGE | F32: 37-12 | G32: 6 | H32: 72 | I32: =+J32/0.4536 -> 37.477954 | J32: 17 | K32: =+J32*1.01 -> 17.17 | L32: HJMU1514901
A33: KV03847/290889 | B33: 183K0738-A-B4 | C33: CM30S SLUB SINGLE | D33: SIMPLY SAGE | F33: 37-12 | G33: 7 | H33: 75 | I33: =+J33/0.4536 -> 39.241621 | J33: 17.799999 | K33: =+J33*1.01 -> 17.977999 | L33: HJMU1514901
A34: KV03847/290889 | B34: 183K0738-A-B4 | C34: CM30S SLUB SINGLE | D34: SIMPLY SAGE | F34: 37-12 | G34: 8 | H34: 69 | I34: =+J34/0.4536 -> 36.155202 | J34: 16.4 | K34: =+J34*1.01 -> 16.564 | L34: HJMU1514901
A35: KV03847/290889 | B35: 183K0738-A-B4 | C35: CM30S SLUB SINGLE | D35: SIMPLY SAGE | F35: 37-12 | G35: 9 | H35: 74 | I35: =+J35/0.4536 -> 38.359788 | J35: 17.4 | K35: =+J35*1.01 -> 17.574 | L35: HJMU1514901
A36: KV03847/290889 | B36: 183K0738-A-B4 | C36: CM30S SLUB SINGLE | D36: SIMPLY SAGE | F36: 37-12 | G36: 10 | H36: 72 | I36: =+J36/0.4536 -> 37.477954 | J36: 17 | K36: =+J36*1.01 -> 17.17 | L36: HJMU1514901
A37: KV03847/290889 | B37: 183K0738-A-B4 | C37: CM30S SLUB SINGLE | D37: SIMPLY SAGE | F37: 37-12 | G37: 11 | H37: 75 | I37: =+J37/0.4536 -> 38.800706 | J37: 17.6 | K37: =+J37*1.01 -> 17.776 | L37: HJMU1514901
A38: KV03847/290889 | B38: 183K0738-A-B4 | C38: CM30S SLUB SINGLE | D38: SIMPLY SAGE | F38: 37-12 | G38: 12 | H38: 74 | I38: =+J38/0.4536 -> 38.359788 | J38: 17.4 | K38: =+J38*1.01 -> 17.574 | L38: HJMU1514901
... A68: KV03847/290889 | B68: 183K0738-A-B4 | C68: CM30S SLUB SINGLE | D68: SIMPLY SAGE | F68: 37-12 | G68: 42 | H68: 71 | I68: =+J68/0.4536 -> 36.81658 | J68: 16.700001 | K68: =+J68*1.01 -> 16.867001 | L68: HJMU1514901
D69: TOTAL | G69: 42 | H69: =SUM(H27:H68) -> 3033 | I69: =+J69/0.4536 -> 1579.3651 | J69: =SUM(J27:J68) -> 716.4 | K69: =+J69*1.01 -> 723.564 | L69: HJMU1514901
A70: KV03847/290889 | B70: 183K0738-A-B4 | C70: CM30S SLUB SINGLE | D70: SIMPLY SAGE | F70: 37-13 | G70: 1 | H70: 71 | I70: =+J70/0.4536 -> 37.477954 | J70: 17 | K70: =+J70*1.01 -> 17.17 | L70: HJMU1514901
A71: KV03847/290889 | B71: 183K0738-A-B4 | C71: CM30S SLUB SINGLE | D71: SIMPLY SAGE | F71: 37-13 | G71: 2 | H71: 68 | I71: =+J71/0.4536 -> 35.714287 | J71: 16.200001 | K71: =+J71*1.01 -> 16.362001 | L71: HJMU1514901
A72: KV03847/290889 | B72: 183K0738-A-B4 | C72: CM30S SLUB SINGLE | D72: SIMPLY SAGE | F72: 37-13 | G72: 3 | H72: 73 | I72: =+J72/0.4536 -> 38.359788 | J72: 17.4 | K72: =+J72*1.01 -> 17.574 | L72: HJMU1514901
A73: KV03847/290889 | B73: 183K0738-A-B4 | C73: CM30S SLUB SINGLE | D73: SIMPLY SAGE | F73: 37-13 | G73: 4 | H73: 72 | I73: =+J73/0.4536 -> 38.139328 | J73: 17.299999 | K73: =+J73*1.01 -> 17.472999 | L73: HJMU1514901
A74: KV03847/290889 | B74: 183K0738-A-B4 | C74: CM30S SLUB SINGLE | D74: SIMPLY SAGE | F74: 37-13 | G74: 5 | H74: 74 | I74: =+J74/0.4536 -> 39.021166 | J74: 17.700001 | K74: =+J74*1.01 -> 17.877001 | L74: HJMU1514901
A75: KV03847/290889 | B75: 183K0738-A-B4 | C75: CM30S SLUB SINGLE | D75: SIMPLY SAGE | F75: 37-13 | G75: 6 | H75: 75 | I75: =+J75/0.4536 -> 39.46208 | J75: 17.9 | K75: =+J75*1.01 -> 18.079 | L75: HJMU1514901
A76: KV03847/290889 | B76: 183K0738-A-B4 | C76: CM30S SLUB SINGLE | D76: SIMPLY SAGE | F76: 37-13 | G76: 7 | H76: 71 | I76: =+J76/0.4536 -> 37.477954 | J76: 17 | K76: =+J76*1.01 -> 17.17 | L76: HJMU1514901
A77: KV03847/290889 | B77: 183K0738-A-B4 | C77: CM30S SLUB SINGLE | D77: SIMPLY SAGE | F77: 37-13 | G77: 8 | H77: 70 | I77: =+J77/0.4536 -> 37.257495 | J77: 16.9 | K77: =+J77*1.01 -> 17.069 | L77: HJMU1514901
A78: KV03847/290889 | B78: 183K0738-A-B4 | C78: CM30S SLUB SINGLE | D78: SIMPLY SAGE | F78: 37-13 | G78: 9 | H78: 73 | I78: =+J78/0.4536 -> 38.800706 | J78: 17.6 | K78: =+J78*1.01 -> 17.776 | L78: HJMU1514901
A79: KV03847/290889 | B79: 183K0738-A-B4 | C79: CM30S SLUB SINGLE | D79: SIMPLY SAGE | F79: 37-13 | G79: 10 | H79: 73 | I79: =+J79/0.4536 -> 38.580247 | J79: 17.5 | K79: =+J79*1.01 -> 17.675 | L79: HJMU1514901
A80: KV03847/290889 | B80: 183K0738-A-B4 | C80: CM30S SLUB SINGLE | D80: SIMPLY SAGE | F80: 37-13 | G80: 11 | H80: 71 | I80: =+J80/0.4536 -> 37.698414 | J80: 17.1 | K80: =+J80*1.01 -> 17.271 | L80: HJMU1514901
A81: KV03847/290889 | B81: 183K0738-A-B4 | C81: CM30S SLUB SINGLE | D81: SIMPLY SAGE | F81: 37-13 | G81: 12 | H81: 73 | I81: =+J81/0.4536 -> 38.800706 | J81: 17.6 | K81: =+J81*1.01 -> 17.776 | L81: HJMU1514901
... A121: KV03847/290889 | B121: 183K0738-A-B4 | C121: CM30S SLUB SINGLE | D121: SIMPLY SAGE | F121: 37-13 | G121: 52 | H121: 74 | I121: =+J121/0.4536 -> 39.021166 | J121: 17.700001 | K121: =+J121*1.01 -> 17.877001 | L121: HJMU1514901
D122: TOTAL | G122: 52 | H122: =SUM(H70:H121) -> 3733 | I122: =+J122/0.4536 -> 1973.7654 | J122: =SUM(J70:J121) -> 895.3 | K122: =+J122*1.01 -> 904.253 | L122: HJMU1514901
D123: ITEM TOTAL | G123: 94 | H123: =+H69+H122 -> 6766 | I123: =+J123/0.4536 -> 3553.1305 | J123: =+J69+J122 -> 1611.7 | K123: =+J123*1.01 -> 1627.817 | L123: HJMU1514901
A124: KV03859/605657 | B124: 183K0232-D | C124: CM30S/1 SLUB SINGLE | D124: GOLLY GEE GARNET | F124: 01-7 | G124: 1 | H124: 71 | I124: =+J124/0.4536 -> 38.13933 | J124: 17.3 | K124: =+J124*1.01 -> 17.473 | L124: HJMU1514901
A125: KV03859/605657 | B125: 183K0232-D | C125: CM30S/1 SLUB SINGLE | D125: GOLLY GEE GARNET | F125: 01-7 | G125: 2 | H125: 69 | I125: =+J125/0.4536 -> 37.037037 | J125: 16.8 | K125: =+J125*1.01 -> 16.968 | L125: HJMU1514901
A126: KV03859/605657 | B126: 183K0232-D | C126: CM30S/1 SLUB SINGLE | D126: GOLLY GEE GARNET | F126: 01-7 | G126: 3 | H126: 72 | I126: =+J126/0.4536 -> 39.021164 | J126: 17.7 | K126: =+J126*1.01 -> 17.877 | L126: HJMU1514901
A127: KV03859/605657 | B127: 183K0232-D | C127: CM30S/1 SLUB SINGLE | D127: GOLLY GEE GARNET | F127: 01-7 | G127: 4 | H127: 70 | I127: =+J127/0.4536 -> 37.698413 | J127: 17.1 | K127: =+J127*1.01 -> 17.271 | L127: HJMU1514901
A128: KV03859/605657 | B128: 183K0232-D | C128: CM30S/1 SLUB SINGLE | D128: GOLLY GEE GARNET | F128: 01-7 | G128: 5 | H128: 73 | I128: =+J128/0.4536 -> 39.462081 | J128: 17.9 | K128: =+J128*1.01 -> 18.079 | L128: HJMU1514901
A129: KV03859/605657 | B129: 183K0232-D | C129: CM30S/1 SLUB SINGLE | D129: GOLLY GEE GARNET | F129: 01-7 | G129: 6 | H129: 70 | I129: =+J129/0.4536 -> 37.477954 | J129: 17 | K129: =+J129*1.01 -> 17.17 | L129: HJMU1514901
A130: KV03859/605657 | B130: 183K0232-D | C130: CM30S/1 SLUB SINGLE | D130: GOLLY GEE GARNET | F130: 01-7 | G130: 7 | H130: 75 | I130: =+J130/0.4536 -> 40.564374 | J130: 18.4 | K130: =+J130*1.01 -> 18.584 | L130: HJMU1514901
A131: KV03859/605657 | B131: 183K0232-D | C131: CM30S/1 SLUB SINGLE | D131: GOLLY GEE GARNET | F131: 01-7 | G131: 8 | H131: 75 | I131: =+J131/0.4536 -> 40.564374 | J131: 18.4 | K131: =+J131*1.01 -> 18.584 | L131: HJMU1514901
A132: KV03859/605657 | B132: 183K0232-D | C132: CM30S/1 SLUB SINGLE | D132: GOLLY GEE GARNET | F132: 01-7 | G132: 9 | H132: 71 | I132: =+J132/0.4536 -> 38.359788 | J132: 17.4 | K132: =+J132*1.01 -> 17.574 | L132: HJMU1514901
A133: KV03859/605657 | B133: 183K0232-D | C133: CM30S/1 SLUB SINGLE | D133: GOLLY GEE GARNET | F133: 01-7 | G133: 10 | H133: 71 | I133: =+J133/0.4536 -> 38.13933 | J133: 17.3 | K133: =+J133*1.01 -> 17.473 | L133: HJMU1514901
A134: KV03859/605657 | B134: 183K0232-D | C134: CM30S/1 SLUB SINGLE | D134: GOLLY GEE GARNET | F134: 01-7 | G134: 11 | H134: 70 | I134: =+J134/0.4536 -> 37.918871 | J134: 17.2 | K134: =+J134*1.01 -> 17.372 | L134: HJMU1514901
A135: KV03859/605657 | B135: 183K0232-D | C135: CM30S/1 SLUB SINGLE | D135: GOLLY GEE GARNET | F135: 01-7 | G135: 12 | H135: 70 | I135: =+J135/0.4536 -> 37.698413 | J135: 17.1 | K135: =+J135*1.01 -> 17.271 | L135: HJMU1514901
... A138: KV03859/605657 | B138: 183K0232-D | C138: CM30S/1 SLUB SINGLE | D138: GOLLY GEE GARNET | F138: 01-7 | G138: 15 | H138: 71 | I138: =+J138/0.4536 -> 38.13933 | J138: 17.3 | K138: =+J138*1.01 -> 17.473 | L138: HJMU1514901
D139: TOTAL | G139: 15 | H139: =SUM(H124:H138) -> 1069 | I139: =+J139/0.4536 -> 576.49912 | J139: =SUM(J124:J138) -> 261.5 | K139: =+J139*1.01 -> 264.115 | L139: HJMU1514901
D140: ITEM TOTAL | G140: 15 | H140: =+H139 -> 1069 | I140: =+J140/0.4536 -> 576.49912 | J140: =+J139 -> 261.5 | K140: =+J140*1.01 -> 264.115 | L140: HJMU1514901
A141: KV03850/136199 | B141: 183K0713-A~B2+ | C141: CM30S SLUB SINGLE(OLD NAVY) | D141: CC77(B12B+CREAM) | F141: 44-B2. | G141: 1 | H141: 68.8 | I141: =+J141/0.4536 -> 36.375661 | J141: 16.5 | K141: =+J141*1.01 -> 16.665 | L141: HJMU1514901
A142: KV03850/136199 | B142: 183K0713-A~B2+ | C142: CM30S SLUB SINGLE(OLD NAVY) | D142: CC77(B12B+CREAM) | F142: 44-B2. | G142: 2 | H142: 56.7 | I142: =+J142/0.4536 -> 29.982363 | J142: 13.6 | K142: =+J142*1.01 -> 13.736 | L142: HJMU1514901
A143: KV03850/136199 | B143: 183K0713-A~B2+ | C143: CM30S SLUB SINGLE(OLD NAVY) | D143: CC77(B12B+CREAM) | F143: 44-B2. | G143: 3 | H143: 70.8 | I143: =+J143/0.4536 -> 37.477954 | J143: 17 | K143: =+J143*1.01 -> 17.17 | L143: HJMU1514901
D144: TOTAL | G144: 3 | H144: 196.3 | I144: =+J144/0.4536 -> 103.83598 | J144: 47.1 | K144: =+J144*1.01 -> 47.571 | L144: HJMU1514901
A145: KV03850/136199 | B145: 183K0713-A~B2+ | C145: CM30S SLUB SINGLE(OLD NAVY) | D145: CC77(B12B+CREAM) | F145: 44-B7 | G145: 1 | H145: 75.5 | I145: =+J145/0.4536 -> 40.784832 | J145: 18.5 | K145: =+J145*1.01 -> 18.685 | L145: HJMU1514901
A146: KV03850/136199 | B146: 183K0713-A~B2+ | C146: CM30S SLUB SINGLE(OLD NAVY) | D146: CC77(B12B+CREAM) | F146: 44-B7 | G146: 2 | H146: 66.9 | I146: =+J146/0.4536 -> 36.155203 | J146: 16.4 | K146: =+J146*1.01 -> 16.564 | L146: HJMU1514901
A147: KV03850/136199 | B147: 183K0713-A~B2+ | C147: CM30S SLUB SINGLE(OLD NAVY) | D147: CC77(B12B+CREAM) | F147: 44-B7 | G147: 3 | H147: 69.8 | I147: =+J147/0.4536 -> 37.698413 | J147: 17.1 | K147: =+J147*1.01 -> 17.271 | L147: HJMU1514901
A148: KV03850/136199 | B148: 183K0713-A~B2+ | C148: CM30S SLUB SINGLE(OLD NAVY) | D148: CC77(B12B+CREAM) | F148: 44-B7 | G148: 4 | H148: 69.8 | I148: =+J148/0.4536 -> 37.698413 | J148: 17.1 | K148: =+J148*1.01 -> 17.271 | L148: HJMU1514901
A149: KV03850/136199 | B149: 183K0713-A~B2+ | C149: CM30S SLUB SINGLE(OLD NAVY) | D149: CC77(B12B+CREAM) | F149: 44-B7 | G149: 5 | H149: 69.8 | I149: =+J149/0.4536 -> 37.698413 | J149: 17.1 | K149: =+J149*1.01 -> 17.271 | L149: HJMU1514901
A150: KV03850/136199 | B150: 183K0713-A~B2+ | C150: CM30S SLUB SINGLE(OLD NAVY) | D150: CC77(B12B+CREAM) | F150: 44-B7 | G150: 6 | H150: 69.8 | I150: =+J150/0.4536 -> 37.698413 | J150: 17.1 | K150: =+J150*1.01 -> 17.271 | L150: HJMU1514901
A151: KV03850/136199 | B151: 183K0713-A~B2+ | C151: CM30S SLUB SINGLE(OLD NAVY) | D151: CC77(B12B+CREAM) | F151: 44-B7 | G151: 7 | H151: 72.2 | I151: =+J151/0.4536 -> 39.021164 | J151: 17.7 | K151: =+J151*1.01 -> 17.877 | L151: HJMU1514901
A152: KV03850/136199 | B152: 183K0713-A~B2+ | C152: CM30S SLUB SINGLE(OLD NAVY) | D152: CC77(B12B+CREAM) | F152: 44-B7 | G152: 8 | H152: 69.8 | I152: =+J152/0.4536 -> 37.698413 | J152: 17.1 | K152: =+J152*1.01 -> 17.271 | L152: HJMU1514901
A153: KV03850/136199 | B153: 183K0713-A~B2+ | C153: CM30S SLUB SINGLE(OLD NAVY) | D153: CC77(B12B+CREAM) | F153: 44-B7 | G153: 9 | H153: 70.2 | I153: =+J153/0.4536 -> 37.918871 | J153: 17.2 | K153: =+J153*1.01 -> 17.372 | L153: HJMU1514901
A154: KV03850/136199 | B154: 183K0713-A~B2+ | C154: CM30S SLUB SINGLE(OLD NAVY) | D154: CC77(B12B+CREAM) | F154: 44-B7 | G154: 10 | H154: 69.8 | I154: =+J154/0.4536 -> 37.698413 | J154: 17.1 | K154: =+J154*1.01 -> 17.271 | L154: HJMU1514901
A155: KV03850/136199 | B155: 183K0713-A~B2+ | C155: CM30S SLUB SINGLE(OLD NAVY) | D155: CC77(B12B+CREAM) | F155: 44-B7 | G155: 11 | H155: 69.8 | I155: =+J155/0.4536 -> 37.698413 | J155: 17.1 | K155: =+J155*1.01 -> 17.271 | L155: HJMU1514901
A156: KV03850/136199 | B156: 183K0713-A~B2+ | C156: CM30S SLUB SINGLE(OLD NAVY) | D156: CC77(B12B+CREAM) | F156: 44-B7 | G156: 13 | H156: 70.6 | I156: =+J156/0.4536 -> 38.13933 | J156: 17.3 | K156: =+J156*1.01 -> 17.473 | L156: HJMU1514901
... A172: KV03850/136199 | B172: 183K0713-A~B2+ | C172: CM30S SLUB SINGLE(OLD NAVY) | D172: CC77(B12B+CREAM) | F172: 44-B7 | G172: 37 | H172: 70.2 | I172: =+J172/0.4536 -> 37.918871 | J172: 17.2 | K172: =+J172*1.01 -> 17.372 | L172: HJMU1514901
D173: TOTAL | G173: 28 | H173: 1978.6 | I173: =+J173/0.4536 -> 1068.7831 | J173: 484.8 | K173: =+J173*1.01 -> 489.648 | L173: HJMU1514901
A174: KV03850/136199 | B174: 183K0713-A~B2+ | C174: CM30S SLUB SINGLE(OLD NAVY) | D174: CC77(B12B+CREAM) | F174: 44-B9 | G174: 1 | H174: 71 | I174: =+J174/0.4536 -> 37.698413 | J174: 17.1 | K174: =+J174*1.01 -> 17.271 | L174: HJMU1514901
A175: KV03850/136199 | B175: 183K0713-A~B2+ | C175: CM30S SLUB SINGLE(OLD NAVY) | D175: CC77(B12B+CREAM) | F175: 44-B9 | G175: 2 | H175: 70.1 | I175: =+J175/0.4536 -> 37.257496 | J175: 16.9 | K175: =+J175*1.01 -> 17.069 | L175: HJMU1514901
A176: KV03850/136199 | B176: 183K0713-A~B2+ | C176: CM30S SLUB SINGLE(OLD NAVY) | D176: CC77(B12B+CREAM) | F176: 44-B9 | G176: 3 | H176: 70.5 | I176: =+J176/0.4536 -> 37.477954 | J176: 17 | K176: =+J176*1.01 -> 17.17 | L176: HJMU1514901
A177: KV03850/136199 | B177: 183K0713-A~B2+ | C177: CM30S SLUB SINGLE(OLD NAVY) | D177: CC77(B12B+CREAM) | F177: 44-B9 | G177: 4 | H177: 70.5 | I177: =+J177/0.4536 -> 37.477954 | J177: 17 | K177: =+J177*1.01 -> 17.17 | L177: HJMU1514901
A178: KV03850/136199 | B178: 183K0713-A~B2+ | C178: CM30S SLUB SINGLE(OLD NAVY) | D178: CC77(B12B+CREAM) | F178: 44-B9 | G178: 5 | H178: 70.5 | I178: =+J178/0.4536 -> 37.477954 | J178: 17 | K178: =+J178*1.01 -> 17.17 | L178: HJMU1514901
A179: KV03850/136199 | B179: 183K0713-A~B2+ | C179: CM30S SLUB SINGLE(OLD NAVY) | D179: CC77(B12B+CREAM) | F179: 44-B9 | G179: 6 | H179: 70.1 | I179: =+J179/0.4536 -> 37.257496 | J179: 16.9 | K179: =+J179*1.01 -> 17.069 | L179: HJMU1514901
A180: KV03850/136199 | B180: 183K0713-A~B2+ | C180: CM30S SLUB SINGLE(OLD NAVY) | D180: CC77(B12B+CREAM) | F180: 44-B9 | G180: 7 | H180: 70.5 | I180: =+J180/0.4536 -> 37.477954 | J180: 17 | K180: =+J180*1.01 -> 17.17 | L180: HJMU1514901
A181: KV03850/136199 | B181: 183K0713-A~B2+ | C181: CM30S SLUB SINGLE(OLD NAVY) | D181: CC77(B12B+CREAM) | F181: 44-B9 | G181: 8 | H181: 72.6 | I181: =+J181/0.4536 -> 38.580247 | J181: 17.5 | K181: =+J181*1.01 -> 17.675 | L181: HJMU1514901
A182: KV03850/136199 | B182: 183K0713-A~B2+ | C182: CM30S SLUB SINGLE(OLD NAVY) | D182: CC77(B12B+CREAM) | F182: 44-B9 | G182: 9 | H182: 59.8 | I182: =+J182/0.4536 -> 31.746032 | J182: 14.4 | K182: =+J182*1.01 -> 14.544 | L182: HJMU1514901
A183: KV03850/136199 | B183: 183K0713-A~B2+ | C183: CM30S SLUB SINGLE(OLD NAVY) | D183: CC77(B12B+CREAM) | F183: 44-B9 | G183: 10 | H183: 70.1 | I183: =+J183/0.4536 -> 37.257496 | J183: 16.9 | K183: =+J183*1.01 -> 17.069 | L183: HJMU1514901
A184: KV03850/136199 | B184: 183K0713-A~B2+ | C184: CM30S SLUB SINGLE(OLD NAVY) | D184: CC77(B12B+CREAM) | F184: 44-B9 | G184: 11 | H184: 70.1 | I184: =+J184/0.4536 -> 37.257496 | J184: 16.9 | K184: =+J184*1.01 -> 17.069 | L184: HJMU1514901
A185: KV03850/136199 | B185: 183K0713-A~B2+ | C185: CM30S SLUB SINGLE(OLD NAVY) | D185: CC77(B12B+CREAM) | F185: 44-B9 | G185: 12 | H185: 71 | I185: =+J185/0.4536 -> 37.698413 | J185: 17.1 | K185: =+J185*1.01 -> 17.271 | L185: HJMU1514901
... A231: KV03850/136199 | B231: 183K0713-A~B2+ | C231: CM30S SLUB SINGLE(OLD NAVY) | D231: CC77(B12B+CREAM) | F231: 44-B9 | G231: 58 | H231: 46.1 | I231: =+J231/0.4536 -> 24.470899 | J231: 11.1 | K231: =+J231*1.01 -> 11.211 | L231: HJMU1514901
D232: TOTAL | G232: 58 | H232: 4095.1 | I232: =+J232/0.4536 -> 2175.485 | J232: 986.8 | K232: =+J232*1.01 -> 996.668 | L232: HJMU1514901
A233: KV03850/136199 | B233: 183K0713-A~B2+ | C233: CM30S/1 SLUB STP(SINGLE) | D233: CC77(B12B+CREAM) | F233: 44-B10 | G233: 31 | H233: 71.3 | I233: =+J233/0.4536 -> 37.698413 | J233: 17.1 | K233: =+J233*1.01 -> 17.271 | L233: HJMU1514901
...
